Workbook
Name Álfaberg: Skóladeildarlisti!$B$10:$G$10
Name Álfakot: Skóladeildarlisti!#REF!
Name Arnarberg: Skóladeildarlisti!$B$11:$F$11
Name Bjarkalundur: Skóladeildarlisti!$B$12:$C$12
Name Engidalsskóli: Skóladeildarlisti!$B$2:$M$2
Name Hlíðarberg: Skóladeildarlisti!$B$13:$E$13
Name Holtasel: Skóladeildarlisti!#REF!
Name Hörðuvellir: Skóladeildarlisti!$B$14:$E$14
Name Hraunkot: Skóladeildarlisti!#REF!
Name Hraunsel: Skóladeildarlisti!#REF!
Name Hraunvallaskóli: Skóladeildarlisti!$B$3:$P$3
Name Hvaleyrarskóli: Skóladeildarlisti!$B$4:$P$4
Name Krakkaberg: Skóladeildarlisti!#REF!
Name Lækjarsel: Skóladeildarlisti!#REF!
Name Lækjarskóli: Skóladeildarlisti!$B$5:$P$5
Name Leikskólinn_við_Hraunvallaskóla: Skóladeildarlisti!$B$15:$F$15
Name Leikskólinn_við_Skarðshlíðarskó: Skóladeildarlisti!$B$16:$F$16
Name Öldutúnsskóli: Skóladeildarlisti!$B$6:$P$6
Name Selið: Skóladeildarlisti!#REF!
Name Setbergsskóli: Skóladeildarlisti!$B$7:$P$7
Name Skarðshlíðarskóli: Skóladeildarlisti!$B$8:$P$8
Name Skarðssel: Skóladeildarlisti!#REF!
Name Smáralundur: Skóladeildarlisti!$B$17:$F$17
Name Stekkjarás: Skóladeildarlisti!$B$18:$I$18
Name Tjarnarás: Skóladeildarlisti!$B$19:$F$19
Name Vesturkot: Skóladeildarlisti!$B$20:$F$20
Name Víðistaðaskóli: Skóladeildarlisti!$B$9:$P$9
Name Víðivellir: Skóladeildarlisti!$B$21:$D$21

Sheet Fjöldi núna
A1: Skóli | B1: Bekkur / Deild | C1: Fjöldi í dag | D1: Starfsmenn | E1: Vikudagamynstur | F1: Gildir frá | H1: Þetta blað fyllist sjálfkrafa út þegar Office-skriftan (Matarstund_Script.ts) keyrir næst — sýnir núverandi gildandi fjöldatölur fyrir alla skóla, reiknaðar út frá Fjöldatölur-sögunni.
A2: Arnarberg | B2: Annað starfsfólk | C2: 0 | D2: 2 | E2: sama alla daga
A3: Arnarberg | B3: Hamar | C3: 22 | D3: 4 | E3: sama alla daga | F3: 46265
A4: Arnarberg | B4: Klettur | C4: 22 | D4: 4 | E4: sama alla daga | F4: 46265
A5: Arnarberg | B5: Krókur | C5: 10 | D5: 2 | E5: sama alla daga | F5: 46265
A6: Arnarberg | B6: Reitur | C6: 15 | D6: 4 | E6: sama alla daga | F6: 46265
A7: Álfaberg | B7: Askja | C7: 22 | D7: 4 | E7: Mán:22 Þri:22 Mið:22 Fim:22 Fös:22 | F7: 46268
A8: Álfaberg | B8: Búrfell | C8: 13 | D8: 4 | E8: Mán:13 Þri:13 Mið:13 Fim:13 Fös:13 | F8: 46268
A9: Álfaberg | B9: Esja | C9: 15 | D9: 4 | E9: Mán:15 Þri:15 Mið:15 Fim:15 Fös:15 | F9: 46268
A10: Álfaberg | B10: Heildarfjöldi — ekki tengt ákveðnum bekk (t.d. stjórnendur) — leggst VIÐ bekkjartölurnar | C10: 0 | D10: 3 | E10: Mán:0 Þri:0 Mið:0 Fim:0 Fös:0 | F10: 46268
A11: Álfaberg | B11: Helgafell | C11: 18 | D11: 4 | E11: Mán:18 Þri:18 Mið:18 Fim:18 Fös:18 | F11: 46268
A12: Álfaberg | B12: Keili | C12: 10 | D12: 4 | E12: Mán:10 Þri:10 Mið:10 Fim:10 Fös:10 | F12: 46268
A13: Álfakot | B13: Setja inn heildarfjölda | C13: 76 | D13: 0 | E13: Mán:76 Þri:76 Mið:76 Fim:76 Fös:76 | F13: 46267
A14: Bjarkalundur | B14: Heildarfjöldi — ekki tengt ákveðnum bekk (t.d. stjórnendur) — leggst VIÐ bekkjartölurnar | C14: 68 | D14: 24 | E14: Mán:68 Þri:68 Mið:68 Fim:68 Fös:68 | F14: 46272
... A21: Engidalsskóli | B21: 7. bekkur | C21: 34 | D21: 0 | E21: Mán:34 Þri:34 Mið:34 Fim:34 Fös:34 | F21: 46261
A22: Engidalsskóli | B22: Heildarfjöldi (fyllt út AÐEINS ef bekkja-/deildaskipting er ekki þekkt) | C22: 0 | D22: 48 | E22: sama alla daga
A23: Hlíðarberg | B23: Heildarfjöldi — ekki tengt ákveðnum bekk (t.d. stjórnendur) — leggst VIÐ bekkjartölurnar | C23: 90 | D23: 28 | E23: Mán:90 Þri:90 Mið:90 Fim:90 Fös:90 | F23: 46274
A24: Holtasel | B24: Setja inn heildarfjölda | C24: 90 | D24: 0 | E24: sama alla daga | F24: 46251
A25: Hraunkot | B25: Setja inn heildarfjölda | C25: 89 | D25: 9 | E25: Mán:89 Þri:89 Mið:89 Fim:89 Fös:89 | F25: 46266
A26: Hraunsel | C26: 137 | D26: 0 | E26: Mán:137 Þri:138 Mið:137 Fim:136 Fös:136 | F26: 46260
A27: Hraunsel | B27: Setja inn heildarfjölda | C27: 145 | D27: 20 | E27: sama alla daga | F27: 46272
A28: Hraunvallaleikskóli | B28: Heildarfjöldi — ekki tengt ákveðnum bekk (t.d. stjórnendur) — leggst VIÐ bekkjartölurnar | C28: 67 | D28: 24 | E28: sama alla daga | F28: 46251
A29: Hraunvallaskóli | B29: 1. bekkur | C29: 65 | D29: 0 | E29: sama alla daga | F29: 46251
A30: Hraunvallaskóli | B30: 2. bekkur | C30: 64 | D30: 0 | E30: sama alla daga | F30: 46251
A31: Hraunvallaskóli | B31: 3. bekkur | C31: 34 | D31: 0 | E31: sama alla daga | F31: 46251
A32: Hraunvallaskóli | B32: 4. bekkur | C32: 55 | D32: 0 | E32: sama alla daga | F32: 46251
A33: Hraunvallaskóli | B33: 5. bekkur | C33: 50 | D33: 0 | E33: sama alla daga | F33: 46251
A34: Hraunvallaskóli | B34: 6. bekkur | C34: 58 | D34: 0 | E34: sama alla daga | F34: 46251
A35: Hraunvallaskóli | B35: 7. bekkur | C35: 49 | D35: 0 | E35: sama alla daga | F35: 46251
A36: Hraunvallaskóli | B36: 8. bekkur | C36: 54 | D36: 0 | E36: sama alla daga | F36: 46251
A37: Hraunvallaskóli | B37: 9. bekkur | C37: 53 | D37: 0 | E37: sama alla daga | F37: 46251
A38: Hraunvallaskóli | B38: 10. bekkur | C38: 66 | D38: 0 | E38: sama alla daga | F38: 46251
A39: Hraunvallaskóli | B39: Heildarfjöldi (fyllt út AÐEINS ef bekkja-/deildaskipting er ekki þekkt) | C39: 0 | D39: 125 | E39: sama alla daga
A40: Hvaleyrarskóli | B40: 1. bekkur | C40: 37 | D40: 0 | E40: sama alla daga | F40: 46253
A41: Hvaleyrarskóli | B41: 2. bekkur | C41: 34 | D41: 0 | E41: sama alla daga | F41: 46253
A42: Hvaleyrarskóli | B42: 3. bekkur | C42: 26 | D42: 0 | E42: sama alla daga | F42: 46253
A43: Hvaleyrarskóli | B43: 4. bekkur | C43: 26 | D43: 0 | E43: sama alla daga | F43: 46253
A44: Hvaleyrarskóli | B44: 5. bekkur | C44: 38 | D44: 0 | E44: sama alla daga | F44: 46253
A45: Hvaleyrarskóli | B45: 6. bekkur | C45: 35 | D45: 0 | E45: sama alla daga | F45: 46253
A46: Hvaleyrarskóli | B46: 7. bekkur | C46: 31 | D46: 0 | E46: sama alla daga | F46: 46253
A47: Hvaleyrarskóli | B47: 8. bekkur | C47: 41 | D47: 0 | E47: sama alla daga | F47: 46253
A48: Hvaleyrarskóli | B48: 9. bekkur | C48: 39 | D48: 0 | E48: sama alla daga | F48: 46253
A49: Hvaleyrarskóli | B49: 10. bekkur | C49: 38 | D49: 0 | E49: sama alla daga | F49: 46253
A50: Hvaleyrarskóli | B50: Heildarfjöldi (fyllt út AÐEINS ef bekkja-/deildaskipting er ekki þekkt) | C50: 0 | D50: 83 | E50: sama alla daga
A51: Hörðuvellir | B51: Hamar | C51: 22 | D51: 4 | E51: Mán:22 Þri:22 Mið:22 Fim:22 Fös:22 | F51: 46275
A52: Hörðuvellir | B52: Hraun | C52: 19 | D52: 4 | E52: Mán:19 Þri:19 Mið:19 Fim:19 Fös:19 | F52: 46275
A53: Hörðuvellir | B53: Laut | C53: 16 | D53: 4 | E53: Mán:16 Þri:16 Mið:16 Fim:16 Fös:16 | F53: 46275
A54: Hörðuvellir | B54: Lækur | C54: 13 | D54: 4 | E54: Mán:13 Þri:13 Mið:13 Fim:13 Fös:13 | F54: 46275
A55: Hörðuvellir | B55: Starfsfólk sem borðar ekki inni á deildum | C55: 0 | D55: 5 | E55: Mán:0 Þri:0 Mið:0 Fim:0 Fös:0 | F55: 46275
A56: Krakkaberg | B56: Setja inn heildarfjölda | C56: 120 | D56: 0 | E56: sama alla daga | F56: 46251
A57: Lækjarsel | B57: Setja inn heildarfjölda | C57: 113 | D57: 0 | E57: Mán:113 Þri:113 Mið:114 Fim:113 Fös:111 | F57: 46275
A58: Lækjarskóli | B58: 1. bekkur | C58: 34 | D58: 0 | E58: sama alla daga | F58: 46253
A59: Lækjarskóli | B59: 2. bekkur | C59: 35 | D59: 0 | E59: sama alla daga | F59: 46253
A60: Lækjarskóli | B60: 3. bekkur | C60: 45 | D60: 0 | E60: sama alla daga | F60: 46253
A61: Lækjarskóli | B61: 4. bekkur | C61: 29 | D61: 0 | E61: sama alla daga | F61: 46253
A62: Lækjarskóli | B62: 5. bekkur | C62: 37 | D62: 0 | E62: sama alla daga | F62: 46253
... A67: Lækjarskóli | B67: 10. bekkur | C67: 41 | D67: 0 | E67: sama alla daga | F67: 46253
A68: Lækjarskóli | B68: Heildarfjöldi (fyllt út AÐEINS ef bekkja-/deildaskipting er ekki þekkt) | C68: 0 | D68: 91 | E68: sama alla daga
A69: Selið | B69: Setja inn heildarfjölda | C69: 152 | D69: 0 | E69: sama alla daga | F69: 46272
A70: Setbergsskóli | B70: 1. bekkur | C70: 41 | D70: 0 | E70: sama alla daga | F70: 46253
A71: Setbergsskóli | B71: 2. bekkur | C71: 41 | D71: 0 | E71: sama alla daga | F71: 46253
A72: Setbergsskóli | B72: 3. bekkur | C72: 39 | D72: 0 | E72: sama alla daga | F72: 46253
A73: Setbergsskóli | B73: 4. bekkur | C73: 39 | D73: 0 | E73: sama alla daga | F73: 46253
A74: Setbergsskóli | B74: 5. bekkur | C74: 52 | D74: 0 | E74: sama alla daga | F74: 46253
A75: Setbergsskóli | B75: 6. bekkur | C75: 38 | D75: 0 | E75: sama alla daga | F75: 46253
A76: Setbergsskóli | B76: 7. bekkur | C76: 40 | D76: 0 | E76: sama alla daga | F76: 46253
A77: Setbergsskóli | B77: 8. bekkur | C77: 38 | D77: 0 | E77: sama alla daga | F77: 46253
A78: Setbergsskóli | B78: 9. bekkur | C78: 34 | D78: 0 | E78: sama alla daga | F78: 46253
A79: Setbergsskóli | B79: 10. bekkur | C79: 44 | D79: 0 | E79: sama alla daga | F79: 46253
A80: Setbergsskóli | B80: Heildarfjöldi (fyllt út AÐEINS ef bekkja-/deildaskipting er ekki þekkt) | C80: 0 | D80: 85 | E80: sama alla daga
A81: Skarðshlíðarleikskóli | B81: Hóll | C81: 20 | D81: 5 | E81: sama alla daga | F81: 46252
A82: Skarðshlíðarleikskóli | B82: Hraun | C82: 25 | D82: 5 | E82: sama alla daga | F82: 46252
A83: Skarðshlíðarleikskóli | B83: Laut | C83: 15 | D83: 5 | E83: sama alla daga | F83: 46252
A84: Skarðshlíðarleikskóli | B84: Lyng | C84: 17 | D84: 5 | E84: sama alla daga | F84: 46252
A85: Skarðshlíðarleikskóli | B85: Sérkennarar | C85: 0 | D85: 2 | E85: sama alla daga
A86: Skarðshlíðarleikskóli | B86: Stjórnendur | C86: 0 | D86: 2 | E86: sama alla daga
A87: Skarðshlíðarskóli | B87: 1. bekkur | C87: 45 | D87: 0 | E87: sama alla daga | F87: 46253
A88: Skarðshlíðarskóli | B88: 2. bekkur | C88: 57 | D88: 0 | E88: sama alla daga | F88: 46253
A89: Skarðshlíðarskóli | B89: 3. bekkur | C89: 59 | D89: 0 | E89: sama alla daga | F89: 46253
A90: Skarðshlíðarskóli | B90: 4. bekkur | C90: 63 | D90: 0 | E90: sama alla daga | F90: 46253
A91: Skarðshlíðarskóli | B91: 5. bekkur | C91: 65 | D91: 0 | E91: sama alla daga | F91: 46253
A92: Skarðshlíðarskóli | B92: 6. bekkur | C92: 57 | D92: 0 | E92: sama alla daga | F92: 46253
A93: Skarðshlíðarskóli | B93: 7. bekkur | C93: 56 | D93: 0 | E93: sama alla daga | F93: 46253
A94: Skarðshlíðarskóli | B94: 8. bekkur | C94: 39 | D94: 0 | E94: sama alla daga | F94: 46253
A95: Skarðshlíðarskóli | B95: 9. bekkur | C95: 53 | D95: 0 | E95: sama alla daga | F95: 46253
A96: Skarðshlíðarskóli | B96: 10. bekkur | C96: 26 | D96: 0 | E96: sama alla daga | F96: 46253
A97: Skarðshlíðarskóli | B97: Heildarfjöldi (fyllt út AÐEINS ef bekkja-/deildaskipting er ekki þekkt) | C97: 0 | D97: 100 | E97: sama alla daga
A98: Skarðssel | B98: Setja inn heildarfjölda | C98: 161 | D98: 0 | E98: Mán:161 Þri:164 Mið:159 Fim:164 Fös:158 | F98: 46266
A99: Smáralundur | B99: Brekka | C99: 17 | D99: 4 | E99: sama alla daga | F99: 46251
A100: Smáralundur | B100: Heildarfjöldi — ekki tengt ákveðnum bekk (t.d. stjórnendur) — leggst VIÐ bekkjartölurnar | C100: 0 | D100: 3 | E100: sama alla daga | F100: 46250
A101: Smáralundur | B101: Holt | C101: 20 | D101: 4 | E101: sama alla daga | F101: 46251
A102: Smáralundur | B102: Lundur | C102: 16 | D102: 5 | E102: sama alla daga | F102: 46251
A103: Smáralundur | B103: Þúfa | C103: 14 | D103: 5 | E103: sama alla daga | F103: 46251
A104: Stekkjarás | B104: Heildarfjöldi — ekki tengt ákveðnum bekk (t.d. stjórnendur) — leggst VIÐ bekkjartölurnar | C104: 144 | D104: 45 | E104: sama alla daga | F104: 46265
A105: Tjarnarás | B105: Glaðheimar | C105: 24 | D105: 5 | E105: sama alla daga | F105: 46251
A106: Tjarnarás | B106: Heildarfjöldi — ekki tengt ákveðnum bekk (t.d. stjórnendur) — leggst VIÐ bekkjartölurnar | C106: 26 | D106: 11 | E106: sama alla daga | F106: 46272
A107: Tjarnarás | B107: Kærleiksheimar | C107: 24 | D107: 4 | E107: sama alla daga | F107: 46251
A108: Tjarnarás | B108: Ljósheimar | C108: 15 | D108: 4 | E108: sama alla daga | F108: 46251
A109: Tjarnarás | B109: Stjörnuheimar | C109: 14 | D109: 4 | E109: sama alla daga | F109: 46251
... A124: Víðistaðaskóli | B124: 10. bekkur | C124: 80 | D124: 0 | E124: sama alla daga | F124: 46274
...

Sheet Vöruskrá
A1: VÖRUSKRÁ – HRÁEFNI OG INNIHALDSEFNI | U1: Soðið-hlutfall (verðlagning)
A2: Heiti vöru | B2: Leitarnafn (dropdown) | C2: Framleiðandi / Byrgi | D2: Vörúnúmer | E2: Vöruflokkur | F2: Innihaldslýsing | G2: Ofnæmisvaldar | H2: Fyrirvari | I2: Hlekkur á gagnablað | J2: Orka (kcal/100g) | K2: Fita (g/100g) | L2: Mettuð fita (g/100g) | M2: Kolvetni (g/100g) | N2: Sykur (g/100g) | O2: Prótein (g/100g) | P2: Salt (g/100g) | Q2: Trefjar (g/100g) | R2: Kostnaður (kr/kg) | S2: Athugasemdir | U2: 1.5
A3: Ömmu skonsur heilar | B3: Ömmu skonsur heilar | C3: Gæðabakstur / Ömmubakstur ehf. | D3: 121 | E3: Brauð og bakkelsi | F3: Vatn, **hveiti**, **haframjöl**, repjuolía, sykur, **heilhveiti**, **egg**, **mysuduft**, pálmaolía, lyftiefni (E450, E500), salt, maltað **hveiti**, mjölmeðhöndlunarefni (E300), rotvarnarefni (E282), sykur, bindiefni (E322 úr sólblómum, E471), dextrósi, bragðefni, rotvarnarefni (E211), sýrustillir (E330), vanillubragðefni, kókosolía, litarefni (E150c, E150a), kekkjarvarnarefni (E535) | G3: Glúten (hveiti, hafrar), egg, mjólk | H3: Gæti innihaldið snefil af sesam. | I3: https://gaedabakstur.is/vara/ommuskonsur-heilar-10stk-i-pakka/ | J3: 260 | K3: 12 | L3: 1.3 | M3: 31 | N3: 10 | O3: 5.3 | P3: 1 | Q3: 2.3 | R3: 600 | S3: 160 g/stk. Geymsluþol 5 dagar við stofuhita. | U3: Verðlagningarhlutfall – samþykkt. Tengt: R249, R288, R345. R54 og R239 eru ótengd (sjá skýringar í þeim hólfum).
A4: Bananaskonsur | B4: Bananaskonsur | C4: Gæðabakstur / Ömmubakstur ehf. | D4: 122 | E4: Brauð og bakkelsi | F4: Hrísmjólk (vatn, hrísgrjón, sólblómaolía, kalsíum, maltextrakt, salt, bindiefni E418, vítamín B12, D2, sýrustillir E340), **hveiti**, vatn, sykur, banani, repjuolía, maltað **hveiti**, mjölmeðhöndlunarefni (E300), lyftiefni (E450, E500), salt, vanillubragðefni, litarefni (E150c), kekkjarvarnarefni (E535) | G4: Glúten (hveiti) | H4: Gæti innihaldið snefil af sesam, mjólk og eggjum. | I4: https://gaedabakstur.is/vara/bananaskonsur/ | J4: 237 | K4: 4.3 | L4: 0.3 | M4: 44 | N4: 16 | O4: 4.4 | P4: 0.4 | Q4: 1.5 | R4: 600 | S4: 75 g/stk, 10 stk/pakki. Frystivara (-18°C) 3 mánuðir.
A5: Sólkjarnabrauð plötubrauð | B5: Sólkjarnabrauð plötubrauð | C5: Gæðabakstur / Ömmubakstur ehf. | D5: 730 | E5: Brauð og bakkelsi | F5: **Hveiti**, vatn, sólkjarnafræ, **rúgmjöl**, hörfræ, maltað **hveiti**, salt, maltað **bygg**, mjölmeðhöndlunarefni (E300), ger, malt extrakt (úr **byggi**), súrdeigsduft úr hveiti (**hveiti**, gerlar), dextrósi, **hveitiglúten**, bindiefni (E472e, E491), ensím, kekkjarvarnarefni (E535) | G5: Glúten (hveiti, rúgur, bygg) | H5: Gæti innihaldið snefil af sesamfræjum | I5: https://drive.google.com/file/d/1p07uLGGtQjJr-CEfMOPWvz0nx16AzC1e/view?usp=sharing | J5: 311 | K5: 10.8 | L5: 1.3 | M5: 40.3 | N5: 1.7 | O5: 10.5 | P5: 1.1 | Q5: 4.7 | R5: 600 | S5: 500 g. Geymsluþol 2 dagar eftir framleiðslu.
A6: Beyglur fínar KS(48) | B6: Beyglur fínar KS(48) | C6: Myllan | D6: 3413 | E6: Brauð og bakkelsi | F6: **Hveiti**, vatn, sykur, maltað mjöl (**bygg**, **hveiti**), salt, ger, óvirkt þurrger, ýruefni (E472e), repjuolía, mjölmeðhöndlunarefni (E300), ensím. | G6: Glúten (hveiti, bygg) | H6: Framleitt á svæði þar sem unnið er með sesamfræ, mjólk, egg, lúpínu, soja | I6: https://www.myllan.is/is/vorulinur/frosin-pokkud-vara/beyglur-finar | J6: 257 | K6: 0.9 | L6: 0.2 | M6: 51 | N6: 2.6 | O6: 9.4 | P6: 1.5 | Q6: 2.4 | R6: 600 | S6: 95 g/stk, 48 stk í söluein. Frystivara -18°C, geymsluþol 270 dagar.
A7: Heilkornasamlokubrauð stórt | B7: Heilkornasamlokubrauð stórt | C7: Myllan | D7: 1036 | E7: Brauð og bakkelsi | F7: Vatn, heilkorna **heilhveiti** 17%, heilkorna **rúgmjöl** 17%, **hveiti**, **hveitiglúten**, **hveitiflögur**, **rúgmjöl**, þurrkað súrdeig (**rúgur**, súrdeigsgerlar), **hveitikurl**, ger, maltextrakt (**bygg**), repjuolía, salt, þykkingarefni (E415), sýrustillir (E262), ýruefni (E471, E472e), þurrkað súrdeig (**hveiti**, súrdeigsgerlar), mjölmeðhöndlunarefni (E300) | G7: Glúten (hveiti, rúgur, bygg) | H7: Framleitt á svæði þar sem unnið er með sesamfræ, egg, mjólk og lúpínu | I7: https://www.myllan.is/is/vorulinur/samlokubraud/heilkornasamlokubraud-stort | J7: 244 | K7: 2.9 | L7: 0.6 | M7: 37 | N7: 1.6 | O7: 14 | P7: 1 | Q7: 6.6 | R7: 600 | S7: 1000 g. Geymsluþol 5 dagar. 49% af þurrefnum heilkorn.
A8: Heimilisbrauð 1/1 | B8: Heimilisbrauð 1/1 | C8: Myllan | D8: 1023 | E8: Brauð og bakkelsi | F8: **Hveiti**, vatn, **hveitikurl**, repjuolía, ger, salt, **hveititrefjar**, mjölmeðhöndlunarefni (E300), ýruefni (E481) | G8: Glúten (hveiti) | H8: Framleitt á svæði þar sem unnið er með sesamfræ, mjólk, egg og lúpínu | I8: https://www.myllan.is/is/vorulinur/samlokubraud/heimilisbraud-heilt | J8: 250 | K8: 2.7 | L8: 0.4 | M8: 45 | N8: 0.3 | O8: 9 | P8: 1.4 | Q8: 3.1 | R8: 531 | S8: 770 g. Geymsluþol 5 dagar. Vegan, trefjagjafi.
A9: Lífskornabrauð m/ tröllahöfrum og chia | B9: Lífskornabrauð m/ tröllahöfrum og chia | C9: Myllan | D9: 1063 | E9: Brauð og bakkelsi | F9: Vatn, **tröllahafrar** 21%, heilkorna **heilhveiti** 16%, **hveiti**, **hveitiglúten**, **rúgmjöl**, þurrkað súrdeig (**rúgur**, súrdeigsgerlar), **hveitikurl**, ger, chia fræ 1% (Salvia hispanica), maltextrakt (**bygg**), repjuolía, joðbætt salt, þykkingarefni (E415), sýrustillir (E262), ýruefni (E471, E472e), mjölmeðhöndlunarefni (E300) | G9: Glúten (hafrar, hveiti, rúgur, bygg) | H9: Framleitt á svæði þar sem unnið er með sesamfræ, egg, mjólk og lúpínu | I9: https://www.myllan.is/is/vorulinur/vegan-vorur/lifskorn-trollahafrar-chiafrae | J9: 241 | K9: 4.3 | L9: 0.8 | M9: 33 | N9: 1.2 | O9: 14 | P9: 0.9 | Q9: 6.8 | R9: 600 | S9: 450 g. Geymsluþol 6 dagar. Vegan, trefjaríkt.
A10: Hvítlauksbrauð / baguette | B10: Hvítlauksbrauð / baguette | C10: Myllan | D10: 4280 | E10: Brauð og bakkelsi | F10: Mjöl (**hveiti**, maltað **hveiti**), vatn, smjör (**mjólk**), jurtafita (pálma), jurtaolía (repju), joðbætt salt, ger, hvítlaukur 0,6%, laukduft, ýruefni (E472e, E471, sólblómalesitín), sýrustillir (E341, E450, E330), óvirkt ger, steinselja, salt, þykkingarefni (E412), bragðefni, þráavarnarefni (E300), ensím (alfaamýlasi, xýlanasi) | G10: Glúten (hveiti), mjólk | H10: Getur innihaldið snefil af eggjum, soja, sinnepi og sesamfræjum. | I10: https://drive.google.com/file/d/1ISY9dqVNVBuKMul2k8e0kwwb7vSrJhlW/view?usp=sharing | J10: 305 | K10: 14 | L10: 6.4 | M10: 37 | N10: 0.8 | O10: 6.6 | P10: 1.5 | Q10: 1.9 | R10: 797 | S10: 175 g/stk. 36 stk í söluein. Frystivara -18°C, geymsluþol 548 dagar. Næringargildi miðast við forbakaða/óbakaða vöru.
A11: Dökkt súrdeigsbrauð (Skanörgrova) | B11: Dökkt súrdeigsbrauð (Skanörgrova) | C11: Pågen/ Ójk | D11: 1003 | E11: Brauð og bakkelsi | F11: Vatn, **hveiti**mjöl, súrdeig úr **hveiti**korni (13%), heilkorna**hveiti**mjöl, dinkel**hveiti**mjöl, muldir heilkornakjarnar úr dinkel**hveiti**, **hafra**grjón, skolað heilkorna**hafra**mjöl, **hveiti**glúten, heilkorna**rúg**mjöl, heilkorna durum**hveiti**mjöl, **hafra**trefjar, kaldpressuð repjuolía (1%), **hveiti**kímar, gul hörfræ, sykur (eingöngu sem næring fyrir ger), ger, malt úr **byggi** og **hveiti**, salt. | G11: Glúten (hveiti, rúgur, hafrar, bygg) | I11: https://drive.google.com/file/d/1_xC3btJzq-zmdaQHqlJ0_0EY7KwFaCqs/view?usp=sharing | J11: 308 | K11: 7.8 | L11: 0.8 | M11: 48 | N11: 9.1 | O11: 10 | P11: 1.4 | Q11: 6 | R11: 600
A12: Ljóst súrdeigsbrauð (LantGoda Surdegsbröd) | B12: Ljóst súrdeigsbrauð (LantGoda Surdegsbröd) | C12: Pågen/ Ójk | D12: 1004 | E12: Brauð og bakkelsi | F12: Vatn, **hveiti**mjöl, súrdeig úr **hveiti** (13%), heilkorna**hveiti**mjöl, dinkel**hveiti**mjöl, muldir heilkornakjarnar úr dinkel**hveiti**, **hafra**grjón, skolað heilkorna**hafra**mjöl, **hveiti**glúten, heilkorna**rúg**mjöl, heilkorna durum**hveiti**mjöl, **hafra**trefjar, kaldpressuð repjuolía (1%), **hveiti**kímar, gul hörfræ, sykur (eingöngu sem næring fyrir ger), ger, malt úr **byggi** og **hveiti**, salt. | G12: Glúten (hveiti, rúg, hafrar, bygg) | I12: https://drive.google.com/file/d/1aObopp1C2qlx3QieZ3phPb3MzLNGDVZz/view?usp=sharing | J12: 262 | K12: 3 | L12: 0.4 | M12: 45 | N12: 4.1 | O12: 11 | P12: 0.9 | Q12: 5 | R12: 600 | S12: 650 g. Frystivara 180 dagar, kælivara 7 dagar þiðnuð.
A13: Hrökkbrauð – Spelt (Burger crispbread) | B13: Hrökkbrauð – Spelt (Burger crispbread) | C13: Burger Knäcke/ Nathan | E13: Brauð og bakkelsi | F13: Heilkorna**rúg**mjöl, speltflögur (**hveiti**), heilkorna**spelt**mjöl (**hveiti**), salt. | G13: Glúten (Hveiti, rúgur, spelt) | H13: Getur innihaldið snefil af sesam, mjólk og öðrum glútentegundum | I13: https://drive.google.com/file/d/1vwvU9xL9chLkyyy34xePImiUaHAxA66A/view?usp=sharing | J13: 324 | K13: 1.6 | L13: 0.3 | M13: 59 | N13: 1.8 | O13: 8.6 | P13: 1.3 | Q13: 21 | R13: 600 | S13: 250 g. Þurrgeymist 12 mánuðir.
A14: Heilhveitikex (HAUST Graham biscuit) | B14: Heilhveitikex (HAUST Graham biscuit) | C14: Continental Bakeries North Europe AB | D14: 307242 | E14: Brauð og bakkelsi | F14: **Hveiti**mjöl, heilkorna **hveiti**mjöl 30%, sykur, jurtafita (pálma), lyftiefni (ammoníumkarbónöt, natríumkarbónöt), salt, bragðefni. | G14: Glúten (hveiti) | H14: Getur innihaldið snefil af hnetum og sesam | I14: https://docs.google.com/document/d/1hSm-4pt3r15YYOeuqlWMbkkVgdKc8cwt0qPlCRs1ssM/edit?usp=sharingex.pdf | J14: 478 | K14: 20.8 | L14: 10.5 | M14: 62.4 | N14: 22.7 | O14: 8 | P14: 1.1 | R14: 800 | S14: 225 g. Þurrgeymist 12 mánuðir. Upprunaland: Þýskaland.
A15: Horn / Mini croissant 25g | B15: Horn / Mini croissant 25g | C15: Boulangerie Neuhauser SA | D15: 401262 | E15: Brauð og bakkelsi | F15: **Hveiti**mjöl, vatn, **smjör** 18%, ger, sykur, **egg**, salt, **hveiti**glúten, maltað **hveiti**mjöl, óvirkt ger, mjölmeðhöndlunarefni (askorbínsýra E300), ensím. | G15: Glúten (hveiti), mjólk, egg | I15: https://drive.google.com/file/d/1DNHhTRSDQjq03Ewnj0fn_Ex30mAnbK52/view?usp=sharing | J15: 308 | K15: 15 | L15: 9.2 | M15: 36 | N15: 5.4 | O15: 6.8 | P15: 1 | Q15: 1.4 | R15: 600 | S15: 25 g/stk. 40 stk/poki. Frystivara -18°C. Bakið 10–12 mín við 165°C.
A16: Arna skyr vanillu | B16: Arna skyr vanillu | C16: Arna | E16: Mjólkurvörur | F16: **Mjólk**, sykur (5.0%), maíssterkja, vanilluþykkni (0,1%), vanillukorn, sítrónusafi, skyrgerlar, laktasi. | G16: Mjólk (laktósalaus) | I16: https://drive.google.com/file/d/1yzNdxeJqQSbLVXSF15Oeij4m2PUBv2GA/view?usp=sharing | J16: 78 | K16: 0.3 | L16: 0.2 | M16: 7.9 | N16: 7.9 | O16: 11 | P16: 0.1 | R16: 933 | S16: 1 kg. Kælivara 0–4°C. Þar af viðbættur sykur 5,0 g.
A17: Heimilis grjónagrautur | B17: Heimilis grjónagrautur | C17: Matarstræti | D17: 400208 | E17: Grautar og morgunmatur | F17: **Mjólk**, hrísgrjón(12%), sykur, salt. | G17: Mjólk | I17: https://drive.google.com/file/d/1Q4ZfVecv6vttdWG8fU0WA-1aeEo59cEB/view?usp=sharing | J17: 91 | K17: 3 | L17: 1.6 | M17: 14 | N17: 4.6 | O17: 3 | P17: 0.5 | R17: 350 | S17: 2 kg. Kælivara. Geymsluþol 20 dagar.
A18: Oatly iKaffe haframjólk 1lt | B18: Oatly iKaffe haframjólk 1lt | R18: 407
A19: Oatly iMat Fraiche (sýrður hafrarjómi) | B19: Oatly iMat Fraiche (sýrður hafrarjómi) | C19: Oatly/ Innnes | D19: 61529 | E19: Plöntubasað | F19: Gerjaður hafragrunnur (vatn, **hafrar** 10%), repjuolía, fullhertar jurtaolíur (kókos, repju), kartöflusterkja, ýruefni (E472e), bindiefni (E407), sýrur (eplasýra, mjólkursýra), kalsíumkarbónat, kalsíumfosföt. | G19: Glúten (hafrar) | I19: https://docs.google.com/document/d/1vtp7UoMhU2kAQ80lddgVvUUhOoVTIYypmLZ4XRd5l3E/edit?usp=sharing | J19: 177 | K19: 15 | L19: 6.4 | M19: 9.1 | N19: 4.1 | O19: 1 | P19: 0 | Q19: 1 | R19: 1800 | S19: 200 ml. Kælivara. Geymsluþol 158 dagar.
A20: Debic Vegan Top (jurtarjómi) | B20: Debic Vegan Top (jurtarjómi) | C20: FrieslandCampina/Nathan | D20: 1180281 | E20: Plöntubasað | F20: Vatn (64%), jurtaolía (29%) (pálmakjarni, pálmi), þurrkað glúkósasíróp (5%), umbreytt sterkja, salt, bindiefni (E339, gellangúmmí), ýruefni (lesitín, E435, E472b), litarefni (karótín), náttúruleg bragðefni. | G20: Engir skráðir | I20: https://drive.google.com/file/d/1VkCiTqPDw5l0voO-OiMPXkFvU-St0eZv/view?usp=sharing | J20: 295 | K20: 30 | L20: 25 | M20: 6.2 | O20: 0 | P20: 0.1 | Q20: 0 | R20: 1800 | S20: EAN: 8713300128979. 5 L Bag-in-Box. Kælivara 2–7°C. Geymsluþol 183 dagar. Eftir opnun: nota innan 4 daga.
A21: Ali brauðskinka 62% | B21: Ali brauðskinka 62% | C21: Ali | E21: Kjöt / Alifuglar | F21: Grísakjöt (62%), vatn, kartöflumjöl, **sojaprótein**, salt, þrúgusykur, bindiefni (E451), þráavarnarefni (E301, E330), gerextrakt, þykkingarefni (E410, E407), bragðefni, rotvarnarefni (E270, E250) | G21: Soja | I21: https://docs.google.com/document/d/1tYCZIN-9wdHVdNDDkGYzBt6KHJktVy-txKVoBoCKeKQ/edit?usp=sharing | J21: 122 | K21: 5.9 | L21: 2.4 | M21: 3.6 | N21: 1.6 | O21: 13.4 | P21: 2.7 | R21: 1836 | S21: Kælivara 0–4°C. Vacumpakkar, geymsluþol 21 dagur.
A22: Ali kjúklingapylsur | B22: Ali kjúklingapylsur | C22: Ali | E22: Kjöt / Alifuglar | F22: Kjúklingakjöt 58%, kjúklingaskinn 24%, vatn, salt, krydd (**sinnep**, hvítlaukur), gerextrakt, bragðefni, rotvarnarefni (E250) | G22: Sinnep | I22: https://drive.google.com/file/d/1YjhRYrqRfXtv7LqVwi1Ut5s0ZlUPbbqk/view?usp=sharing | J22: 173 | K22: 13.4 | L22: 4.8 | M22: 0.3 | N22: 0.3 | O22: 13.7 | P22: 2.8 | R22: 1900 | S22: Kælivara 0–4°C. Geymsluþol 21 dagur.
A23: Kjúklingabollur 5 kg | B23: Kjúklingabollur 5 kg | C23: Matfugl ehf. | D23: 174170 | E23: Kjöt / Alifuglar | F23: Kjúklingaleggjakjöt, kartöflusterkja, vatn, **soja**prótein, salt, þurrkað grænmeti (laukur, hvítlaukur, paprika), bragðefni (**soja**), krydd (**sinnep**), þrúgusykur, **hveiti**prótein, gerextrakt, litarefni (E160c), krydd, ger, repjuolía, fosfat (E450) | G23: Glúten (hveiti), soja, sinnep | I23: https://drive.google.com/file/d/1YThV-MnjJNGCpLCeYQojXy09zGYF6MrY/view?usp=sharing | J23: 177 | K23: 9 | L23: 1.8 | M23: 7 | N23: 0.9 | O23: 17 | P23: 1.8 | R23: 1900 | S23: Frystivara -18°C, geymsluþol 10 mánuðir. Kælivara 0–4°C, 20 dagar.
A24: Kjúklingabollur án ofnæmisvalda | B24: Kjúklingabollur án ofnæmisvalda | C24: Matfugl ehf. | D24: 174171 | E24: Kjöt / Alifuglar | F24: Kjúklingakjöt (90%), vatn, kartöflusterkja, salt, baunamjöl, sykur, krydd, bindiefni (E450), kryddjurtir, karrý (turmerik, kóríander, fenugreek, dillfræ, negull, chili), broddkúmen, laukur, hvítlaukur, kóríander, bragðefni, cayennepipar, svartur pipar, engifer, kanill, kekkjavarnarefni (E551), litarefni paprika (E 160c), negull, sýra (E330), repjuolía. | R24: 1400
A25: Kjúklingaborgarar í cornflakes | B25: Kjúklingaborgarar í cornflakes | C25: Matfugl ehf. | D25: 174311 / 174312 / 174350 | E25: Kjöt / Alifuglar | F25: Kjötfylling (79%) (Kjúklingakjöt (83% af fyllingu), vatn, **soja**prótein, salt, krydd, gerþykkni, laukur), Brauðhjúpur (**hveiti**, maís, vatn, sykur, salt, maltað **bygg** extrakt), repjuolía. | G25: Glúten (hveiti, bygg), soja | I25: https://drive.google.com/file/d/1eikdCgUrXnNjx_B4w2fUH_3E5nIrr0Kz/view?usp=sharing | J25: 237 | K25: 13 | L25: 4.7 | M25: 14 | N25: 1.1 | O25: 16 | P25: 1.5 | R25: 1900 | S25: Frystivara -18°C, geymsluþol 10 mánuðir. Kælivara 0–4°C, 20 dagar.
A26: Kjúklinga lærakjöt Rodizio | B26: Kjúklinga lærakjöt Rodizio | C26: Matfugl ehf. | D26: 171481 / 171482 / 171483 / 171484 / 171498 / 171499 | E26: Kjöt / Alifuglar | F26: Úrbeinuð skinnlaus kjúklingalæri (83%), vatn, salt, jurtaolia (repju og palma olia), sykur, mango chutney, ávaxtaþykkni, sýrustillir (E500), krydd reykbragðefni, rotvarnarefni (E262), þráavarnarefni (E320) | I26: https://drive.google.com/file/d/111MXMHumSNCo1SX0OgN5_iw4ol6nI6Y0/view?usp=sharing | J26: 206 | K26: 10 | L26: 1.8 | M26: 4 | N26: 3.3 | O26: 25 | P26: 3.2 | R26: 2400 | S26: Kælivara 0–4°C, 21 dagur. Frystivara -18°C, 8 mánuðir.
A27: Kjúklingalærkjöt, hráir strimlar | B27: Kjúklingalærkjöt, hráir strimlar | C27: Innnes Flevo | D27: 309924 | E27: Kjöt / Alifuglar | F27: Úrbeinuð, skinnlaus kjúklingalæri | I27: https://innnes.is/media/r4em233a/309924_rawstripes_71467_309924.pdf | J27: 153 | K27: 8.5 | L27: 2.4 | M27: 1.4 | N27: 0.2 | O27: 17.5 | P27: 0.4 | Q27: 0.5 | R27: 1734
A28: Kjúklingalæri úrbeinuð | B28: Kjúklingalæri úrbeinuð | C28: Danpo | D28: 844014 | E28: Kjöt / Alifuglar | F28: Úrbeinuð og skinnlaus kjúklingalæri 80%, vatn 19%, salt, sykur, þráavarnarefni (E331, E301), sýrustillir (E262). | I28: https://drive.google.com/file/d/1GO4O3alIJnHNWfA6fdAD_SVmAdbBm5wZ/view?usp=sharing | J28: 137 | K28: 9 | L28: 2.3 | O28: 14 | P28: 0.8 | R28: 2400 | S28: 4 x 2500 g. Frystivara -18°C, geymsluþol 12 mánuðir. Halal viðurkennt. <0,5 g kolvetni og sykur.
A29: NOL Kindakæfa 200g | B29: NOL Kindakæfa 200g | C29: Kjarnafæði Norðlenska hf. | D29: 70519 | E29: Kjöt / Alifuglar | F29: Lambakjöt 80%, kjötsoð, laukduft, salt, pipar. | I29: https://docs.google.com/document/d/1LXzsuB69-IC_oRxF1lHfWTuKdnHk4OhCG33dUGHUGSs/edit?usp=sharing | J29: 264 | K29: 24 | L29: 12 | M29: 1 | N29: 0 | O29: 11 | P29: 2.1 | Q29: 0 | R29: 1800 | S29: Kælivara 0–4°C. Geymsluþol 14 dagar. Soðin vara. Upprunaland: Ísland.
A30: Lifrarpylsa án mjólkur, soðin | B30: Lifrarpylsa án mjólkur, soðin | C30: Kjarnafæði Norðlenska hf. | D30: 59804 | E30: Kjöt / Alifuglar | F30: Lambalifur 32%, lambamör, **rúgmjöl**, **haframjöl**, vatn, salt. | G30: Glúten (rúgur, hafrar) | I30: https://docs.google.com/document/d/1dqgFZjSbMdctBpuTsZ86-uVkLNdvEtPTC6Kh8455--Y/edit?usp=sharing | J30: 401 | K30: 32.7 | L30: 16.6 | M30: 15.7 | N30: 0.3 | O30: 10.3 | P30: 1 | Q30: 3.8 | R30: 1800 | S30: 1 kg. Kælivara 0–4°C. Geymsluþol 35 dagar. Upprunaland: Ísland.
A31: Ýsa í raspi - Hafið | B31: Ýsa í raspi - Hafið | C31: Hafið fiskverslun | D31: 1164 | E31: Fiskur | F31: **Ýsa**, raspur (**hveiti**, vatn, ger, salt, litarefni (E100, E160b)), hjúpur (**hveiti**glúten, salt, umbreytt **hveiti**sterkja). | G31: Glúten (hveiti), fiskur | I31: https://docs.google.com/document/d/1mrPTXRk_Pt2msU-ckh0eoh4oUCEKrI5g/edit?usp=sharing&ouid=115242652208709673085&rtpof=true&sd=true | J31: 125 | K31: 1 | L31: 0.3 | M31: 11 | N31: 0.2 | O31: 18 | P31: 0.7 | R31: 1800 | S31: Orka: 530 kJ/125 kcal. Umbúðir: plastbakki, plastfilma, pappahólkur.
A32: Fiskibollur án glúten | B32: Fiskibollur án glúten | C32: Norðanfiskur | D32: 9060 | E32: Fiskur | F32: **Þorskur**, laukur, kartöflumjöl, umbreytt maíssterkja, jurtatrefjar, **soja**prótein, laukduft, salt, bindiefni (E451), hvítur pipar repjuolía. | G32: Fiskur, soja | I32: https://drive.google.com/file/d/1su1X4NqQ06JKbPrLHqbYVzuDSI9b-_ZY/view?usp=sharing | J32: 125 | K32: 1.3 | L32: 0.1 | M32: 14.2 | N32: 0.7 | O32: 14.1 | P32: 1.4 | R32: 1800 | S32: 5 kg/kassa. Án glutens, mjólkurvara og eggja.
A33: Anamma Vegan Nuggets Pea | B33: Anamma Vegan Nuggets Pea | C33: Orkla Foods Sweden/Danól | D33: 454071477 | E33: Plöntubasað | F33: Vatn, baunaprótein(17%), repjuolía, glútenlaus raspur (hrísgrjónamjöl, kjúklingabaunamjöl, maíssterkja, salt, dextrósi), hrísgrjónamjöl, maíssterkja, laukur, salt, náttúruleg bragðefni (paprika, kóríander, múskat), bindiefni (metýlsellulósi) | G33: Engir skráðir | H33: Getur innihaldið snefil af soja | I33: https://docs.google.com/document/d/1hD7vfcvl0f75johYoY3PnnS548AlpCDkNKyTSEnJezk/edit?usp=sharing | J33: 256 | K33: 17 | L33: 1.2 | M33: 14 | N33: 0 | O33: 12 | P33: 1.2 | R33: 2500 | S33: 3 kg pakki (~100 stk, 22–23 g/stk). Frystivara -18°C. Vegan, án glútens, mjólkur og eggs.
A34: BBQ Oumph! (Pulled) | B34: BBQ Oumph! (Pulled) | C34: LiveKindly Collective AB | D34: 1407 | E34: Plöntubasað | F34: **Soja**prótein 54,3% (vatn, **soja**próteinþykkni), grillsósa 45,7% (vatn, krydd, sykur, salt, karamellaður sykur, tómatur, laukur, hvítlaukur, pipar, engifer, steinselja, svartur pipar, cayennepipar, sýrustillir sítrónusýra, repjuolía, náttúruleg bragðefni, maltódextrín, umbreytt maíssterkja, bragðefni), tómatpúrra, eplaþykkni, edik, reykbragðefni. | G34: Soja | I34: https://drive.google.com/file/d/1ny7Hc5Bb9td7Jjuz8iDeeFNvGw0ASEur/view?usp=sharing | J34: 115 | K34: 0.7 | L34: 0.1 | M34: 11 | N34: 9.4 | O34: 14 | P34: 1.5 | Q34: 4.7 | R34: 1800 | S34: EAN: 07316641014072. 2 kg. Frystivara -18°C, geymsluþol 547 dagar.
A35: Asískar grænmetisbollur | B35: Asískar grænmetisbollur | C35: Avita/Danco | D35: 8808 | E35: Plöntubasað | F35: Grænmeti (gulrætur, hvítkál, bambus, paprika, svartir sveppir, blaðlaukur, laukur, sykurbaunir) 40,5%, hrísgrjón 35%, repjuolía, kartöfluflögur, baunasterkja, döðlur 3%, sólblómaolía, krydd, salt, sykur, steinselja, kartöflusterkja, bindiefni (hýdroxýprópýl metýlsellulósi) | G35: Engir skráðir | I35: https://drive.google.com/file/d/1apWuKGpcNAqp6PlmDeLj6QCa3EUrWc9L/view?usp=sharing | J35: 182 | K35: 7.5 | L35: 0.8 | M35: 24.7 | N35: 5.3 | O35: 1.9 | P35: 1.4 | R35: 350 | S35: ~25 g/stk. 5 x 1.200 g í kassa. Frystivara -18°C, geymsluþol 18 mánuðir.
A36: Falafel bollur Funky Harissa & Grilled Pepper | B36: Falafel bollur Funky Harissa & Grilled Pepper | C36: Salomon FoodWorld | D36: 8530200 | E36: Plöntubasað | F36: Kjúklingabaunir (33%), kartöflur, **hveiti**mjöl, kjúklingabaunamjöl, vatn, paprika (5%), gulrætur, þurrkaðir tómatar (3%), laukur, piparþykkni, repjuolía, krydd, svart kúmen, hvítlaukur, maísmjöl, salt, chili, kryddþykkni, sýra (sítrónusýra), tómatþykkni, **hveiti**sterkja, kryddjurtir, lyftiefni (dífosföt, natríumkarbónöt) | G36: Glúten (hveiti) | I36: https://drive.google.com/file/d/1Y-R-GvIw5gcBuCYDUT2F0S5nKyBx43UH/view?usp=sharing | J36: 222 | K36: 7.4 | L36: 0.9 | M36: 28 | N36: 3.6 | O36: 7.6 | P36: 1.1 | Q36: 6.5 | R36: 1800 | S36: 1 kg (52–56 stk). 3 x 1 kg = 3 kg/kassa. Frystivara -18°C, geymsluþol 450 dagar. Vegan.
A37: Garden Gourmet Vegan Nuggets - EKKI í notkun | B37: Garden Gourmet Vegan Nuggets - EKKI í notkun | C37: Nestlé Professional/ Innnes | D37: 12608135 | E37: Plöntubasað | F37: Endurvatnað **hveiti**prótein 40,9% (vatn, **hveiti**prótein 9,7%, **hveiti**mjöl 2,8%), raspur 17% (**hveiti**mjöl, salt, ger, repjuolía, kryddþykkni paprika), vatn, jurtaolíur (repja, sólblómaolía), **hveiti**mjöl, baunaprótein, sýrustillir (buffrað edik), bindiefni (metýlsellulósi), **hveiti**glúten 1,7%, náttúruleg bragðefni, sterkja, sítrustrefjar, salt, bambustrefjar, laukduft, hvítur pipar, **soja**sósa (**sojabaunir**, **hveiti**, salt) | G37: Glúten (hveiti), soja | H37: Getur innihaldið snefil af eggjum. | I37: https://drive.google.com/file/d/1_5EjaAcN-dT9_KQ7b3yra7RVnqiPPeaS/view?usp=sharing | J37: 238 | K37: 13.4 | L37: 1.6 | M37: 13.3 | N37: 1.7 | O37: 13.6 | P37: 1.1 | Q37: 5.1 | R37: 1800 | S37: 2 kg pakki (~100 stk). Frystivara -18°C, geymsluþol 15 mánuðir. Vegan.
A38: Marrakesh pottréttur | B38: Marrakesh pottréttur | C38: Álfasaga ehf. / Móðir Náttúra | D38: 816 | E38: Plöntubasað | F38: Tómatar, kjúklingabaunir, laukur, gulrætur, sætar kartöflur, eplasafi (eplasafi, þráavarnarefni E330), blómkál, repjuolía, döðlur, limesafi (lime safi, þráavarnarefni E224, inniheldur **SÚLFÍÐ**), paprikumauk (rauð paprika, eggaldin, sólblómaolía, sykur, salt, sýrustillir E260, krydd, chili, náttúruleg bragðefni), hvítlaukur, salt, kóríander, chilimauk (rauður chili, salt, sykur, sýrustillir E260, E330, rotvarnarefni E211), grænmetiskraftur (salt, pálmaolía, maltodextrín, gulrætur, laukur, **sellerí**, blaðlaukur, graslaukur), sykur, krydd (túrmerik, hvítur pipar, kóríander, múskat, **sellerí**), rósmarínkraftur, kúmen, engifer, túrmerik, svartur pipar, kanill. | G38: Súlfít, sellerí. | H38: Framleitt á svæði þar sem unnið er með hnetur | I38: https://docs.google.com/document/d/1lFUBZ6JnrNhmfGUHlIWLvOeyf8UZVP0UP7Z3nm8HOlw/edit?usp=sharing | J38: 118 | K38: 4.5 | L38: 0.4 | M38: 13.5 | N38: 5.7 | O38: 3.8 | P38: 0.9 | Q38: 4 | R38: 1800 | S38: 2 x 2,5 kg í kassa. Frystivara -18°C. Geymsluþol 1 ár. Tilbúið til neyslu, þarf aðeins að hita.
A39: Vegan grjónagrautur | B39: Vegan grjónagrautur | C39: Í-MAT / Matarstund | D39: FH-20260127-01 | E39: Plöntubasað | F39: Vegan rjómi (vatn , jurtaolía pálmakjarni, pálmi, þurrkað glúkósasíróp, umbreytt sterkja, salt, bindiefni E339, gellangúmmí, ýruefni lesitín, E435, E472b, litarefni karótín, náttúruleg bragðefni), vatn, hrísgrjón, sykur, salt. | G39: Engir skráðir | I39: https://drive.google.com/file/d/12DfeqymW1tAoO22_uIYQhTJKAtpxDRqo/view?usp=sharing | J39: 74 | K39: 1.6 | L39: 0.3 | M39: 13 | N39: 1.2 | O39: 1.8 | P39: 0.4 | R39: 350 | S39: ~10 L (~40 skammtar á 250 g). Kælivara 0–4°C / Frystivara. Vegan, laktósalaust. Næringargildi eru áætluð viðmið.
A40: Brunoise grænmetisblanda | B40: Brunoise grænmetisblanda | C40: Ardo/Garri | D40: MMB610 | E40: Grænmeti | F40: Sellerírót (33%), gulrætur (32%), blaðlaukur (15%), **sellerí** (10%), laukur (10%) | G40: Sellerí | I40: https://drive.google.com/file/d/1GJCXmg1Vj2I1EBYaQMCFT7B1s7hEMNUD/view?usp=sharing | J40: 26 | K40: 0.4 | L40: 0.1 | M40: 3.4 | N40: 2.9 | O40: 1 | P40: 0.1 | Q40: 2.5 | R40: 400 | S40: Frystivara -18°C.
A41: Grænar baunir (niðursoðnar) | B41: Grænar baunir (niðursoðnar) | C41: Ora / Myllan | D41: 21030 / 21025 / 21010 / 25010 | E41: Niðursuðuvörur | F41: Grænar baunir, vatn, sykur, salt. | G41: Engir skráðir | I41: https://drive.google.com/file/d/17KSvB7zRQOJLiWj6tLaTlWxpIBsKk_M-/view?usp=sharing | J41: 120 | K41: 0.8 | L41: 0.1 | M41: 20 | N41: 3.1 | O41: 7 | P41: 1 | R41: 350 | S41: Fáanlegar í 275g, 420g, 850g og 4,5 kg dósum. Geymsluþol 48 mánuðir.
A42: Franskar Mydibel Classic 9/9 | B42: Franskar Mydibel Classic 9/9 | C42: Clarebout Potatoes | E42: Grænmeti | F42: Kartöflur 97%, sólblómaolía 3%. Vinnsluhjálparefni (dextrósi, tvínatríumdífosfat). | G42: Engir skráðir | I42: https://drive.google.com/file/d/1NTqzKXREB617l_w7DuQp8ELURiDGn_ti/view?usp=sharing | J42: 120 | K42: 2.7 | L42: 0.4 | M42: 22.9 | O42: 2.2 | P42: 0.1 | Q42: 2.6 | R42: 400 | S42: 2,5 kg pakki. Frystivara -18°C. <0,5 g sykur. Cutsize 10x10 mm.
A43: Kartöflubátar (Potato Wedges) | B43: Kartöflubátar (Potato Wedges) | C43: Mydibel | E43: Grænmeti | F43: Kartöflur 97%, sólblómaolía. | G43: Engir skráðir | I43: https://vefverslun.ojk-isam.is/api/BlobForward/inline/ojkisam/189951b7-effb-4203-bd14-2e1084333a72.pdf | J43: 130 | K43: 3.8 | L43: 2.1 | M43: 20 | O43: 2.7 | P43: 0.1 | Q43: 2.7 | R43: 830 | S43: Frystivara -18°C, geymsluþol 24 mánuðir. <0,5 g sykur.
A44: Hvítlauks aioli GARRI vegan 725 ml | B44: Hvítlauks aioli GARRI vegan 725 ml | C44: Kjarnavörur hf. | D44: 12737 | E44: Sósur / Dressingar / Kraftar | F44: Repjuolía, vatn, hvítlaukur, **sinnep** (vatn, sykur, edik, **sinnep**sduft, umbreytt kartöflusterkja, salt, umbreytt maíssterkja, karrí, túrmerik duft, rotvarnarefni E202, E211), kryddblanda (salt, kryddblanda, maltódextrín, kekkjavarnarefnii E552), sykur, umbreytt kartöflusterkja, salt, edik, kryddblanda, rotvarnarefni (E260, E211, E202), **sinnep**sduft, sýra (E330), bindiefni (E415) | G44: Sinnep | I44: https://drive.google.com/file/d/12plSEq_gkegCbnbLks9oisLjM1HR3Ncx/view?usp=sharing | J44: 519 | K44: 56 | L44: 3.6 | M44: 6 | N44: 4.1 | P44: 1.1 | R44: 200 | S44: 713 g nettóþyngd. 6 x 725 ml sölueining. Kælivara 0–4°C. Geymsluþol 5 mánuðir.
A45: Í MAT Karrísósa vegan 10 ltr | B45: Í MAT Karrísósa vegan 10 ltr | C45: Kjarnavörur hf. | D45: 310008 | E45: Sósur / Dressingar / Kraftar | F45: Repjuolía, vatn, kryddblanda (rotvarnarefni E260, E211, E202, **sinnep**sduft, krydd, sýra E330), karrí (kóríander, túrmerik, fenugreek, kúmen, salt, fennel, chili, sykur, laukduft, pipar), hunangslíki (sykur, vatn, sýra E507, sýrustillir E500, bragðefni, hunangsbragðefni, litarefni E150a, E150c), umbreytt kartöflusterkja (E1450), sykur, grænmetiskraftur (maltródextrín, bragðefni, grænmeti), salt, kryddblanda (maltódextrín, gerþykkni, pálmaolía, kryddblanda), rotvarnarefni (E202), bindiefni (E412) | G45: Sinnep | I45: https://drive.google.com/file/d/1RA_hEPDQMpqswOh6yfemnR-S_oqXCP2_/view?usp=sharing | J45: 532 | K45: 57 | L45: 3.7 | M45: 5.9 | N45: 3 | P45: 1.2 | R45: 600 | S45: 10 ltr (9,7 kg). 1 x 10 ltr sölueining. Kælivara 0–4°C. Geymsluþol 4 mánuðir.
A46: Í MAT Vegan kokteilsósa 10 ltr | B46: Í MAT Vegan kokteilsósa 10 ltr | C46: Kjarnavörur hf. | D46: 310001 | E46: Sósur / Dressingar / Kraftar | F46: Repjuolía, tómatsósa (vatn, tómatpúrra, rotvarnarefni E260, E211), vatn, **sinnep** (edik, sinnepsduft, umbreytt maíssterkja, karrí úr túrmerik, kóríander, negul, engifer, múskati, kardimommum og cayennepipar, túrmerikduft, kryddblanda úr papriku, lauk, chilipipar, svörtum pipar, hvítlauk, maltódextríni, tómatdufti og kekkjavarnarefni E552, hvítur pipar), kryddblanda (sinnepsduft, sýra E330), eplaedik, umbreytt kartöflusterkja, sykur, salt, paprikuduft, rotvarnarefni (E202), broddkúmen, bindiefni (E412) | G46: Sinnep | I46: https://docs.google.com/document/d/1jjpLQLnejNxDdmA90ekhQ3HbNVINXitkS6-S1W5yeak/edit?usp=sharing | J46: 448 | K46: 45 | L46: 2.9 | M46: 12 | N46: 9.9 | P46: 1.4 | R46: 600 | S46: 10 ltr (10 kg). 1 x 10 ltr sölueining. Kælivara 0–4°C. Geymsluþol 4 mánuðir.
A47: Knorr brún sósa (Brun basissauce, granulat) - Tilbúin sósa | B47: Knorr brún sósa (Brun basissauce, granulat) - Tilbúin sósa | C47: Knorr / Unilever | D47: 67453014 | E47: Sósur / Dressingar / Kraftar | F47: Vatn, umbreytt sterkja, hrísgrjónamjöl, maltódextrín, sykur, bragðefni, salt, gerþykkni, ristaður laukur, sólblómaolía, litarefni (E150c), salvía. | G47: Engir skráðir | I47: https://drive.google.com/file/d/1A544lje2nijReN8m6qcUAXHEHx-gg4OG/view?usp=sharing | J47: 25 | K47: 0.3 | L47: 0 | M47: 5 | N47: 0.7 | O47: 0.5 | P47: 0.5 | Q47: 0.1 | R47: 600 | S47: 3,75 kg. Þurrgeymist. Notkunarskammtur: 75 g á 1 lítri vatn. Saltinnihald í fullbúinni sósu: 0,7%.
A48: Borðsalt | B48: Borðsalt | C48: Katla matvælaiðja ehf. | D48: 10232 | E48: Krydd | F48: Salt (salt, kekkjavarnarefni E535, lyftiefni E500). | G48: Engir skráðir | H48: Framleitt á svæði þar sem unnið er með mjólk, glúten, egg, sesam, sellerí, soja og sinnep. | I48: https://drive.google.com/file/d/18_svh90eLQ1eSbJF3qr3eWDjhyhpL95Y/view?usp=sharing | J48: 0 | K48: 0 | L48: 0 | M48: 0 | N48: 0 | O48: 0 | P48: 100 | R48: 120 | S48: 15 x 1 kg. Þurrgeymist 36 mánuðir.
A49: Hvítlauksblanda Ört & Vitlökskrydda | B49: Hvítlauksblanda Ört & Vitlökskrydda | C49: Nordic Spice AB/Garri | D49: 30104 | E49: Krydd | F49: Salt, svartur pipar, hvítlaukur, paprikubitar, laukur, steinselja, dextrósi, timían, estragon. | G49: Engir skráðir | H49: Framleitt á svæði þar sem unnið er með glúten, fisk, krabbadýr, lindýr, mjólk, soja, sellerí, sinnep og sesam. | I49: https://drive.google.com/file/d/1zCXy9QE-qppLvTnBD_yF5HvXpDu8Y7p3/view?usp=sharing | J49: 178 | K49: 1.1 | L49: 0.3 | M49: 31 | N49: 4.7 | O49: 6.3 | P49: 51 | R49: 4000 | S49: Þurrgeymist 24 mánuðir. Framleidd í Svíþjóð.
A50: Hvítlauksduft (Vitlökspulver) | B50: Hvítlauksduft (Vitlökspulver) | C50: Nordic Spice AB/Garri | D50: 35049 | E50: Krydd | F50: Hvítlauksduft 100% | G50: Engir skráðir | H50: Framleitt á svæði þar sem unnið er með glúten, fisk, krabbadýr, lindýr, mjólk, soja, sellerí, sinnep og sesam. | I50: https://drive.google.com/file/d/1MSRdefMEGeUCyN8gS7xeRyI53AOLv84-/view?usp=sharing | J50: 385 | K50: 0.8 | L50: 0.1 | M50: 73 | N50: 24 | O50: 17 | P50: 0.1 | R50: 4313 | S50: Þurrgeymist 24 mánuðir. Upprunaland: USA.
A51: Hvítlaukspipar (Ekran garlic pepper) | B51: Hvítlaukspipar (Ekran garlic pepper) | C51: Verstegen Spices & Sauces B.V. | D51: 465301 | E51: Krydd | F51: Pipar 39%, hvítlaukur 35%, salt, steinselja. | G51: Engir skráðir | I51: https://drive.google.com/file/d/1K0qP0waouin3uVEFV28d1FvQ27k24k4A/view?usp=sharing | J51: 288 | K51: 2.8 | L51: 0.4 | M51: 46.7 | N51: 0.9 | O51: 11.9 | P51: 16.4 | Q51: 14.3 | R51: 3000 | S51: 1,5 kg PP dós. Þurrgeymist 3 ár. Vegan.
A52: Laukduft (Lökpulver) | B52: Laukduft (Lökpulver) | C52: Nordic Spice AB/Garri | D52: 35050 | E52: Krydd | F52: Laukduft 100% | G52: Engir skráðir | H52: Framleitt á svæði þar sem unnið er með glúten, fisk, krabbadýr, lindýr, mjólk, soja, sellerí, sinnep og sesam. | I52: https://drive.google.com/file/d/1YHkMc_djsZPOsdKJXrJwmjd5dzhluJHF/view?usp=sharing | J52: 385 | K52: 1.1 | L52: 0.2 | M52: 81 | N52: 36 | O52: 11 | P52: 0.1 | R52: 3365 | S52: Þurrgeymist 24 mánuðir. Upprunaland: USA.
A53: Knorr grænmetiskraftur þurr | B53: Knorr grænmetiskraftur þurr | C53: Knorr / Unilever | D53: 29039101 | E53: Sósur / Dressingar / Kraftar | F53: Salt, maltódextrín, grænmetisduft 11% (laukur, gulrætur, gulrótarsafaduft, blaðlaukur), sterkja (maís, kartöflur), sykur, gerþykkni, bragðefni, krydd. | G53: Engir skráðir | H53: Saltinnihald í tilbúnu soði er 0,7%. | I53: https://danol.datadwell.com/link/72156-599036.pdf/play?player=1 | J53: 200 | K53: 2 | L53: 1 | M53: 40 | N53: 12 | O53: 6 | P53: 45 | R53: 350 | S53: 5 kg / 333 L bouillon. Þurrgeymist, ekki yfir 23°C. Vegan, glútenlaust.
A54: Kókosmjólk Roland Coconut Milk | B54: Kókosmjólk Roland Coconut Milk | C54: Roland Foods LLC | D54: 86026 | E54: Niðursuðuvörur | F54: Kókosmjólk, vatn, gúargúmmí. | G54: Engir skráðir | I54: https://drive.google.com/file/d/1FvEYUVnd2_BK17DbZjzv5N3_8u3AZbzA/view?usp=sharing | J54: 181 | K54: 18 | L54: 15.3 | M54: 2.8 | N54: 1 | O54: 2 | P54: 0 | Q54: 0 | R54: 450 | S54: 98 fl.oz. (2,9 L) dós, 6 dósar/kassa. Þurrgeymist 3 ár. Eftir opnun: kæla og nota innan 5 daga. Vegan.
A55: Hrísgrjón Thai Hom Mali (Royal Umbrella) | B55: Hrísgrjón Thai Hom Mali (Royal Umbrella) | C55: Khao C.P. Co., Ltd. | E55: Kornvörur og hráefni | F55: Hrísgrjón 100% | G55: Engir skráðir | I55: https://drive.google.com/file/d/1DoKkdQMWFLTDnrAu21AaCM2FHpZ73bgS/view?usp=sharing | J55: 365 | K55: 0.7 | L55: 0.2 | M55: 80 | N55: 0.1 | O55: 7.1 | P55: 0 | Q55: 1.3 | R55: 350
A56: Hrísgrjón Thai Hom Mali - SOÐIN | B56: Hrísgrjón Thai Hom Mali - SOÐIN | C56: Khao C.P. Co., Ltd. | E56: Kornvörur og hráefni | F56: Hrísgrjón 100% | G56: Engir skráðir | J56: 130 | K56: 0.3 | L56: 0.1 | M56: 28.6 | N56: 0 | O56: 2.7 | P56: 0 | Q56: 0.4 | R56: 350
A57: Maizenamjöl (majssterkja) | B57: Maizenamjöl (majssterkja) | C57: Maizena / Unilever | D57: 237528 | E57: Kornvörur og hráefni | F57: Maíssterkja. | G57: Engir skráðir | I57: https://drive.google.com/file/d/1CmXprz2PFHVmxfaM0CalYclE2qYOhpF7/view?usp=sharing | J57: 355 | K57: 0.5 | L57: 0 | M57: 86 | N57: 0 | O57: 0.5 | P57: 0 | Q57: 1 | R57: 400 | S57: 2,5 kg. Þurrgeymist. Glúten- og laktósalaust. Vegan.
A58: Múslí Granóla hnetulaus | B58: Múslí Granóla hnetulaus | C58: hberg Garri | D58: 78121144 | R58: 883
A59: Granóla múslí | B59: Granóla múslí | C59: H-Berg ehf. | D59: 21144 | E59: Grautar og morgunmatur | F59: Heilkornaflögur (61,5%) (**hafrar**, **hveiti**), sykur, sólblómaolía, stökkt korn (6,2%) (hrísmjöl, **hveiti**, sykur, maltað **bygg**, salt), **hveiti**, glúkósasýróp, hunang, lyftiefni (E500), kanill, karamellaður sykur, bragðefni, þráavarnarefni (E306) | G59: Glúten (hafrar, hveiti, bygg). | H59: Gæti innihaldið snefil af hnetum, mjólk og soja | I59: https://docs.google.com/document/d/1ifrlgLmRek3D49wWNhUQ_AdEsalsUL9A3wL-voKvyxI/edit?usp=sharing | J59: 430 | K59: 13 | L59: 1.4 | M59: 66 | N59: 17 | O59: 9.3 | P59: 0.2 | Q59: 6 | R59: 600 | S59: 1 kg. Þurrgeymist ≤20°C í 12 mánuðir. Upprunaland hráefnis: Holland.
A60: Nachos Tortilla Chips Salted (Santa Maria) | B60: Nachos Tortilla Chips Salted (Santa Maria) | C60: Paulig / Santa Maria | D60: 200815 | E60: Kornvörur og hráefni | F60: Maís mjöl (78%), sólblómaolía, salt. | G60: Engir skráðir | H60: Getur innihaldið snefil af soja | I60: https://docs.google.com/document/d/1TTmK_n2QFHKIN4R5nh8vlgj5w-uy7i6hZxC_Tw6B1Oc/edit?usp=sharing | J60: 472 | K60: 20 | L60: 2 | M60: 64 | N60: 0.8 | O60: 6.6 | P60: 1.2 | Q60: 4 | R60: 400 | S60: 475 g. Þurrgeymist. Geymsluþol 300 dagar. Vegan, glútenlaust.
A61: Ömmu rúgbrauð (mjólkurlaust) | B61: Ömmu rúgbrauð (mjólkurlaust) | C61: Gæðabakstur / Ömmubakstur ehf. | D61: 609 | E61: Brauð og bakkelsi | F61: **Rúg**mjöl, vatn, sykur, heil**hveiti**, maltað **bygg**, malt extrakt (úr **byggI**), súrdeigsduft úr hveiti (**hveiti**, mjólkursýrugerlar), salt, rotvarnarefni (E282), ger, mjölmeðhöndlunarefni (E300), kekkjarvarnarefni (E535), bindiefni (E491) | G61: Glúten (rúgur, hveiti, bygg) | H61: Gæti innihaldið snefil af sesam | I61: https://gaedabakstur.is/vara/ommurugbraud-30-sneida/ | J61: 252 | K61: 1.1 | L61: 0.2 | M61: 50 | N61: 20 | O61: 4.8 | P61: 0.6 | Q61: 8.2 | R61: 1018 | S61: 1200 g. 8 dagar við stofuhita, 6 mánuðir í frosti (-18°C). Vegan. Inniheldur engar dýraafurðir.
A62: Oumph! Färs (hakk) | B62: Oumph! Färs (hakk) | C62: LiveKindly Collective AB | D62: 600234 | E62: Plöntubasað | F62: Vatn, **soja**próteinþykkni 19%, repjuolía, kryddblanda (laukduft, salt, bragðefni, hvítlauksduft), hleypiefni (metýlsellulósi), litarefni sykurlitur ammoníakferli). | G62: Soja | I62: https://drive.google.com/file/d/17I0KWyblXTi11MUMbyMelwqAThnVoPX7/view?usp=sharing | J62: 131 | K62: 7.2 | L62: 0.5 | M62: 1.4 | N62: 0.6 | O62: 13 | P62: 0.9 | Q62: 4.2 | R62: 1800 | S62: EAN: 07316641013839. 2 kg. Frystivara -18°C, geymsluþol 365 dagar. Upprunaland: Svíþjóð.
A63: Pizza Snack Margherita | B63: Pizza Snack Margherita | C63: Dr. August Oetker Nahrungsmittel KG | D63: 1-25-002000 / F11221 | E63: Brauð og bakkelsi | F63: **Hveiti**mjöl, 21% **ostur** (mozzarella, edam), 15% tómatpúrra, vatn, 7,9% tómatþykkni, repjuolía, ger, salt, sykur, extra virgin ólífuolía, basil, oregano, hvítlaukur, laukur, pipar, ristaður laukur. | G63: Glúten (hveiti), mjólk | H63: Getur innihaldið snefil af soja | I63: https://drive.google.com/file/d/1xmupIyoGoDbKzYW0SmUzAFTzdGR7wPpN/view?usp=sharing | J63: 227 | K63: 7.5 | L63: 3.6 | M63: 29 | N63: 3.8 | O63: 10 | P63: 1 | R63: 600 | S63: GTIN: 4001724035558. 28 x 150 g/ks. Frystivara -18°C. Konvektomat: 200°C forheitt, 10 mín við 185°C.
A64: Hönö Skärgårdskaka (Pólarbrauð) | B64: Hönö Skärgårdskaka (Pólarbrauð) | C64: Pågen/ Ójk | D64: 1186 | E64: Brauð og bakkelsi | F64: **Hveiti**mjöl, vatn, sykur, sigtað **rúg**mjöl, repjuolía, heilkorna **rúg**mjöl, **hveiti**glúten, heilkorna **hveiti**mjöl, **hveiti**mjöl, ger, ýruefni (mónó- og díglýseríð fitusýra úr sólblóma- og repjuolíu), lyftiefni (hjartarsalt), malt úr **byggi**, salt. | G64: Glúten (hveiti, rúgur, bygg). | I64: https://drive.google.com/file/d/1wQ6Aj25cbHnFwYYRVBbBao0ceJotW3tK/view?usp=sharing | J64: 296 | K64: 4.5 | L64: 0.5 | M64: 52 | N64: 9.7 | O64: 9.1 | P64: 0.8 | Q64: 3.3 | R64: 600 | S64: GTIN: 07311070337297. 18 stk/pakki. Frystivara 180 dagar, kælivara 7 dagar þiðnuð. Upprunaland: Svíþjóð.
A65: Creamy mashed potatoes - Ekki í notkun | B65: Creamy mashed potatoes - Ekki í notkun | C65: Agristo nv | D65: 304384 | E65: Grænmeti | F65: Kartöflur (86,2%), **mjólk** (9,7%), smjörfita, salt, hvítur pipar. | G65: Mjólk | I65: https://drive.google.com/file/d/1Q5pHOTieK7b4Gy3bBGFnnGvU9GEQuRj9/view?usp=sharing | J65: 104 | K65: 3.1 | L65: 1.9 | M65: 16 | O65: 2 | P65: 0.5 | Q65: 1.9 | R65: 400 | S65: Frystivara -18°C, geymsluþol 18 mánuðir. Vegetarian. Án litarefna, bragðefna og pálmaolíu. Sykur <0,5 g.
A66: Quinoa Grænkálsbuff | B66: Quinoa Grænkálsbuff | C66: Ardo Austria Frost GmbH | D66: RLQ320V / UQB410 | E66: Plöntubasað | F66: Grænkál 17%, raspur 15% (**spelt**mjöl, poppað kínóa, sólblómaolía, salt, ger), forsoðið kínóa 13% (vatn, kínóa), vatn, jurtaolía (sólblómaolía, repjuolía í mismunandi hlutföllum), kartöflur, gulrætur, ristaður laukur (laukur, repjuolía), **sojabaunir**, kartöfluflögur, **hveiti**mjöl, kryddblanda (salt, maltódextrín, krydd), sojasósa (vatn, salt, **sojabaunir**, **hveiti**), joðbætt salt (salt, kalíumjoðíð), karríduft, hvítlauksduft, malað engifer, svartur pipar. | G66: Glúten (spelt, hveiti), soja. | I66: https://drive.google.com/file/d/1K9SR8AXu2Qag_F36czw5QGX4OuqCSj7q/view?usp=sharing | J66: 212 | K66: 11.4 | L66: 1.3 | M66: 21.7 | N66: 1.9 | O66: 4.5 | P66: 1 | Q66: 2.5 | R66: 1800 | S66: ~75 g/stk. 6 x 1200 g/ks. Frystivara -18°C, geymsluþol 24 mánuðir. Vegan (V-Label.EU).
A67: Rauðkál | B67: Rauðkál | C67: Samsø Syltefabrik A/S | D67: 63771 | E67: Niðursuðuvörur | F67: Rauðkál, sykur, edik, salt, síróp, rifsberjasafi. | G67: Engir skráðir | I67: https://drive.google.com/file/d/1Rqb9kj8tVDkHq7eyRPXcNpc6UUH_taBS/view?usp=sharing | J67: 74 | K67: 0.5 | L67: 0.1 | M67: 17 | N67: 15 | O67: 1.3 | P67: 0.4 | Q67: 1.7 | R67: 450 | S67: Nettóþyngd: 4250 g, brúttóþyngd: 4569 g. EAN: 05706680028734. Geymsluþol 1090 dagar óopnaður. Upprunaland: Danmörk.
A68: Sweet Potato Rust Cut (Sætar kartöflur) | B68: Sweet Potato Rust Cut (Sætar kartöflur) | C68: Monliz España S.L.U. | D68: ME0062001 | E68: Grænmeti | F68: Sætar kartöflur | G68: Engir skráðir | I68: https://drive.google.com/file/d/1jCcWn6ueSY2iLASOI_k-MMXCXPZq0Hst/view?usp=sharing | J68: 72 | K68: 0.1 | L68: 0 | M68: 15.2 | N68: 5.7 | O68: 1.4 | P68: 0.1 | Q68: 2.5 | R68: 400 | S68: Blanched, cooled and frozen. Frystivara -18°C, geymsluþol 36 mánuðir. Vegan, án glútens. Upprunaland: Spánn.
A69: Chunky Salsa Medium (Salsa sósa) | B69: Chunky Salsa Medium (Salsa sósa) | C69: Paulig / Santa Maria | D69: 4551 | E69: Sósur / Dressingar / Kraftar | F69: Tómatar (81%) (hakkaðir tómatar, tómatpúrra), laukur (8%), grænt chili, salt, maíssterkja, krydd og kryddjurtir (chilipipar, hvítlaukur, kúmen, cayennepipar, kóríander, oregano), jalapeño (0,6%), paprika, vínedik, límónusafi. | G69: Engir skráðir | I69: https://vefverslun.ojk-isam.is/api/BlobForward/inline/ojkisam/3adc8233-495e-4c7d-81f5-7158bf814740.pdf | J69: 33 | K69: 0 | L69: 0 | M69: 5.5 | N69: 4.8 | O69: 1.6 | P69: 1 | Q69: 1.9 | R69: 600 | S69: GTIN: 07311310045517. 3700 g. Þurrgeymist 545 dagar. Kæla eftir opnun, nota innan 4 vikna. Vegan, glútenlaust.
A70: Salt vacuum | B70: Salt vacuum | C70: Nordic Spice AB/Garri | D70: 35039 | E70: Krydd | F70: Salt, kekkjavarnarefni (E535). | G70: Engir skráðir | H70: Framleitt á svæði þar sem unnið er með glúten, fisk, krabbadýr, lindýr, mjólk, soja, sellerí, sinnep og sesam. | I70: https://drive.google.com/file/d/18_svh90eLQ1eSbJF3qr3eWDjhyhpL95Y/view?usp=sharing | J70: 0 | K70: 0 | L70: 0 | M70: 0 | N70: 0 | O70: 0 | P70: 99 | R70: 120 | S70: Þurrgeymist 36 mánuðir. Án joðs. Upprunaland: ESB (EU). Framleidd í Svíþjóð.
A71: Reykt kjúklingaálegg | B71: Reykt kjúklingaálegg | C71: Matfugl ehf. | D71: 174440 / 174481 | E71: Kjöt / Alifuglar | F71: Kjúklingarbringur (42%), alifuglakjöt (28%), vatn (25%), salt, þrúgusykur, bindiefni (E451, E407, E410), gerextrakt, þráavarnarefni (E301, E330), bragðefni, sykur, pipar, rotvarnarefni (E270) | G71: Engir skráðir | I71: https://docs.google.com/document/d/1m0YKiZ4cQZAZVlQ9NBO-W9jBUEk9w4-k1SKb9XI2P-o/edit?usp=sharing | J71: 85 | K71: 0.8 | L71: 0.3 | M71: 1.8 | N71: 1.7 | O71: 16 | P71: 2.6 | R71: 1900 | S71: Kælivara 0-4°C. Geymsluþol 21 dagur. Uppfyllir örverufræðileg viðmið skv. reglugerð (EB) nr. 2073/2005.
A72: Sauce tikka masala GT-CHEF | B72: Sauce tikka masala GT-CHEF | C72: GoldenTurtleForChefs (ZLI)/ Garri | D72: 60486 | E72: Sósur / Dressingar / Kraftar | F72: Vatn, sykur, laukur, tómatmauk, sólblómaolía, salt, kóríanderduft, engifer, hvítlaukur, **sinnep**duft, sýrustillir (sítrónusýra E330), chili, kúmenduft, fenugreeklauf, svartur piparduft, kóríander, þráavarnarefni (E306, tókóferólríkt þykkni). | G72: Sinnep | I72: https://drive.google.com/file/d/1psBkJzLFrs5mN4fj1wYpcBp884WsVURp/view?usp=sharing | J72: 150 | K72: 5.9 | L72: 0.6 | M72: 22 | N72: 18 | O72: 1.4 | P72: 4.4 | Q72: 1.6 | R72: 600 | S72: 1 L flaska. Þurrgeymist 18 mánuðir. Kæla eftir opnun, nota innan 14 daga. Vegan.
A73: Skólabollur - Brauðbollur | B73: Skólabollur - Brauðbollur | C73: Myllan | D73: 3651 | E73: Brauð og bakkelsi | F73: Vatn, heilkorna **rúg**mjöl 20%, heilkorna **hveiti**mjöl 17%, **hveiti**mjöl, **hveiti**glúten, **rúg**mjöl, þurrkað súrdeig (**rúg**, súrdeigsgerlar), **hveiti**kurl, ger, maltextrakt (**bygg**), repjuolía, joðbætt salt, þykkingarefni (E415), sýrustillir (E262), ýruefni (E471, E472e), mjölmeðhöndlunarefni (E300), maltað **hveiti**. | G73: Glúten (rúgur, hveiti, bygg) | H73: Framleitt á svæði þar sem unnið er með sesamfræ, egg, mjólk og lúpínu | I73: https://drive.google.com/file/d/14DAgTI18dATCiMOlGqGBlT2S4QVgoDrD/view?usp=sharing | J73: 221 | K73: 2.8 | L73: 0.5 | M73: 34 | N73: 1.4 | O73: 11 | P73: 1.1 | Q73: 6.4 | R73: 600 | S73: EAN: 5690568036518. 675 g/pakki (90 stk í ks). Frystivara -18°C, geymsluþol 180 dagar. Vegan.
A74: Smjör 500 g | B74: Smjör 500 g | C74: MS | D74: 1005 | E74: Mjólkurvörur | F74: **Rjómi**, salt. | G74: Mjólk | I74: https://docs.google.com/document/d/149N3quKMoWawGv9LE2FddvRhKdpdb7Cxfmhury4OOtc/edit?usp=sharing | J74: 738 | K74: 82 | L74: 49 | M74: 0.4 | N74: 0.4 | O74: 0.6 | P74: 1.2 | R74: 2300 | S74: 500 g. A-vítamín 791 μg (99% NV). Kælivara. Upprunaland: Ísland.
A75: Smjörvi 400 g | B75: Smjörvi 400 g | C75: MS | D75: 2500 | E75: Mjólkurvörur | F75: **Rjómi**, repjuolía, salt, A-vítamín og D-vítamín. | G75: Mjólk | I75: https://docs.google.com/document/d/1UjBm-Tv-Iec76nq1yK04YofrHL0yfr89sWsBhPn2Bfg/edit?usp=sharing | J75: 702 | K75: 78 | L75: 37 | M75: 0.4 | N75: 0.4 | O75: 0.6 | P75: 1.2 | R75: 1200 | S75: 400 g. A-vítamín 900 μg (113% NV), D-vítamín 7,5 μg (150% NV). Kælivara. Upprunaland: Ísland.
A76: Violife Grated Mozzarella Flavour | B76: Violife Grated Mozzarella Flavour | C76: Arivia S.A. | D76: 312 | E76: Plöntubasað | F76: Vatn, kókosolía (24%), umbreytt sterkja, sterkja, sjávarsalt, reyniberjaþykkni, bragðefni, sýrustillir (sítrónusýra), ólífuþykkni, B12-vítamín, litarefni (beta-karótín). | G76: Engir skráðir | I76: https://docs.google.com/document/d/18b2J2oj0tGu3WRVMjz2b5-BVn6Pc_FMyhWrmnMt7mwI/edit?usp=sharing | J76: 305 | K76: 24 | L76: 21 | M76: 22 | N76: 0 | O76: 0.1 | P76: 1.7 | R76: 600 | S76: Kælivara 2-8°C. Geymsluþol 8 mánuðir. Vegan, Kosher, Halal. Fáanlegt í 200g, 250g, 500g, 1kg, 2kg og 2.5kg. Issue/Rev 5/1 (25/06/2024).
A77: Organic Crystal Sourdough Bun (Súrdeigshamborgarabrauð) | B77: Organic Crystal Sourdough Bun (Súrdeigshamborgarabrauð) | C77: Europastry S.A. | D77: 69393 | E77: Brauð og bakkelsi | F77: **Hveiti**mjöl*, vatn, heilkorna **hveiti**súrdeig 4% (heilkorna gerjað **hveiti**mjöl*, vatn), ger*, extra virgin ólífuolía 1,3%*, salt, **bygg**maltmjöl*, **hveiti**glúten*. *Lífrænt. | G77: Glúten (hveiti, bygg). | H77: Getur innihaldið snefil af soja, egg, mjólk, sesam, sinnep | I77: https://drive.google.com/file/d/1_7-lapfB0IXWi_NgfdgjTejZibfQdUt4/view?usp=sharing | J77: 242 | K77: 2.5 | L77: 0.4 | M77: 44 | N77: 0.6 | O77: 9.4 | P77: 1.3 | Q77: 1.8 | R77: 600 | S77: Box EAN: 8424465693935. ~75 g/stk. 60 stk/kassa (4,5 kg). Frystivara -14°C, geymsluþol 450 dagar. Þíðið 40 mín við stofuhita. Lífrænt (BIO). Upprunaland: Spánn.
A78: La Choy Sweet & Sour Sauce (Súrsæt sósa) | B78: La Choy Sweet & Sour Sauce (Súrsæt sósa) | C78: ConAgra Brands / La Choy | D78: 4430012690 | E78: Sósur / Dressingar / Kraftar | F78: Vatn, sykur, eimað edik, umbreytt maíssterkja, salt, þurrkuð græn og rauð paprika, þurrefni úr maíssírópi, litarefni (E160c), þurrefni úr ananassafa. | G78: Engir skráðir | I78: https://innnes.is/sosur/austurlenskar-sosur/la-choy-sursaetsosa-brusi-4x378kg/ | J78: 175 | K78: 0.3 | L78: 0.1 | M78: 42.3 | N78: 37.5 | O78: 0.2 | P78: 0.9 | Q78: 0.2 | R78: 600 | S78: 1 gallon (3,78 L). Þurrgeymist. Kæla eftir opnun. Geymsluþol 720 dagar. Kosher. Upprunaland: Kanada.
A79: Crystal Sugar (Sykur) | B79: Crystal Sugar (Sykur) | C79: Cosun Beet Company | E79: Kornvörur og hráefni | F79: Súkrósi | G79: Engir skráðir | I79: https://drive.google.com/file/d/1xlkj9UFMzhBrHGJoVUjpSgwu6ml60B4l/view?usp=sharing | J79: 400 | K79: 0 | L79: 0 | M79: 100 | N79: 100 | O79: 0 | P79: 0 | Q79: 0 | R79: 350 | S79: Þurrgeymist 10-30°C, geymsluþol 36 mánuðir. Upprunaland: ESB (EU). Án joðs.
A80: Sýrður rjómi 10% | B80: Sýrður rjómi 10% | C80: MS (Mjólkursamsalan Íslands) | E80: Mjólkurvörur | F80: **Undanrenna** og **rjómi**, sýrður með mjólkursýrugerlum, gelatín, ostahleypir. | G80: Mjólk | I80: https://docs.google.com/document/d/1YqVGDpK3zKU6f0K5VqvY9symdnjIMOW0qRxqrtjNvgU/edit?usp=sharing | J80: 119 | K80: 10 | L80: 6.4 | M80: 3.5 | N80: 3.5 | O80: 3.8 | P80: 0.1 | R80: 750 | S80: 180 g. Kælivara. B2-vítamín 0,15 mg (11% NV), B12-vítamín 0,34 μg (14% NV). Upprunaland: Ísland.
A81: Taco Grillkrydda | B81: Taco Grillkrydda | C81: Nordic Spice AB/Garri | D81: 30071 | E81: Krydd | F81: Salt, chilipipar, kúmen, hvítlaukur, svartur pipar, cayennepipar, laukur, engifer, sykur, sýrustillir (sítrónusýra), kekkjavarnarefni (E552), repjuolía, kryddþykkni. | G81: Engir skráðir | H81: Framleitt á svæði þar sem unnið er með glúten, fisk, krabbadýr, lindýr, mjólk, soja, sellerí, sinnep og sesam. | I81: https://drive.google.com/file/d/1mykwklqQSozxJsGLpVCPAvImnPXUQUDp/view?usp=sharing | J81: 222 | K81: 6 | L81: 0.9 | M81: 30 | N81: 4.6 | O81: 7.1 | P81: 45 | R81: 2914 | S81: Þurrgeymist 36 mánuðir. Framleidd í Svíþjóð.
A82: Taco Tubs (Tacoskálar) | B82: Taco Tubs (Tacoskálar) | D82: 200670 | E82: Kornvörur og hráefni | F82: Maís mjöl (74%), sólblómaolía, salt. | G82: Engir skráðir | I82: https://drive.google.com/file/d/1ahiLImnx9aj06P6g_IC6FDywSz9Ozmhm/view?usp=sharing | J82: 483 | K82: 25 | L82: 2.3 | M82: 56 | N82: 1.1 | O82: 5.7 | P82: 1.2 | Q82: 6.3 | R82: 400 | S82: GTIN: 07311312006707. 3625 g/kassa. Þurrgeymist 365 dagar. Vegan, glútenlaust. Upprunaland: Belgía.
A83: Tómatmauk Tomato paste 28% (Rapunzel) - Ekki í notkun | B83: Tómatmauk Tomato paste 28% (Rapunzel) - Ekki í notkun | C83: Rapunzel Naturkost | D83: 1300090 | E83: Niðursuðuvörur | F83: Tómatar | I83: Tómatmauk.pdf | J83: 111 | K83: 0.4 | L83: 0.1 | M83: 18.5 | N83: 12.8 | O83: 4.9 | P83: 0.1 | Q83: 3.7 | R83: 450 | S83: EAN: 4006040181156. 12 x 200 g túpur/kassa. Lífrænt (BIO/Bioagricert). Þurrgeymist 300 dagar. Vegan. Upprunaland: Ítalía.
A84: Tómatpuré Doppio Concentrato 800 g (Menu) | B84: Tómatpuré Doppio Concentrato 800 g (Menu) | C84: Menu SRL | D84: UU1 | E84: Niðursuðuvörur | F84: Tómatar | G84: Engir skráðir | I84: https://drive.google.com/file/d/1d9nwUjnSzxKmopD1MmL_m-j_PclKxewh/view?usp=sharing | J84: 113 | K84: 0.4 | L84: 0 | M84: 19 | N84: 14 | O84: 6 | P84: 0.1 | R84: 450 | S84: EAN: 8002960501759. 800 g dós, 12 í kassa. Þurrgeymist. Geymsluþol 24 mánuðir. Upprunaland: Ítalía.
A85: BL Garden Veg. Burger (Vegan buff) | B85: BL Garden Veg. Burger (Vegan buff) | C85: Bauernland / Danco | D85: 5809 | E85: Plöntubasað | F85: Grænmeti (kartöflur, brokkolí, gulrætur, baunir), **hveiti**mjöl, sólblómaolía, **hveiti**semólína, laukur, borðsalt, sterkja, dextrósi, gerextrakt, ger, sykur, krydd, repjuolía, joðbætt salt (salt, kalíumjoðíð), kryddjurtir. | G85: Glúten (hveiti). | I85: https://drive.google.com/file/d/16HV_oLt59KqpUADMnnBT6NSexgTGM5UJ/view?usp=sharing | J85: 177 | K85: 8.3 | L85: 1 | M85: 20 | N85: 4 | O85: 3.8 | P85: 1.4 | Q85: 3.5 | R85: 1800 | S85: GTIN: 9001969158093. ~100 g/stk. 4 x 1,5 kg/ks. Frystivara -18°C, geymsluþol 15 mánuðir. Vegan.
A86: Garden Gourmet Sensational Fillet Pieces (Vegan kjúklingabitar) | B86: Garden Gourmet Sensational Fillet Pieces (Vegan kjúklingabitar) | C86: Nestlé Professional/ Innnes | D86: 125018 | E86: Plöntubasað | F86: Endurvatnað **soja**próteinþykkni 89,6% (vatn, **soja**próteinþykkni 32,3%), vínedik, sólblómaolía, gerextrakt, bragðefni. | G86: Soja | H86: Getur innihaldið snefil af hveiti | I86: https://drive.google.com/file/d/1ETeaMDmW9SietlS1LO9OpNsUqOW79oWc/view?usp=sharing | J86: 153 | K86: 4.7 | L86: 0.4 | M86: 1.2 | N86: 0.1 | O86: 22.5 | P86: 0.6 | Q86: 8 | R86: 1800 | S86: EAN: 08445291307636. 3 x 2 kg. Frystivara -18°C, geymsluþol 15 mánuðir. Vegan.
A87: Garden Gourmet / Hälsans Kök Vegan Mince (Vegan hakk) | B87: Garden Gourmet / Hälsans Kök Vegan Mince (Vegan hakk) | C87: Nestlé Professional/ Innnes | D87: 12592004 | E87: Plöntubasað | F87: Endurvatnað **soja**prótein 93,9% (vatn, **soja**próteinþykkni 30%), sólblómaolía, **bygg**maltextrakt, laukduft, náttúruleg bragðefni, hvítlauksduft, salt, paprikuduft, svartur pipar, kúmen. | G87: Glúten (bygg), soja | I87: https://drive.google.com/file/d/1dLk5SlPKdYyJqdOZST2ULLFV06BQ8Wyr/view?usp=sharing | J87: 128 | K87: 2.5 | L87: 0.3 | M87: 1.8 | N87: 0.6 | O87: 21.2 | P87: 0.3 | Q87: 6.7 | R87: 1800 | S87: EAN: 08445291347403. 3 x 2 kg. Frystivara -18°C, geymsluþol 18 mánuðir. Vegan.
A88: Tomato Traditional Round Pizza Base (Vegan pizzabotn) | B88: Tomato Traditional Round Pizza Base (Vegan pizzabotn) | C88: Valpizza | D88: 1900 | E88: Brauð og bakkelsi | F88: **Hveiti**mjöl, vatn, tómatpúrra 26%, sólblómaolía, salt, ger, maltað **hveiti**mjöl, sykur, oregano, svartur pipar. | G88: Glúten (hveiti) | H88: Getur innihaldið snefil af fiski, sinnepi, soja og mjólk. | I88: https://drive.google.com/file/d/1jVXpwZuTyebCJ-h1nS5OcnGIQDoW5t_E/view?usp=sharing | J88: 195 | K88: 2.5 | L88: 0.5 | M88: 35 | N88: 1.5 | O88: 7 | P88: 1.2 | Q88: 2 | R88: 600 | S88: 285 g/stk. 29 ± 1 cm. Frystivara -18°C, geymsluþol 12 mánuðir. Þíðið ~10 mín, bakið 200-220°C í 4-6 mín.
A89: Chiliborgari (Veganborgari) | B89: Chiliborgari (Veganborgari) | C89: Álfasaga ehf. (Móðir Náttúra) | D89: 106 | E89: Plöntubasað | F89: **Bygg**, kjúklingabaunir, fennel, kartöflur, kartöflumjöl, tómatpúrra, chilimauk 1% (rauður chili, gulrætur, salt, paprika, sýrustillir E260, E330, bindiefni E412, E415, repjuolía, rotvarnarefni E202, E211, sítrónusafi, sýra E330, litarefni E160c), salt, hvítlaukur, krydd (steinselja, timían, rósmarín, basilika, majoram, estragon, oreganó), kúmen, kóríander. | G89: Glúten (bygg) | H89: Getur innihaldið snefil af hnetum og sesam. | I89: https://drive.google.com/file/d/1YQru_x8azI1hqGirhRjm-Qm2o17OCDE0/view?usp=sharing | J89: 272 | K89: 2.6 | L89: 0.4 | M89: 47.2 | N89: 1.3 | O89: 10.2 | P89: 0.9 | Q89: 9.5 | R89: 1800 | S89: EAN: 5694311277760. 120 g/stk. Kælivara 0-4°C. Tilbúið til neyslu. Vegan.
A90: Nautgripahakk 2 kg frosið | B90: Nautgripahakk 2 kg frosið | C90: Kjarnafæði Norðlenska hf. | D90: 50003 | E90: Kjöt / Alifuglar | F90: Nautgripakjöt 100 %. | G90: Engir skráðir | I90: https://drive.google.com/file/d/1-vP8CdWqhbmoIHP2wGMBpmpDcUhmyKw4/view?usp=sharing | J90: 179 | K90: 11 | L90: 3.1 | M90: 0 | N90: 0 | O90: 20 | P90: 0.2 | Q90: 0 | R90: 2000 | S90: 2 kg/stk. Frystivara -18°C. Geymsluþol 360 dagar. Uppruni: Þýskaland.
A91: Nautgripahakk ferskt Erlent | B91: Nautgripahakk 2 kg frosið | C91: Kjarnafæði Norðlenska hf. | D91: 50003 | E91: Kjöt / Alifuglar | F91: Nautgripakjöt 100 %. | G91: Engir skráðir | I91: https://drive.google.com/file/d/1-vP8CdWqhbmoIHP2wGMBpmpDcUhmyKw4/view?usp=sharing | J91: 179 | K91: 11 | L91: 3.1 | M91: 0 | N91: 0 | O91: 20 | P91: 0.2 | Q91: 0 | R91: 2450 | S91: ferskt 0-4'c. Uppruni: Þýskaland.
A92: Bláber frosið (Wild Blueberries) | B92: Bláber frosið (Wild Blueberries) | C92: N.V. d'Arta | E92: Ávextir og ber | F92: Bláber | G92: Engir skráðir | I92: https://drive.google.com/file/d/1XJ1WHz_-GsR3Kmtlg7CIktpTVkuGTSa7/view?usp=sharing | J92: 37 | K92: 0.5 | L92: 0.1 | M92: 3.7 | N92: 2.1 | O92: 0 | P92: 0 | R92: 1200 | S92: IQF. 5 x 1 kg pakki. Frystivara -20°C. Geymsluþol 30 mánuðir. Uppruni: Kanada, Evrópa.
A93: Bláber Ardo | B93: Bláber ardo | C93: Ardo/Garri | E93: Ávextir og ber | F93: Bláber | G93: Engir skráðir | I93: https://garri.overcastcdn.com/documents/420XBO310.pdf | J93: 37 | K93: 0.5 | L93: 0.1 | M93: 3.7 | N93: 2.1 | O93: 0 | P93: 0 | R93: 811
A94: Blómkál frosið (Cauliflower florets 15/35 mm) | B94: Blómkál frosið (Cauliflower florets 15/35 mm) | C94: Ardo/Garri | D94: BLG610 | E94: Grænmeti | F94: Blómkál | G94: Engir skráðir | I94: https://drive.google.com/file/d/1_7ul9uB97dD2-zXWYH8o_SDakGyLr6xe/view?usp=sharing | J94: 31 | K94: 0.9 | L94: 0.2 | M94: 2.1 | N94: 1.8 | O94: 2.9 | P94: 0 | Q94: 1.6 | R94: 400 | S94: Florets 15/35 mm. Blanched. Frystivara -18°C. GMO-free.
A95: Fennel frosinn (Diced Fennel) | B95: Fennel frosinn (Diced Fennel) | C95: Ardo/Garri | D95: VEN610 | E95: Grænmeti | F95: Fennika | G95: Engir skráðir | I95: https://drive.google.com/file/d/13GbGHeuMDCDu9-4phkA2Gb6N7Glr04GZ/view?usp=sharing | J95: 17 | K95: 0.2 | M95: 1.8 | N95: 1.7 | O95: 0.9 | P95: 0.5 | Q95: 2.3 | R95: 400 | S95: Diced 10x10 mm. Blanched. Frystivara -18°C. GMO-free.
A96: Forsteiktur laukur (Pre-fried sliced onions) | B96: Forsteiktur laukur (Pre-fried sliced onions) | C96: Ardo/Garri | E96: Grænmeti | F96: Laukur (90%), repjuolía (10%). | G96: Engir skráðir | I96: https://drive.google.com/file/d/1qe8jA8Hk6RxXOyfM7cBQ5h9W5KAo2CVf/view?usp=sharing | J96: 114 | K96: 8.6 | L96: 1.1 | M96: 6.9 | N96: 3.9 | O96: 1.2 | P96: 0 | Q96: 1.9 | R96: 400 | S96: Geymsluþol 24 mánuðir. Frystivara -18°C. Uppruni lauksins: ESB.
A97: Grænmetisbollur | B97: Grænmetisbollur | C97: Álfasaga ehf. (Móðir Náttúra) | D97: 220 | E97: Plöntubasað | F97: Vatn, **bygg**, kjúklingabaunir, sætar kartöflur, svartar baunir, laukur, kartöflur, baunaprótein, repjuolía, hvítlaukur, bindiefni (E461), sterkja, tómatpúrra, salt, basil, papríkukrydd, hvítur pipar, rósmarín. | G97: Glúten (bygg) | H97: Gæti innihaldið snefil af hnetum og sesam. | I97: https://drive.google.com/file/d/1PX_eU1Wgs2dzM0SbE9-EHWEIiCDqMv88/view?usp=sharing | J97: 264 | K97: 7.8 | L97: 0.7 | M97: 29.9 | N97: 2.8 | O97: 13.3 | P97: 1.7 | Q97: 10.5 | R97: 1800 | S97: 5 kg í kassa. Kælivara 0-4°C. Tilbúið til neyslu. Vegan.
A98: Hvítlaukur í olíu (Crushed garlic, coarse cut with oil) | B98: Hvítlaukur í olíu (Crushed garlic, coarse cut with oil) | C98: APPETIT Levnedsmidler A/S / Wiik & Co. | E98: Grænmeti | F98: Hvítlaukur 95%, repjuolía 4%, mjólkursýra (E270) 1%. | G98: Súlfít | I98: https://drive.google.com/file/d/1LQQG6zdc-XSLzYb6RKlxdzBpQOUufTtB/view?usp=sharing | J98: 153 | K98: 4.2 | L98: 0 | M98: 23.4 | N98: 0 | O98: 5.1 | P98: 0 | R98: 900 | S98: Geymsla 2-22°C. Geymsluþol 12 mánuðir. Eftir opnun: 2-8°C. Upprunaland: Danmörk.
A99: Jarðarber frosið | B99: Jarðarber frosið | C99: Global Food Link S.L.U. | D99: 228004 | E99: Ávextir og ber | F99: Jarðarber | G99: Engir skráðir | I99: https://drive.google.com/file/d/19LpgAetZiskpHR9eV63DDPNUbJkWcOya/view?usp=sharing | J99: 43 | K99: 0.5 | L99: 0.1 | M99: 9.1 | N99: 4.6 | O99: 0.4 | P99: 0 | Q99: 2.1 | R99: 700 | S99: IQF. Frystivara -18°C. Geymsluþol 24 mánuðir. Uppruni: Egyptaland.
A100: Jarðarber frosin Ardo | B100: Jarðarber frosið Ardo | C100: Ardo/Garri | D100: 42005005 | E100: Ávextir og ber | F100: Jarðarber | G100: Engir skráðir | I100: https://garri.overcastcdn.com/documents/42005005.pdf | J100: 43 | K100: 0.5 | L100: 0.1 | M100: 9.1 | N100: 4.6 | O100: 0.4 | P100: 0 | Q100: 2.1 | R100: 990
...

Sheet Réttabanki
A1: RÉTTABANKI – UPPSKRIFTIR
A2: Heiti réttar | B2: Vara (leitarnafn) | C2: Magn (g/100kg) | D2: Innihaldslýsing (sjálfvirkt) | E2: Ofnæmisvaldar (sjálfvirkt) | F2: Fyrirvari (sjálfvirkt) | G2: Orka (kcal/100g) | H2: Fita (g/100g) | I2: Mettuð fita (g/100g) | J2: Kolvetni (g/100g) | K2: Sykur (g/100g) | L2: Prótein (g/100g) | M2: Salt (g/100g) | N2: Trefjar (g/100g) | O2: Foodcost (kr/100kg) | P2: Athugasemd | Q2: Eldunarleiðbeiningar | R2: Eldunarleiðbeiningar (template) | S2: Réttur (fyllt niður) | T2: Línukostnaður (kr) | U2: Kostnaður (kr/kg réttar) | W2: (lykill)
A3: Pasta með kjötbollum í mildri tómatsósu | D3: Kinda- og nautgripakjöt 50% (uppruni Ísland), grænmeti 41% (kartöflur, brokkólí, laukur, gulrætur), kartöflusterkja, salt, krydd (pipar, oregano, basil, paprika) | Tómatar | Laukur | Gulrætur | Vatn | Súkrósi | Oregano 100% (Origanum vulgare L.). | Svartur pipar 100% (Piper nigrum), hitaþurrkað. | Hvítlaukur 95%, repjuolía 4%, mjólkursýra (E270) 1%. | Salt (salt, kekkjavarnarefni E535, lyftiefni E500). | Maíssterkja. | Repjuolía | Grænmetiskraftur (vatn, laukur, gulrótþykkni, tómatur, **sellerí**rót, jurtaextrakt), bragðefni, glúkósasíróp, gerþykkni, salt, litarefni (karamellusykur), repjuolía, maltódextrín, sykur. | E3: Súlfít, Sellerí | G3: 117.83 | H3: 7.2 | I3: 2.65 | J3: 16.4 | L3: 7.25 | M3: 2.62 | N3: 0.3 | P3: Í-Mat / Matarstund | Pastahlutfall 40%, sósa og kjötbollur 60% | Q3: 1. Hitið sósu í potti við meðalhita í 15-20 mín, hrærið reglulega. 2. Hitið kjötbollur í ofni 180°C í 10-12 mín. 3. Eldið pasta skv. leiðbeiningum á pakka. 4. Berið fram með pasta og kjötbollum í sósu. | R3: Hitið sósu í potti við meðalhita í 15-20 mín. Hitið kjötbollur í ofni 180°C í 10-12 mín. Eldið pasta skv. leiðbeiningum. Berið fram saman. | S3: Pasta með kjötbollum í mildri tómatsósu | U3: 977 kr/kg | W3: Pasta með kjötbollum í mildri tómatsósu
B4: Skólabollur, Kjöt og grænmeti | C4: 25000 | D4: Kinda- og nautgripakjöt 50% (uppruni Ísland), grænmeti 41% (kartöflur, brokkólí, laukur, gulrætur), kartöflusterkja, salt, krydd (pipar, oregano, basil, paprika) | G4: 110 | H4: 12 | I4: 6 | J4: 12 | K4: 0.6 | L4: 12 | M4: 1.6 | O4: 45 | S4: Pasta með kjötbollum í mildri tómatsósu | T4: 45000 | W4: Pasta með kjötbollum í mildri tómatsósu
B5: Tómatpuré Doppio Concentrato 800 g (Menu) | C5: 18000 | D5: Tómatar | E5: Engir skráðir | G5: 113 | H5: 0.4 | I5: 0 | J5: 19 | K5: 14 | L5: 6 | M5: 0.1 | O5: 8 | S5: Pasta með kjötbollum í mildri tómatsósu | T5: 8100 | W5: Pasta með kjötbollum í mildri tómatsósu
B6: Laukur (ferskur) | C6: 5000 | D6: Laukur | E6: Engir skráðir | G6: 40 | H6: 0.1 | I6: 0 | J6: 9.3 | K6: 4.2 | L6: 1.1 | M6: 0 | N6: 1.7 | O6: 1 | S6: Pasta með kjötbollum í mildri tómatsósu | T6: 1250 | W6: Pasta með kjötbollum í mildri tómatsósu
B7: Gulrætur (ferskar) | C7: 3000 | D7: Gulrætur | E7: Engir skráðir | G7: 41 | H7: 0.2 | I7: 0 | J7: 9.6 | K7: 4.7 | L7: 0.9 | M7: 0.1 | N7: 2.8 | O7: 1 | S7: Pasta með kjötbollum í mildri tómatsósu | T7: 750 | W7: Pasta með kjötbollum í mildri tómatsósu
B8: Vatn | C8: 4000 | D8: Vatn | E8: Engir skráðir | G8: 0 | H8: 0 | I8: 0 | J8: 0 | K8: 0 | L8: 0 | M8: 0 | N8: 0 | O8: 0 | S8: Pasta með kjötbollum í mildri tómatsósu | T8: 400 | W8: Pasta með kjötbollum í mildri tómatsósu
B9: Crystal Sugar (Sykur) | C9: 300 | D9: Súkrósi | E9: Engir skráðir | G9: 400 | H9: 0 | I9: 0 | J9: 100 | K9: 100 | L9: 0 | M9: 0 | N9: 0 | O9: 0 | S9: Pasta með kjötbollum í mildri tómatsósu | T9: 105 | W9: Pasta með kjötbollum í mildri tómatsósu
B10: Oregano | C10: 80 | D10: Oregano 100% (Origanum vulgare L.). | F10: Framleitt á svæði þar sem unnið er með glúten, fisk, krabbadýr, lindýr, mjólk, soja, sellerí, sinnep og sesam. | G10: 480 | H10: 10 | I10: 2.7 | J10: 64 | K10: 4.1 | L10: 11 | M10: 0 | O10: 1 | S10: Pasta með kjötbollum í mildri tómatsósu | T10: 788 | W10: Pasta með kjötbollum í mildri tómatsósu
B11: Svartur pipar, malaður | C11: 40 | D11: Svartur pipar 100% (Piper nigrum), hitaþurrkað. | F11: Framleitt á svæði þar sem unnið er með glúten, fisk, krabbadýr, lindýr, mjólk, soja, sellerí, sinnep og sesam. | G11: 386 | H11: 3.3 | I11: 1 | J11: 65 | K11: 0.6 | L11: 11 | M11: 0.1 | O11: 0 | S11: Pasta með kjötbollum í mildri tómatsósu | T11: 280 | W11: Pasta með kjötbollum í mildri tómatsósu
B12: Hvítlaukur í olíu (Crushed garlic, coarse cut with oil) | C12: 300 | D12: Hvítlaukur 95%, repjuolía 4%, mjólkursýra (E270) 1%. | E12: Súlfít | S12: Pasta með kjötbollum í mildri tómatsósu | T12: 270 | W12: Pasta með kjötbollum í mildri tómatsósu
B13: Borðsalt | C13: 800 | D13: Salt (salt, kekkjavarnarefni E535, lyftiefni E500). | E13: Engir skráðir | F13: Framleitt á svæði þar sem unnið er með mjólk, glúten, egg, sesam, sellerí, soja og sinnep. | G13: 0 | H13: 0 | I13: 0 | J13: 0 | K13: 0 | L13: 0 | M13: 100 | O13: 0 | S13: Pasta með kjötbollum í mildri tómatsósu | T13: 96 | W13: Pasta með kjötbollum í mildri tómatsósu
B14: Tómat kryddblanda | C14: 80 | S14: Pasta með kjötbollum í mildri tómatsósu | T14: 48 | W14: Pasta með kjötbollum í mildri tómatsósu
B15: Maizenamjöl (majssterkja) | C15: 1200 | D15: Maíssterkja. | E15: Engir skráðir | O15: 0 | S15: Pasta með kjötbollum í mildri tómatsósu | T15: 480 | W15: Pasta með kjötbollum í mildri tómatsósu
B16: Repjuolía | C16: 1200 | D16: Repjuolía | E16: Engir skráðir | S16: Pasta með kjötbollum í mildri tómatsósu | T16: 474 | W16: Pasta með kjötbollum í mildri tómatsósu
B17: Nautakraftur Vegan | C17: 1000 | D17: Grænmetiskraftur (vatn, laukur, gulrótþykkni, tómatur, **sellerí**rót, jurtaextrakt), bragðefni, glúkósasíróp, gerþykkni, salt, litarefni (karamellusykur), repjuolía, maltódextrín, sykur. | E17: Sellerí | S17: Pasta með kjötbollum í mildri tómatsósu | T17: 600 | W17: Pasta með kjötbollum í mildri tómatsósu
A18: Lambakjötspottréttur með kartöflum | D18: Lambakjöt 100% (Ísland) | Gulrætur | Fersk paprika | **Sellerí** | Laukur | Tómatar | Salt (salt, kekkjavarnarefni E535, lyftiefni E500). | Svartur pipar 100% (Piper nigrum), hitaþurrkað. | Repjuolía | Grænmetiskraftur (vatn, laukur, gulrótþykkni, tómatur, **sellerí**rót, jurtaextrakt), bragðefni, glúkósasíróp, gerþykkni, salt, litarefni (karamellusykur), repjuolía, maltódextrín, sykur. | Hvítlauksduft 100% | Þurrkað rósmarín (Rosmarinus officinalis) | Vatn | Maíssterkja. | E18: Engir, Sellerí | G18: 113.55 | H18: 6.55 | I18: 2.39 | J18: 7.33 | L18: 6.86 | M18: 1.08 | N18: 1.8 | P18: Matarstund | LP-100KG-20260529 | Q18: 1. Hitið pottrétt í ofni 160°C í 45-60 mín. 2. Potturinn er tilbúinn þegar kjötið er mjúkt. 3. Berið fram heitt. | R18: Hitið pottrétt í ofni 160°C í 45-60 mín. Tilbúinn þegar kjötið er mjúkt. Berið fram heitt. | S18: Lambakjötspottréttur með kartöflum | U18: 1.659 kr/kg | W18: Lambakjötspottréttur með kartöflum
B19: Lambakjöt teningar | C19: 35000 | D19: Lambakjöt 100% (Ísland) | E19: Engir skráðir | G19: 77 | H19: 0.1 | I19: 0 | J19: 17 | K19: 0.8 | L19: 2 | M19: 0 | N19: 2.2 | O19: 137 | S19: Lambakjötspottréttur með kartöflum | T19: 136500 | W19: Lambakjötspottréttur með kartöflum
B20: Gulrætur (ferskar) | C20: 18000 | D20: Gulrætur | E20: Engir skráðir | G20: 41 | H20: 0.2 | I20: 0 | J20: 9.6 | K20: 4.7 | L20: 0.9 | M20: 0.1 | N20: 2.8 | O20: 5 | S20: Lambakjötspottréttur með kartöflum | T20: 4500 | W20: Lambakjötspottréttur með kartöflum
B21: Paprika (fersk) | C21: 18000 | D21: Fersk paprika | E21: Engir | S21: Lambakjötspottréttur með kartöflum | T21: 14400 | W21: Lambakjötspottréttur með kartöflum
B22: Sellerí (ferskt) | C22: 2000 | D22: **Sellerí** | E22: Sellerí | S22: Lambakjötspottréttur með kartöflum | T22: 1000 | W22: Lambakjötspottréttur með kartöflum
B23: Laukur (ferskur) | C23: 12000 | D23: Laukur | E23: Engir skráðir | G23: 40 | H23: 0.1 | I23: 0 | J23: 9.3 | K23: 4.2 | L23: 1.1 | M23: 0 | N23: 1.7 | O23: 3 | S23: Lambakjötspottréttur með kartöflum | T23: 3000 | W23: Lambakjötspottréttur með kartöflum
B24: Tómatpuré Doppio Concentrato 800 g (Menu) | C24: 2500 | D24: Tómatar | E24: Engir skráðir | G24: 113 | H24: 0.4 | I24: 0 | J24: 19 | K24: 14 | L24: 6 | M24: 0.1 | O24: 1 | S24: Lambakjötspottréttur með kartöflum | T24: 1125 | W24: Lambakjötspottréttur með kartöflum
B25: Borðsalt | C25: 600 | D25: Salt (salt, kekkjavarnarefni E535, lyftiefni E500). | E25: Engir skráðir | F25: Framleitt á svæði þar sem unnið er með mjólk, glúten, egg, sesam, sellerí, soja og sinnep. | G25: 0 | H25: 0 | I25: 0 | J25: 0 | K25: 0 | L25: 0 | M25: 100 | O25: 0 | S25: Lambakjötspottréttur með kartöflum | T25: 72 | W25: Lambakjötspottréttur með kartöflum
B26: Svartur pipar, malaður | C26: 80 | D26: Svartur pipar 100% (Piper nigrum), hitaþurrkað. | F26: Framleitt á svæði þar sem unnið er með glúten, fisk, krabbadýr, lindýr, mjólk, soja, sellerí, sinnep og sesam. | G26: 386 | H26: 3.3 | I26: 1 | J26: 65 | K26: 0.6 | L26: 11 | M26: 0.1 | O26: 1 | S26: Lambakjötspottréttur með kartöflum | T26: 560 | W26: Lambakjötspottréttur með kartöflum
B27: Repjuolía | C27: 1500 | D27: Repjuolía | E27: Engir skráðir | S27: Lambakjötspottréttur með kartöflum | T27: 593 | W27: Lambakjötspottréttur með kartöflum
B28: Nautakraftur Vegan | C28: 1200 | D28: Grænmetiskraftur (vatn, laukur, gulrótþykkni, tómatur, **sellerí**rót, jurtaextrakt), bragðefni, glúkósasíróp, gerþykkni, salt, litarefni (karamellusykur), repjuolía, maltódextrín, sykur. | E28: Sellerí | S28: Lambakjötspottréttur með kartöflum | T28: 720 | W28: Lambakjötspottréttur með kartöflum
B29: Hvítlauksduft (Vitlökspulver) | C29: 400 | D29: Hvítlauksduft 100% | E29: Engir skráðir | F29: Framleitt á svæði þar sem unnið er með glúten, fisk, krabbadýr, lindýr, mjólk, soja, sellerí, sinnep og sesam. | S29: Lambakjötspottréttur með kartöflum | T29: 1725 | W29: Lambakjötspottréttur með kartöflum
B30: Timían | C30: 100 | S30: Lambakjötspottréttur með kartöflum | T30: 300 | W30: Lambakjötspottréttur með kartöflum
B31: Rósmarín (þurrkað) | C31: 50 | D31: Þurrkað rósmarín (Rosmarinus officinalis) | E31: Engir skráðir | F31: Framleitt á svæði þar sem unnið er með glúten, fisk, mjólk, soja, sellerí, sinnep og sesam. | S31: Lambakjötspottréttur með kartöflum | T31: 150 | W31: Lambakjötspottréttur með kartöflum
B32: Vatn | C32: 7350 | D32: Vatn | E32: Engir skráðir | G32: 0 | H32: 0 | I32: 0 | J32: 0 | K32: 0 | L32: 0 | M32: 0 | N32: 0 | O32: 1 | S32: Lambakjötspottréttur með kartöflum | T32: 735 | W32: Lambakjötspottréttur með kartöflum
B33: Maizenamjöl (majssterkja) | C33: 1200 | D33: Maíssterkja. | E33: Engir skráðir | O33: 0 | S33: Lambakjötspottréttur með kartöflum | T33: 480 | W33: Lambakjötspottréttur með kartöflum
A34: Mildur kjúklingakarrýréttur | D34: Úrbeinuð, skinnlaus kjúklingalæri | Fersk paprika | Laukur (90%), repjuolía (10%). | Gulrætur | Kókosmjólk, vatn, gúargúmmí. | Grænmetiskraftur (vatn, laukur, gulrótarsafi, tómatur, jurtaextrakt), glúkósasíróp, bragðefni, salt, gerextrakt, maltódextrín, sykur, sólblómaolía. | Hvítlauksduft 100% | Maíssterkja. | Salt, svartur pipar, hvítlaukur, paprikubitar, laukur, steinselja, dextrósi, timían, estragon. | Túrmerik, dillfræ, fenugreek (grikkjasmári), kóríander, cayennepipar, svartur pipar, negull. | Salt (salt, kekkjavarnarefni E535, lyftiefni E500). | Svartur pipar 100% (Piper nigrum), hitaþurrkað. | Vatn | E34: Engir | G34: 123.69 | H34: 7.79 | I34: 3.39 | J34: 5.39 | L34: 8.81 | M34: 1.55 | N34: 0.7 | P34: Matarstund | MK-100KG-20260529 | Q34: 1. Hitið karrýsósu í potti við meðalhita í 20-25 mín, hrærið reglulega. 2. Eldið hrísgrjón skv. leiðbeiningum. 3. Berið fram karrý yfir hrísgrjónum. | R34: Hitið karrýsósu í potti við meðalhita í 20-25 mín, hrærið reglulega. Eldið hrísgrjón skv. leiðbeiningum. Berið fram. | S34: Mildur kjúklingakarrýréttur | U34: 1.017 kr/kg | W34: Mildur kjúklingakarrýréttur
B35: Kjúklingalærkjöt - Rose | C35: 35000 | D35: Úrbeinuð, skinnlaus kjúklingalæri | G35: 137 | H35: 9 | I35: 2.3 | L35: 14 | M35: 0.8 | O35: 61 | S35: Mildur kjúklingakarrýréttur | T35: 60690 | W35: Mildur kjúklingakarrýréttur
B36: Paprika (fersk) | C36: 6000 | D36: Fersk paprika | E36: Engir | O36: 5 | R36: GUFA 98°C, lok á, kjarnhiti 75°C. Hrá: 3,3 kg hrísgrjón + 5 kg sjóðandi vatn, 55 mín. Endurhituð: 25 mín. | S36: Mildur kjúklingakarrýréttur | T36: 4800 | W36: Mildur kjúklingakarrýréttur
B37: Forsteiktur laukur (Pre-fried sliced onions) | C37: 8000 | D37: Laukur (90%), repjuolía (10%). | E37: Engir skráðir | G37: 114 | H37: 8.6 | I37: 1.1 | J37: 6.9 | K37: 3.9 | L37: 1.2 | M37: 0 | N37: 1.9 | O37: 3 | S37: Mildur kjúklingakarrýréttur | T37: 3200 | W37: Mildur kjúklingakarrýréttur
B38: Gulrætur (ferskar) | C38: 8000 | D38: Gulrætur | E38: Engir skráðir | G38: 41 | H38: 0.2 | I38: 0 | J38: 9.6 | K38: 4.7 | L38: 0.9 | M38: 0.1 | N38: 2.8 | O38: 2 | S38: Mildur kjúklingakarrýréttur | T38: 2000 | W38: Mildur kjúklingakarrýréttur
B39: Kókosmjólk Roland Coconut Milk | C39: 12000 | D39: Kókosmjólk, vatn, gúargúmmí. | E39: Engir skráðir | G39: 181 | H39: 18 | I39: 15.3 | J39: 2.8 | K39: 1 | L39: 2 | M39: 0 | N39: 0 | O39: 5 | S39: Mildur kjúklingakarrýréttur | T39: 5400 | W39: Mildur kjúklingakarrýréttur
B40: Kjúklingakraftur Vegan (Essential Cuisine) | C40: 1200 | D40: Grænmetiskraftur (vatn, laukur, gulrótarsafi, tómatur, jurtaextrakt), glúkósasíróp, bragðefni, salt, gerextrakt, maltódextrín, sykur, sólblómaolía. | S40: Mildur kjúklingakarrýréttur | T40: 720 | W40: Mildur kjúklingakarrýréttur
B41: Hvítlauksduft (Vitlökspulver) | C41: 500 | D41: Hvítlauksduft 100% | E41: Engir skráðir | F41: Framleitt á svæði þar sem unnið er með glúten, fisk, krabbadýr, lindýr, mjólk, soja, sellerí, sinnep og sesam. | G41: 385 | H41: 0.8 | I41: 0.1 | J41: 73 | K41: 24 | L41: 17 | M41: 0.1 | O41: 2 | S41: Mildur kjúklingakarrýréttur | T41: 2157 | W41: Mildur kjúklingakarrýréttur
B42: Maizenamjöl (majssterkja) | C42: 1000 | D42: Maíssterkja. | E42: Engir skráðir | O42: 0 | S42: Mildur kjúklingakarrýréttur | T42: 400 | W42: Mildur kjúklingakarrýréttur
B43: Hvítlauksblanda Ört & Vitlökskrydda | C43: 500 | D43: Salt, svartur pipar, hvítlaukur, paprikubitar, laukur, steinselja, dextrósi, timían, estragon. | E43: Engir skráðir | F43: Framleitt á svæði þar sem unnið er með glúten, fisk, krabbadýr, lindýr, mjólk, soja, sellerí, sinnep og sesam. | S43: Mildur kjúklingakarrýréttur | W43: Mildur kjúklingakarrýréttur
B44: Karríduft (Curry powder) | C44: 500 | D44: Túrmerik, dillfræ, fenugreek (grikkjasmári), kóríander, cayennepipar, svartur pipar, negull. | E44: Engir skráðir | F44: Framleitt á svæði þar sem unnið er með glúten, fisk, mjólk, soja, sellerí, sinnep og sesam. | S44: Mildur kjúklingakarrýréttur | T44: 1500 | W44: Mildur kjúklingakarrýréttur
B45: Borðsalt | C45: 600 | D45: Salt (salt, kekkjavarnarefni E535, lyftiefni E500). | E45: Engir skráðir | F45: Framleitt á svæði þar sem unnið er með mjólk, glúten, egg, sesam, sellerí, soja og sinnep. | G45: 0 | H45: 0 | I45: 0 | J45: 0 | K45: 0 | L45: 0 | M45: 100 | O45: 0 | S45: Mildur kjúklingakarrýréttur | T45: 72 | W45: Mildur kjúklingakarrýréttur
B46: Svartur pipar, malaður | C46: 100 | D46: Svartur pipar 100% (Piper nigrum), hitaþurrkað. | F46: Framleitt á svæði þar sem unnið er með glúten, fisk, krabbadýr, lindýr, mjólk, soja, sellerí, sinnep og sesam. | G46: 386 | H46: 3.3 | I46: 1 | J46: 65 | K46: 0.6 | L46: 11 | M46: 0.1 | O46: 1 | S46: Mildur kjúklingakarrýréttur | T46: 700 | W46: Mildur kjúklingakarrýréttur
B47: Vatn | C47: 7600 | D47: Vatn | E47: Engir skráðir | G47: 0 | H47: 0 | I47: 0 | J47: 0 | K47: 0 | L47: 0 | M47: 0 | N47: 0 | O47: 1 | S47: Mildur kjúklingakarrýréttur | T47: 760 | W47: Mildur kjúklingakarrýréttur
A48: Kjúklingasúpa með núðlum og grænmeti | D48: Úrbeinuð og skinnlaus kjúklingalæri 80%, vatn 19%, salt, sykur, þráavarnarefni (E331, E301), sýrustillir (E262). | Vatn | **Hveiti**semólína, vatn | Grænmetiskraftur (vatn, laukur, gulrótarsafi, tómatur, jurtaextrakt), glúkósasíróp, bragðefni, salt, gerextrakt, maltódextrín, sykur, sólblómaolía. | Gulrætur | Laukur | Blaðlaukur | **Sellerí** | Hvítlauksduft 100% | Repjuolía | Þurrkuð steinselja (Petroselinum sativum Hoffm) | Salt (salt, kekkjavarnarefni E535, lyftiefni E500). | Svartur pipar 100% (Piper nigrum), hitaþurrkað. | E48: Glúten (hveiti), Sellerí | G48: 105.64 | H48: 3.29 | I48: 0.72 | J48: 13.26 | L48: 6.06 | M48: 1.96 | N48: 0.3 | P48: Matarstund | KSN-100KG-20260529 | Q48: 1. Hitið súpu í potti við meðalhita í 20-25 mín. 2. Bætið núðlum við 5 mín áður en þið berið fram. 3. Berið fram heitt með brauði. | R48: Hitið súpu í potti í 20-25 mín. Bætið núðlum við 5 mín áður en berið fram. Berið fram heitt. | S48: Kjúklingasúpa með núðlum og grænmeti | U48: 822 kr/kg | W48: Kjúklingasúpa með núðlum og grænmeti
B49: Kjúklingalæri úrbeinuð | C49: 25000 | D49: Úrbeinuð og skinnlaus kjúklingalæri 80%, vatn 19%, salt, sykur, þráavarnarefni (E331, E301), sýrustillir (E262). | G49: 137 | H49: 9 | I49: 2.3 | L49: 14 | M49: 0.8 | O49: 60 | S49: Kjúklingasúpa með núðlum og grænmeti | T49: 60000 | W49: Kjúklingasúpa með núðlum og grænmeti
B50: Vatn | C50: 45000 | D50: Vatn | E50: Engir skráðir | G50: 0 | H50: 0 | I50: 0 | J50: 0 | K50: 0 | L50: 0 | M50: 0 | N50: 0 | O50: 5 | S50: Kjúklingasúpa með núðlum og grænmeti | T50: 4500 | W50: Kjúklingasúpa með núðlum og grænmeti
B51: Núðlur | C51: 12000 | D51: **Hveiti**semólína, vatn | E51: Glúten (hveiti) | F51: Gæti innihaldið soja | S51: Kjúklingasúpa með núðlum og grænmeti | T51: 6000 | W51: Kjúklingasúpa með núðlum og grænmeti
B52: Kjúklingakraftur Vegan (Essential Cuisine) | C52: 5000 | D52: Grænmetiskraftur (vatn, laukur, gulrótarsafi, tómatur, jurtaextrakt), glúkósasíróp, bragðefni, salt, gerextrakt, maltódextrín, sykur, sólblómaolía. | G52: 278 | H52: 1.3 | I52: 0.1 | J52: 52.6 | K52: 36.5 | L52: 13.8 | M52: 27 | N52: 0.4 | O52: 3 | S52: Kjúklingasúpa með núðlum og grænmeti | T52: 3000 | W52: Kjúklingasúpa með núðlum og grænmeti
B53: Gulrætur (ferskar) | C53: 5000 | D53: Gulrætur | E53: Engir skráðir | G53: 41 | H53: 0.2 | I53: 0 | J53: 9.6 | K53: 4.7 | L53: 0.9 | M53: 0.1 | N53: 2.8 | O53: 1 | S53: Kjúklingasúpa með núðlum og grænmeti | T53: 1250 | W53: Kjúklingasúpa með núðlum og grænmeti
B54: Laukur (ferskur) | C54: 3000 | D54: Laukur | E54: Engir skráðir | G54: 40 | H54: 0.1 | I54: 0 | J54: 9.3 | K54: 4.2 | L54: 1.1 | M54: 0 | N54: 1.7 | O54: 1 | S54: Kjúklingasúpa með núðlum og grænmeti | T54: 750 | W54: Kjúklingasúpa með núðlum og grænmeti
B55: Blaðlaukur (ferskur) | C55: 2000 | D55: Blaðlaukur | E55: Engir skráðir | G55: 61 | H55: 0.3 | I55: 0 | J55: 14.2 | K55: 3.9 | L55: 1.5 | M55: 0 | N55: 1.8 | O55: 1 | S55: Kjúklingasúpa með núðlum og grænmeti | T55: 800 | W55: Kjúklingasúpa með núðlum og grænmeti
B56: Sellerí (ferskt) | C56: 1000 | D56: **Sellerí** | E56: Sellerí | G56: 16 | H56: 0.2 | I56: 0 | J56: 3 | K56: 1.3 | L56: 0.7 | M56: 0.1 | N56: 1.6 | O56: 1 | S56: Kjúklingasúpa með núðlum og grænmeti | T56: 500 | W56: Kjúklingasúpa með núðlum og grænmeti
B57: Hvítlauksduft (Vitlökspulver) | C57: 500 | D57: Hvítlauksduft 100% | E57: Engir skráðir | F57: Framleitt á svæði þar sem unnið er með glúten, fisk, krabbadýr, lindýr, mjólk, soja, sellerí, sinnep og sesam. | G57: 385 | H57: 0.8 | I57: 0.1 | J57: 73 | K57: 24 | L57: 17 | M57: 0.1 | O57: 2 | S57: Kjúklingasúpa með núðlum og grænmeti | T57: 2157 | W57: Kjúklingasúpa með núðlum og grænmeti
B58: Repjuolía | C58: 500 | D58: Repjuolía | E58: Engir skráðir | S58: Kjúklingasúpa með núðlum og grænmeti | T58: 198 | W58: Kjúklingasúpa með núðlum og grænmeti
B59: Steinselja (þurrkuð) | C59: 300 | D59: Þurrkuð steinselja (Petroselinum sativum Hoffm) | E59: Engir skráðir | F59: Framleitt á svæði þar sem unnið er með glúten, fisk, mjólk, soja, sellerí, sinnep og sesam. | S59: Kjúklingasúpa með núðlum og grænmeti | T59: 900 | W59: Kjúklingasúpa með núðlum og grænmeti
B60: Borðsalt | C60: 400 | D60: Salt (salt, kekkjavarnarefni E535, lyftiefni E500). | E60: Engir skráðir | F60: Framleitt á svæði þar sem unnið er með mjólk, glúten, egg, sesam, sellerí, soja og sinnep. | G60: 0 | H60: 0 | I60: 0 | J60: 0 | K60: 0 | L60: 0 | M60: 100 | O60: 0 | S60: Kjúklingasúpa með núðlum og grænmeti | T60: 48 | W60: Kjúklingasúpa með núðlum og grænmeti
B61: Svartur pipar, malaður | C61: 300 | D61: Svartur pipar 100% (Piper nigrum), hitaþurrkað. | F61: Framleitt á svæði þar sem unnið er með glúten, fisk, krabbadýr, lindýr, mjólk, soja, sellerí, sinnep og sesam. | G61: 386 | H61: 3.3 | I61: 1 | J61: 65 | K61: 0.6 | L61: 11 | M61: 0.1 | O61: 2 | S61: Kjúklingasúpa með núðlum og grænmeti | T61: 2100 | W61: Kjúklingasúpa með núðlum og grænmeti
A62: Pastagratín með osti og grænmeti | D62: Gerilsneydd **mjólk**, pálmaolía, kekkjavarnarefni (kartöflumjöl), salt, **mjólkursýrugerlar**, ostahleypir (örveruleg). | **Mjólk**, laktasaensím, D-vítamín. Síuð, fitusprengd og gerilsneydd. | Rjómi (**mjólk**) | Brokkolí | Fersk paprika | Gulrætur 100% | Laukur | Maíssterkja. | Repjuolía | Hvítlauksduft 100% | Salt (salt, kekkjavarnarefni E535, lyftiefni E500). | Svartur pipar, **sinnep**, laukur, rauð paprika, hvítlaukur. | E62: Mjólk, Engir, Sinnep | G62: 218.95 | H62: 13.73 | I62: 7.52 | J62: 7.2 | L62: 8.52 | M62: 1.04 | N62: 0.4 | P62: Matarstund | POG-100KG-20260529 | Q62: 1. Hitið gratín í ofni 180°C í 25-30 mín. 2. Gratínið er tilbúið þegar osturinn er gullinn. 3. Látið standa í 5 mín áður en þið berið fram. | R62: Hitið gratín í ofni 180°C í 25-30 mín. Tilbúið þegar osturinn er gullinn. Látið standa í 5 mín. | S62: Pastagratín með osti og grænmeti | U62: 780 kr/kg | W62: Pastagratín með osti og grænmeti
B63: Rifinn ostur – Pizzatopping mozzarella (Ulkjær) | C63: 18000 | D63: Gerilsneydd **mjólk**, pálmaolía, kekkjavarnarefni (kartöflumjöl), salt, **mjólkursýrugerlar**, ostahleypir (örveruleg). | E63: Mjólk | G63: 301 | H63: 21 | I63: 12 | J63: 3.2 | K63: 1 | L63: 24 | M63: 1.4 | N63: 0 | O63: 27 | S63: Pastagratín með osti og grænmeti | T63: 27000 | W63: Pastagratín með osti og grænmeti
B64: Nýmjólk 1 L (MS) | C64: 20000 | D64: **Mjólk**, laktasaensím, D-vítamín. Síuð, fitusprengd og gerilsneydd. | E64: Mjólk | F64: Laktósalaust. | G64: 67 | H64: 3.9 | I64: 2.3 | J64: 4.7 | K64: 4.7 | L64: 3.3 | M64: 0.1 | N64: 0 | O64: 4 | S64: Pastagratín með osti og grænmeti | T64: 4000 | W64: Pastagratín með osti og grænmeti
B65: Matreiðslurjómi (MS) | C65: 10000 | D65: Rjómi (**mjólk**) | E65: Mjólk | S65: Pastagratín með osti og grænmeti | T65: 9000 | W65: Pastagratín með osti og grænmeti
B66: Brokkolí (ferskt) | C66: 5000 | D66: Brokkolí | E66: Engir | S66: Pastagratín með osti og grænmeti | T66: 3000 | W66: Pastagratín með osti og grænmeti
B67: Paprika (fersk) | C67: 3000 | D67: Fersk paprika | E67: Engir | S67: Pastagratín með osti og grænmeti | T67: 2400 | W67: Pastagratín með osti og grænmeti
B68: Gulrætur sneiðar | C68: 4000 | D68: Gulrætur 100% | G68: 30 | H68: 0.4 | I68: 0.1 | J68: 4.4 | K68: 4.2 | L68: 0.6 | M68: 0.1 | N68: 3.2 | O68: 2 | S68: Pastagratín með osti og grænmeti | T68: 1600 | W68: Pastagratín með osti og grænmeti
B69: Laukur (ferskur) | C69: 2000 | D69: Laukur | E69: Engir skráðir | G69: 40 | H69: 0.1 | I69: 0 | J69: 9.3 | K69: 4.2 | L69: 1.1 | M69: 0 | N69: 1.7 | O69: 1 | S69: Pastagratín með osti og grænmeti | T69: 500 | W69: Pastagratín með osti og grænmeti
B70: Maizenamjöl (majssterkja) | C70: 1200 | D70: Maíssterkja. | E70: Engir skráðir | O70: 0 | S70: Pastagratín með osti og grænmeti | T70: 480 | W70: Pastagratín með osti og grænmeti
B71: Repjuolía | C71: 800 | D71: Repjuolía | E71: Engir skráðir | S71: Pastagratín með osti og grænmeti | T71: 316 | W71: Pastagratín með osti og grænmeti
B72: Hvítlauksduft (Vitlökspulver) | C72: 400 | D72: Hvítlauksduft 100% | E72: Engir skráðir | F72: Framleitt á svæði þar sem unnið er með glúten, fisk, krabbadýr, lindýr, mjólk, soja, sellerí, sinnep og sesam. | S72: Pastagratín með osti og grænmeti | T72: 1725 | W72: Pastagratín með osti og grænmeti
B73: Borðsalt | C73: 400 | D73: Salt (salt, kekkjavarnarefni E535, lyftiefni E500). | E73: Engir skráðir | F73: Framleitt á svæði þar sem unnið er með mjólk, glúten, egg, sesam, sellerí, soja og sinnep. | G73: 0 | H73: 0 | I73: 0 | J73: 0 | K73: 0 | L73: 0 | M73: 100 | O73: 0 | S73: Pastagratín með osti og grænmeti | T73: 48 | W73: Pastagratín með osti og grænmeti
B74: Piparblanda | C74: 200 | D74: Svartur pipar, **sinnep**, laukur, rauð paprika, hvítlaukur. | E74: Sinnep | F74: Framleitt á svæði þar sem unnið er með glúten, fisk, mjólk, soja, sellerí, sinnep og sesam. | G74: 386 | H74: 3.3 | I74: 1 | J74: 65 | K74: 0.6 | L74: 11 | M74: 0.1 | O74: 1 | S74: Pastagratín með osti og grænmeti | T74: 600 | W74: Pastagratín með osti og grænmeti
A75: Vegan mexicosúpa | D75: Pálmafita, tómatduft (20,5%), umbreytt maíssterkja, sykur, salt, bragðefni, maíssterkja, repjuolía, laukduft, þurrkað glúkósasíróp, þykkingarefni (xantangúmmí E415), sýra (eplasýra, mjólkursýra), hvítur pipar. | Rauð paprika 33%, græn paprika 33%, gul paprika 34% | Laukur (90%), repjuolía (10%). | Fennika | Grænmetiskraftur (vatn, laukur, gulrótarsafi, tómatur, jurtaextrakt), glúkósasíróp, bragðefni, salt, gerextrakt, maltódextrín, sykur, sólblómaolía. | Hvítlaukur | Salt (salt, kekkjavarnarefni E535, lyftiefni E500). | Grillað grænmeti: brokkólí 25%, kúrbítur 25%, eggaldin 20%, gul paprika 10%, rauð paprika 10%, laukur 10%, sólblómaolía. | Vatn | E75: Engir skráðir | G75: 54.16 | H75: 2.3 | I75: 0.85 | J75: 6.71 | L75: 1.34 | M75: 2.64 | N75: 0.7 | P75: Matarstund | FH-MEX-100KG-01 | Q75: 1. Hitið súpu í potti við meðalhita í 20-25 mín, hrærið reglulega. 2. Berið fram með brauði eða maístortillu. | R75: Hitið súpu í potti við meðalhita í 20-25 mín, hrærið reglulega. Berið fram með brauði. | S75: Vegan mexicosúpa | U75: 213 kr/kg | W75: Vegan mexicosúpa
B76: Tómatsúpugrunnur (Oscar) | C76: 5500 | D76: Pálmafita, tómatduft (20,5%), umbreytt maíssterkja, sykur, salt, bragðefni, maíssterkja, repjuolía, laukduft, þurrkað glúkósasíróp, þykkingarefni (xantangúmmí E415), sýra (eplasýra, mjólkursýra), hvítur pipar. | G76: 478 | H76: 29.4 | I76: 12.7 | J76: 47 | K76: 19.4 | L76: 4.8 | M76: 9.4 | N76: 3.3 | O76: 3 | S76: Vegan mexicosúpa | T76: 3300 | W76: Vegan mexicosúpa
B77: Paprikuteningar litblandir | C77: 2500 | D77: Rauð paprika 33%, græn paprika 33%, gul paprika 34% | G77: 28 | H77: 0.4 | I77: 0.1 | J77: 4.5 | K77: 4.3 | L77: 0.9 | M77: 0 | N77: 1.6 | O77: 1 | S77: Vegan mexicosúpa | T77: 1000 | W77: Vegan mexicosúpa
B78: Forsteiktur laukur (Pre-fried sliced onions) | C78: 2000 | D78: Laukur (90%), repjuolía (10%). | E78: Engir skráðir | G78: 114 | H78: 8.6 | I78: 1.1 | J78: 6.9 | K78: 3.9 | L78: 1.2 | M78: 0 | N78: 1.9 | O78: 1 | S78: Vegan mexicosúpa | T78: 800 | W78: Vegan mexicosúpa
B79: Fennel frosinn (Diced Fennel) | C79: 1250 | D79: Fennika | E79: Engir skráðir | G79: 17 | H79: 0.2 | J79: 1.8 | K79: 1.7 | L79: 0.9 | M79: 0.5 | N79: 2.3 | O79: 1 | S79: Vegan mexicosúpa | T79: 500 | W79: Vegan mexicosúpa
B80: Kjúklingakraftur Vegan (Essential Cuisine) | C80: 5000 | D80: Grænmetiskraftur (vatn, laukur, gulrótarsafi, tómatur, jurtaextrakt), glúkósasíróp, bragðefni, salt, gerextrakt, maltódextrín, sykur, sólblómaolía. | G80: 278 | H80: 1.3 | I80: 0.1 | J80: 52.6 | K80: 36.5 | L80: 13.8 | M80: 27 | N80: 0.4 | O80: 3 | S80: Vegan mexicosúpa | T80: 3000 | W80: Vegan mexicosúpa
B81: Hvítlaukur (ferskur) | C81: 400 | D81: Hvítlaukur | E81: Engir skráðir | G81: 149 | H81: 0.5 | I81: 0.1 | J81: 33.1 | K81: 1 | L81: 6.4 | M81: 0 | N81: 2.1 | O81: 1 | S81: Vegan mexicosúpa | T81: 600 | W81: Vegan mexicosúpa
B82: Borðsalt | C82: 500 | D82: Salt (salt, kekkjavarnarefni E535, lyftiefni E500). | E82: Engir skráðir | F82: Framleitt á svæði þar sem unnið er með mjólk, glúten, egg, sesam, sellerí, soja og sinnep. | G82: 0 | H82: 0 | I82: 0 | J82: 0 | K82: 0 | L82: 0 | M82: 100 | O82: 0 | S82: Vegan mexicosúpa | T82: 60 | W82: Vegan mexicosúpa
B83: Country Grill grænmetisblanda | C83: 9000 | D83: Grillað grænmeti: brokkólí 25%, kúrbítur 25%, eggaldin 20%, gul paprika 10%, rauð paprika 10%, laukur 10%, sólblómaolía. | G83: 57 | H83: 2.4 | I83: 0.5 | J83: 5.2 | K83: 3.8 | L83: 2 | M83: 0.2 | N83: 3.1 | O83: 4 | S83: Vegan mexicosúpa | T83: 3600 | W83: Vegan mexicosúpa
B84: Vatn | C84: 64526 | D84: Vatn | E84: Engir skráðir | G84: 0 | H84: 0 | I84: 0 | J84: 0 | K84: 0 | L84: 0 | M84: 0 | N84: 0 | O84: 6 | S84: Vegan mexicosúpa | T84: 6453 | W84: Vegan mexicosúpa
A85: Plokkfiskur - Mjólkurlaus | D85: Ýsa | Kartöflur | Laukur | Repjuolía | Vatn (64%), jurtaolía (29%) (pálmakjarni, pálmi), þurrkað glúkósasíróp (5%), umbreytt sterkja, salt, bindiefni (E339, gellangúmmí), ýruefni (lesitín, E435, E472b), litarefni (karótín), náttúruleg bragðefni. | Vatn | Maíssterkja. | Salt (salt, kekkjavarnarefni E535, lyftiefni E500). | Þurrkað vín, edik | Sykur, sykurreyrssíróp. | Múskat 100% (Myristica fragrans), hitaþurrkað. | Túrmerik, dillfræ, fenugreek (grikkjasmári), kóríander, cayennepipar, svartur pipar, negull. | Svartur pipar 100% (Piper nigrum), hitaþurrkað. | E85: Fiskur, Súlfít, Engir | G85: 115.06 | H85: 4.18 | I85: 2.62 | J85: 9.64 | L85: 10.05 | M85: 0.68 | N85: 0.9 | P85: Matarstund | PLK-100KG-20260529 | Q85: 1. Hitið í potti við lágan hita í 15-20 mín, hrærið reglulega. 2. Gætið þess að brenna ekki við botn. 3. Berið fram með rúgbrauði. | R85: Hitið í potti við lágan hita í 15-20 mín, hrærið reglulega. Gætið botnbruna. Berið fram með rúgbrauði. | S85: Plokkfiskur - Mjólkurlaus | U85: 1.135 kr/kg | W85: Plokkfiskur - Mjólkurlaus
B86: Ýsa | C86: 40000 | D86: Ýsa | E86: Fiskur | G86: 61 | H86: 1 | I86: 0 | J86: 0 | K86: 0 | L86: 14 | M86: 3 | O86: 84 | S86: Plokkfiskur - Mjólkurlaus | T86: 83600 | W86: Plokkfiskur - Mjólkurlaus
B87: Kartöflur (ferskar) | C87: 36000 | D87: Kartöflur | E87: Engir skráðir | G87: 77 | H87: 0.1 | I87: 0 | J87: 17 | K87: 0.8 | L87: 2 | M87: 0 | N87: 2.2 | O87: 7 | S87: Plokkfiskur - Mjólkurlaus | T87: 7200 | W87: Plokkfiskur - Mjólkurlaus
B88: Laukur (ferskur) | C88: 4500 | D88: Laukur | E88: Engir skráðir | G88: 40 | H88: 0.1 | I88: 0 | J88: 9.3 | K88: 4.2 | L88: 1.1 | M88: 0 | N88: 1.7 | O88: 1 | S88: Plokkfiskur - Mjólkurlaus | T88: 1125 | W88: Plokkfiskur - Mjólkurlaus
B89: Repjuolía | C89: 800 | D89: Repjuolía | E89: Engir skráðir | S89: Plokkfiskur - Mjólkurlaus | T89: 316 | W89: Plokkfiskur - Mjólkurlaus
B90: Debic Vegan Top (jurtarjómi) | C90: 10000 | D90: Vatn (64%), jurtaolía (29%) (pálmakjarni, pálmi), þurrkað glúkósasíróp (5%), umbreytt sterkja, salt, bindiefni (E339, gellangúmmí), ýruefni (lesitín, E435, E472b), litarefni (karótín), náttúruleg bragðefni. | E90: Engir skráðir | G90: 295 | H90: 30 | I90: 25 | J90: 6.2 | L90: 0 | M90: 0.1 | N90: 0 | O90: 18 | S90: Plokkfiskur - Mjólkurlaus | T90: 18000 | W90: Plokkfiskur - Mjólkurlaus
B91: Vatn | C91: 5000 | D91: Vatn | E91: Engir skráðir | G91: 0 | H91: 0 | I91: 0 | J91: 0 | K91: 0 | L91: 0 | M91: 0 | N91: 0 | O91: 1 | S91: Plokkfiskur - Mjólkurlaus | T91: 500 | W91: Plokkfiskur - Mjólkurlaus
B92: Maizenamjöl (majssterkja) | C92: 1800 | D92: Maíssterkja. | E92: Engir skráðir | O92: 1 | S92: Plokkfiskur - Mjólkurlaus | T92: 720 | W92: Plokkfiskur - Mjólkurlaus
B93: Borðsalt | C93: 550 | D93: Salt (salt, kekkjavarnarefni E535, lyftiefni E500). | E93: Engir skráðir | F93: Framleitt á svæði þar sem unnið er með mjólk, glúten, egg, sesam, sellerí, soja og sinnep. | G93: 0 | H93: 0 | I93: 0 | J93: 0 | K93: 0 | L93: 0 | M93: 100 | O93: 0 | S93: Plokkfiskur - Mjólkurlaus | T93: 66 | W93: Plokkfiskur - Mjólkurlaus
B94: Hvítvínsedik | C94: 400 | D94: Þurrkað vín, edik | E94: Súlfít | S94: Plokkfiskur - Mjólkurlaus | T94: 240 | W94: Plokkfiskur - Mjólkurlaus
B95: Púðursykur | C95: 250 | D95: Sykur, sykurreyrssíróp. | E95: Engir | S95: Plokkfiskur - Mjólkurlaus | T95: 100 | W95: Plokkfiskur - Mjólkurlaus
B96: Múskat, malaður | C96: 40 | D96: Múskat 100% (Myristica fragrans), hitaþurrkað. | F96: Framleitt á svæði þar sem unnið er með glúten, fisk, krabbadýr, lindýr, mjólk, soja, sellerí, sinnep og sesam. | S96: Plokkfiskur - Mjólkurlaus | T96: 145 | W96: Plokkfiskur - Mjólkurlaus
B97: Karríduft (Curry powder) | C97: 60 | D97: Túrmerik, dillfræ, fenugreek (grikkjasmári), kóríander, cayennepipar, svartur pipar, negull. | E97: Engir skráðir | F97: Framleitt á svæði þar sem unnið er með glúten, fisk, mjólk, soja, sellerí, sinnep og sesam. | S97: Plokkfiskur - Mjólkurlaus | T97: 180 | W97: Plokkfiskur - Mjólkurlaus
B98: Svartur pipar, malaður | C98: 100 | D98: Svartur pipar 100% (Piper nigrum), hitaþurrkað. | F98: Framleitt á svæði þar sem unnið er með glúten, fisk, krabbadýr, lindýr, mjólk, soja, sellerí, sinnep og sesam. | G98: 386 | H98: 3.3 | I98: 1 | J98: 65 | K98: 0.6 | L98: 11 | M98: 0.1 | O98: 1 | S98: Plokkfiskur - Mjólkurlaus | T98: 700 | W98: Plokkfiskur - Mjólkurlaus
A99: Nautagrýta | D99: Nautgripakjöt 100 %. | Sellerírót (33%), gulrætur (32%), blaðlaukur (15%), **sellerí** (10%), laukur (10%) | Tómatar (81%) (hakkaðir tómatar, tómatpúrra), laukur (8%), grænt chili, salt, maíssterkja, krydd og kryddjurtir (chilipipar, hvítlaukur, kúmen, cayennepipar, kóríander, oregano), jalapeño (0,6%), paprika, vínedik, límónusafi. | Tómatar | Salt, chilipipar, kúmen, hvítlaukur, svartur pipar, cayennepipar, laukur, engifer, sykur, sýrustillir (sítrónusýra), kekkjavarnarefni (E552), repjuolía, kryddþykkni. | Hvítlaukur | Repjuolía | Grænmetiskraftur (vatn, laukur, gulrótþykkni, tómatur, **sellerí**rót, jurtaextrakt), bragðefni, glúkósasíróp, gerþykkni, salt, litarefni (karamellusykur), repjuolía, maltódextrín, sykur. | Maíssterkja. | Salt (salt, kekkjavarnarefni E535, lyftiefni E500). | Svartur pipar 100% (Piper nigrum), hitaþurrkað. | Vatn | E99: Sellerí | G99: 106.54 | H99: 4.92 | I99: 1.07 | J99: 7.89 | L99: 8.2 | M99: 5.08 | N99: 0.4 | P99: Í-Mat / Matarstund | KH-20260605-1 | Q99: 1. Hitið grýtu í ofni 160°C í 45-60 mín eða í potti við lágan hita. 2. Berið fram með kartöflum eða brauði. | R99: Hitið grýtu í ofni 160°C í 45-60 mín eða potti við lágan hita. Berið fram með kartöflum eða brauði. | S99: Nautagrýta | U99: 865 kr/kg | W99: Nautagrýta
B100: Nautgripahakk 2 kg frosið | C100: 35000 | D100: Nautgripakjöt 100 %. | E100: Engir skráðir | G100: 179 | H100: 11 | I100: 3.1 | J100: 0 | K100: 0 | L100: 20 | M100: 0.2 | N100: 0 | O100: 70 | S100: Nautagrýta | T100: 70000 | W100: Nautagrýta
...

Sheet Grunnmatseðill
A1: GRUNNMATSEÐILL | T1: Eldunarleiðbeiningar | AB1: Gildir-listi (sjálfvirkt) ↓ | AC1: Bæði | AD1: Áætluð stækkun skammts – Grunnskóli vs Leikskóli | AF1: Kostnaðareftirlit (sjálfvirkt) ↓
A2: Dagsetning | B2: Dagur (sjálfvirkt) | C2: Vika (sjálfvirkt) | D2: Gildir fyrir | E2: Máltíðartegund | F2: Vara / Réttur (leitarnafn) | G2: Birtingarnafn (vefur) | H2: Skammtur Leikskóli (g) | I2: Skammtur Grunnskóli (g) | J2: Foodcost (blandað viðmið) | K2: Innihaldslýsing (sjálfvirkt) | L2: Ofnæmisvaldar (sjálfvirkt) | M2: Fyrirvari (sjálfvirkt) | N2: Orka (kcal) | O2: Fita (g) | P2: Mettuð fita (g) | Q2: Kolvetni (g) | R2: Prótein (g) | S2: Salt (g) | T2: Eldunarpöntun (1, 2, 3...) | U2: Upphafsástand | V2: Eldunaraðferð | W2: Ofnhiti (°C) | X2: Eldunartími (mín) | Y2: Kjarnhiti (°C) | Z2: Athugasemd | AA2: Hvíld eftir eldun (mín) | AB2: Leikskóli | AC2: Leikskóli | AD2: 0.5 | AF2: Foodcost Leikskóli (kr/skammt) | AG2: Foodcost Grunnskóli (kr/skammt) | AH2: Hlutfall af fjárheimild | AI2: Staða (30% hámark) | AJ2: Dagsetning (fyllt)
A3: 46258 | B3: Mánudagur | C3: 35 | D3: Grunnskólar starfsmenn | E3: Aðalréttur | G3: Nautapottréttur Provence, kartöflumús | J3: =IF($F3="","",IFERROR(IFERROR(INDEX(Réttabanki!$U:$U,MATCH($F3,Réttabanki!$A:$A,0)),INDEX(Vöruskrá!$R:$R,MATCH($F3,Vöruskrá!$B:$B,0)))*($H3+IF($I3="",$H3*(1+$AD$2),$I3))/2/1000,"")) | K3: VANTAR – innihaldslýsing af umbúðum | Tómatar 100%. | Gulrætur | Laukur | Blaðlaukur | **Sellerí** | Hvítlaukur | Tómatar | Grænmetiskraftur (vatn, laukur, gulrótþykkni, tómatur, **sellerí**rót, jurtaextrakt), bragðefni, glúkósasíróp, gerþykkni, salt, litarefni (karamellusykur), repjuolía, maltódextrín, sykur. | Þurrkað rósmarín (Rosmarinus officinalis) | Oregano 100% (Origanum vulgare L.). | Lárviðarlauf 100% (Laurus nobilis). | Svartur pipar 100% (Piper nigrum), hitaþurrkað. | Salt (salt, kekkjavarnarefni E535, lyftiefni E500). | Repjuolía | Vatn | Kartöflur (80%), **nýmjólk**, **smjörfita**, salt, ýruefni (mónó- og díglýseríð fitusýra), krydd | L3: VANTAR – staðfesta ofnæmisvalda, Sellerí, Mjólk | M3: =IF($F3="","",IFERROR(IFERROR(INDEX(Réttabanki!$F:$F,MATCH($F3,Réttabanki!$A:$A,0)),INDEX(Vöruskrá!$H:$H,MATCH($F3,Vöruskrá!$B:$B,0))),"")) | N3: =IF($F3="","",IFERROR(IFERROR(INDEX(Réttabanki!$G:$G,MATCH($F3,Réttabanki!$A:$A,0)),INDEX(Vöruskrá!$J:$J,MATCH($F3,Vöruskrá!$B:$B,0)))*($H3+IF($I3="",$H3*(1+$AD$2),$I3))/2/100,"")) | O3: =IF($F3="","",IFERROR(IFERROR(INDEX(Réttabanki!$H:$H,MATCH($F3,Réttabanki!$A:$A,0)),INDEX(Vöruskrá!$K:$K,MATCH($F3,Vöruskrá!$B:$B,0)))*($H3+IF($I3="",$H3*(1+$AD$2),$I3))/2/100,"")) | P3: =IF($F3="","",IFERROR(IFERROR(INDEX(Réttabanki!$I:$I,MATCH($F3,Réttabanki!$A:$A,0)),INDEX(Vöruskrá!$L:$L,MATCH($F3,Vöruskrá!$B:$B,0)))*($H3+IF($I3="",$H3*(1+$AD$2),$I3))/2/100,"")) | Q3: =IF($F3="","",IFERROR(IFERROR(INDEX(Réttabanki!$J:$J,MATCH($F3,Réttabanki!$A:$A,0)),INDEX(Vöruskrá!$M:$M,MATCH($F3,Vöruskrá!$B:$B,0)))*($H3+IF($I3="",$H3*(1+$AD$2),$I3))/2/100,"")) | R3: =IF($F3="","",IFERROR(IFERROR(INDEX(Réttabanki!$L:$L,MATCH($F3,Réttabanki!$A:$A,0)),INDEX(Vöruskrá!$O:$O,MATCH($F3,Vöruskrá!$B:$B,0)))*($H3+IF($I3="",$H3*(1+$AD$2),$I3))/2/100,"")) | S3: =IF($F3="","",IFERROR(IFERROR(INDEX(Réttabanki!$M:$M,MATCH($F3,Réttabanki!$A:$A,0)),INDEX(Vöruskrá!$P:$P,MATCH($F3,Vöruskrá!$B:$B,0)))*($H3+IF($I3="",$H3*(1+$AD$2),$I3))/2/100,"")) | T3: =IF(F3="","",IFERROR(INDEX(Réttabanki!Q:Q,MATCH(F3,Réttabanki!A:A,0)),IFERROR(INDEX(Réttabanki!Q:Q,MATCH(F3,Réttabanki!B:B,0)),""))) | AC3: Grunnskóli | AF3: =IF($F3="","",IFERROR(IFERROR(INDEX(Réttabanki!$U:$U,MATCH($F3,Réttabanki!$A:$A,0)),INDEX(Vöruskrá!$R:$R,MATCH($F3,Vöruskrá!$B:$B,0)))*$H3/1000,"")) | AG3: =IF($F3="","",IFERROR(IFERROR(INDEX(Réttabanki!$U:$U,MATCH($F3,Réttabanki!$A:$A,0)),INDEX(Vöruskrá!$R:$R,MATCH($F3,Vöruskrá!$B:$B,0)))*IF($I3="",$H3*(1+$AD$2),$I3)/1000,"")) | AH3: =IF(N($AF3)+N($AG3)=0,"",MAX(N($AF3)/$AE$6,N($AG3)/$AE$5)) | AI3: =IF($AH3="","",IF($AH3>$AE$7,"⚠ Yfir "&TEXT($AE$7,"0%"),"OK")) | AJ3: =IF($A3<>"",$A3,"") -> 46258
B4: Mánudagur | C4: 35 | D4: Grunnskólar starfsmenn | E4: Aðalréttur | F4: Nautapottréttur að hætti Provence | G4: Nautapottréttur | I4: 200 | J4: =IF($F4="","",IFERROR(IFERROR(INDEX(Réttabanki!$U:$U,MATCH($F4,Réttabanki!$A:$A,0)),INDEX(Vöruskrá!$R:$R,MATCH($F4,Vöruskrá!$B:$B,0)))*($H4+IF($I4="",$H4*(1+$AD$2),$I4))/2/1000,"")) | K4: VANTAR – innihaldslýsing af umbúðum | Tómatar 100%. | Gulrætur | Laukur | Blaðlaukur | **Sellerí** | Hvítlaukur | Tómatar | Grænmetiskraftur (vatn, laukur, gulrótþykkni, tómatur, **sellerí**rót, jurtaextrakt), bragðefni, glúkósasíróp, gerþykkni, salt, litarefni (karamellusykur), repjuolía, maltódextrín, sykur. | Þurrkað rósmarín (Rosmarinus officinalis) | Oregano 100% (Origanum vulgare L.). | Lárviðarlauf 100% (Laurus nobilis). | Svartur pipar 100% (Piper nigrum), hitaþurrkað. | Salt (salt, kekkjavarnarefni E535, lyftiefni E500). | Repjuolía | Vatn | L4: VANTAR – staðfesta ofnæmisvalda, Sellerí | N4: 38.6 | O4: 1.99 | P4: 0.14 | Q4: 5.53 | R4: 0.9 | S4: 1.29 | T4: 1 | U4: Kælt | V4: Ofn | W4: 140 | X4: 50-60 | Y4: 80 | Z4: Hræra 1-2 sinnum | AC4: Leikskólar starfsmenn | AD4: Fjárheimild – forsendur ↓ | AF4: =IF($F4="","",IFERROR(IFERROR(INDEX(Réttabanki!$U:$U,MATCH($F4,Réttabanki!$A:$A,0)),INDEX(Vöruskrá!$R:$R,MATCH($F4,Vöruskrá!$B:$B,0)))*$H4/1000,"")) | AG4: =IF($F4="","",IFERROR(IFERROR(INDEX(Réttabanki!$U:$U,MATCH($F4,Réttabanki!$A:$A,0)),INDEX(Vöruskrá!$R:$R,MATCH($F4,Vöruskrá!$B:$B,0)))*IF($I4="",$H4*(1+$AD$2),$I4)/1000,"")) | AH4: =IF(N($AF4)+N($AG4)=0,"",MAX(N($AF4)/$AE$6,N($AG4)/$AE$5)) | AI4: =IF($AH4="","",IF($AH4>$AE$7,"⚠ Yfir "&TEXT($AE$7,"0%"),"OK")) | AJ4: =IF($A4<>"",$A4,AJ3) -> 46258
B5: Mánudagur | C5: 35 | D5: Grunnskólar starfsmenn | E5: Aðalréttur | F5: Kartöflumús - Mydibel | G5: Kartöflumús | I5: 100 | J5: =IF($F5="","",IFERROR(IFERROR(INDEX(Réttabanki!$U:$U,MATCH($F5,Réttabanki!$A:$A,0)),INDEX(Vöruskrá!$R:$R,MATCH($F5,Vöruskrá!$B:$B,0)))*($H5+IF($I5="",$H5*(1+$AD$2),$I5))/2/1000,"")) -> 25 | K5: Kartöflur (80%), **nýmjólk**, **smjörfita**, salt, ýruefni (mónó- og díglýseríð fitusýra), krydd | L5: Mjólk | M5: Gæti innihaldið snefil af glúten og eggjum | N5: 103 | O5: 3 | P5: 2.1 | Q5: 16 | R5: 2.2 | S5: 0.7 | T5: 2 | U5: Kælt | V5: Ofn | W5: Steam - 98 | X5: 35-45 | Y5: 75 | Z5: Með loki | AC5: Grunnskólar starfsmenn | AD5: Dagsfjárheimild Grunnskóli (kr/dag) | AE5: 1150 | AF5: =IF($F5="","",IFERROR(IFERROR(INDEX(Réttabanki!$U:$U,MATCH($F5,Réttabanki!$A:$A,0)),INDEX(Vöruskrá!$R:$R,MATCH($F5,Vöruskrá!$B:$B,0)))*$H5/1000,"")) -> 0 | AG5: =IF($F5="","",IFERROR(IFERROR(INDEX(Réttabanki!$U:$U,MATCH($F5,Réttabanki!$A:$A,0)),INDEX(Vöruskrá!$R:$R,MATCH($F5,Vöruskrá!$B:$B,0)))*IF($I5="",$H5*(1+$AD$2),$I5)/1000,"")) -> 50 | AH5: =IF(N($AF5)+N($AG5)=0,"",MAX(N($AF5)/$AE$6,N($AG5)/$AE$5)) -> 0.043478261 | AI5: =IF($AH5="","",IF($AH5>$AE$7,"⚠ Yfir "&TEXT($AE$7,"0%"),"OK")) -> OK | AJ5: =IF($A5<>"",$A5,AJ4) -> 46258
B6: Mánudagur | C6: 35 | D6: Leikskóli | E6: Aðalréttur | G6: Nautapottréttur, kartöflumús | J6: =IF($F6="","",IFERROR(IFERROR(INDEX(Réttabanki!$U:$U,MATCH($F6,Réttabanki!$A:$A,0)),INDEX(Vöruskrá!$R:$R,MATCH($F6,Vöruskrá!$B:$B,0)))*($H6+IF($I6="",$H6*(1+$AD$2),$I6))/2/1000,"")) | K6: Nautakjöt 100% (rectangular cut, standard trim, cap on). | VANTAR – innihaldslýsing af umbúðum | Maukaðir tómatar 38%, kúrbítur 20%, eggaldin 20%, laukur 10%, rauð paprika 6%, græn paprika 6%. | Gulrætur (Dökkappelsínugular gulrætur 60%, gular gulrætur 40%.) | Laukur (90%), repjuolía (10%). | Tómatar | Grænmetiskraftur (vatn, laukur, gulrótþykkni, tómatur, **sellerí**rót, jurtaextrakt), bragðefni, glúkósasíróp, gerþykkni, salt, litarefni (karamellusykur), repjuolía, maltódextrín, sykur. | Vatn | Vatn, **sinnep**sfræ, edik, salt, rotvarnarefni (**súlfít**) | Maíssterkja. | Salt (salt, kekkjavarnarefni E535, lyftiefni E500). | Reykt paprika 100% (Capsicum annuum), reykþurrkuð. | Vatn, grænmeti (laukur, hvítlaukur, gulrætur, tómatar, kryddjurtir og krydd), bragðefni, gerþykkni, hoisin-sósa (sykur, rautt misó **soja**baunir, hrísgrjón, salt, vatn, ger, tamari-sojasósa vatn, **soja**baunir, salt, alkóhól, tómatpúrra, vatn, hrísgrjónaedik, stjörnuanís, lakkrís, hvítlauksmauk, chiliduft), salt, sykur, engifermauk, þurrkað glúkósasíróp, maltódextrín, möluð krydd (engifer, chili, kóríander, túrmerik, svartur pipar), repjuolía. | Svartur pipar 100% (Piper nigrum), hitaþurrkað. | Hvítlauksduft 100% | Þurrkað rósmarín (Rosmarinus officinalis) | Kartöflur (80%), **nýmjólk**, **smjörfita**, salt, ýruefni (mónó- og díglýseríð fitusýra), krydd | Kartöflur | L6: VANTAR – staðfesta ofnæmisvalda, Sellerí, Sinnep, súlfít, Soja, Mjólk | M6: =IF($F6="","",IFERROR(IFERROR(INDEX(Réttabanki!$F:$F,MATCH($F6,Réttabanki!$A:$A,0)),INDEX(Vöruskrá!$H:$H,MATCH($F6,Vöruskrá!$B:$B,0))),"")) | N6: =IF($F6="","",IFERROR(IFERROR(INDEX(Réttabanki!$G:$G,MATCH($F6,Réttabanki!$A:$A,0)),INDEX(Vöruskrá!$J:$J,MATCH($F6,Vöruskrá!$B:$B,0)))*($H6+IF($I6="",$H6*(1+$AD$2),$I6))/2/100,"")) | O6: =IF($F6="","",IFERROR(IFERROR(INDEX(Réttabanki!$H:$H,MATCH($F6,Réttabanki!$A:$A,0)),INDEX(Vöruskrá!$K:$K,MATCH($F6,Vöruskrá!$B:$B,0)))*($H6+IF($I6="",$H6*(1+$AD$2),$I6))/2/100,"")) | P6: =IF($F6="","",IFERROR(IFERROR(INDEX(Réttabanki!$I:$I,MATCH($F6,Réttabanki!$A:$A,0)),INDEX(Vöruskrá!$L:$L,MATCH($F6,Vöruskrá!$B:$B,0)))*($H6+IF($I6="",$H6*(1+$AD$2),$I6))/2/100,"")) | Q6: =IF($F6="","",IFERROR(IFERROR(INDEX(Réttabanki!$J:$J,MATCH($F6,Réttabanki!$A:$A,0)),INDEX(Vöruskrá!$M:$M,MATCH($F6,Vöruskrá!$B:$B,0)))*($H6+IF($I6="",$H6*(1+$AD$2),$I6))/2/100,"")) | R6: =IF($F6="","",IFERROR(IFERROR(INDEX(Réttabanki!$L:$L,MATCH($F6,Réttabanki!$A:$A,0)),INDEX(Vöruskrá!$O:$O,MATCH($F6,Vöruskrá!$B:$B,0)))*($H6+IF($I6="",$H6*(1+$AD$2),$I6))/2/100,"")) | S6: =IF($F6="","",IFERROR(IFERROR(INDEX(Réttabanki!$M:$M,MATCH($F6,Réttabanki!$A:$A,0)),INDEX(Vöruskrá!$P:$P,MATCH($F6,Vöruskrá!$B:$B,0)))*($H6+IF($I6="",$H6*(1+$AD$2),$I6))/2/100,"")) | T6: =IF(F6="","",IFERROR(INDEX(Réttabanki!Q:Q,MATCH(F6,Réttabanki!A:A,0)),IFERROR(INDEX(Réttabanki!Q:Q,MATCH(F6,Réttabanki!B:B,0)),""))) | AC6: Engidalsskóli | AD6: Dagsfjárheimild Leikskóli (kr/dag) | AE6: 1350 | AF6: =IF($F6="","",IFERROR(IFERROR(INDEX(Réttabanki!$U:$U,MATCH($F6,Réttabanki!$A:$A,0)),INDEX(Vöruskrá!$R:$R,MATCH($F6,Vöruskrá!$B:$B,0)))*$H6/1000,"")) | AG6: =IF($F6="","",IFERROR(IFERROR(INDEX(Réttabanki!$U:$U,MATCH($F6,Réttabanki!$A:$A,0)),INDEX(Vöruskrá!$R:$R,MATCH($F6,Vöruskrá!$B:$B,0)))*IF($I6="",$H6*(1+$AD$2),$I6)/1000,"")) | AH6: =IF(N($AF6)+N($AG6)=0,"",MAX(N($AF6)/$AE$6,N($AG6)/$AE$5)) | AI6: =IF($AH6="","",IF($AH6>$AE$7,"⚠ Yfir "&TEXT($AE$7,"0%"),"OK")) | AJ6: =IF($A6<>"",$A6,AJ5) -> 46258
B7: Mánudagur | C7: 35 | D7: Leikskóli | E7: Aðalréttur | F7: Nautapottréttur | G7: Nautapottréttur | H7: 180 | J7: =IF($F7="","",IFERROR(IFERROR(INDEX(Réttabanki!$U:$U,MATCH($F7,Réttabanki!$A:$A,0)),INDEX(Vöruskrá!$R:$R,MATCH($F7,Vöruskrá!$B:$B,0)))*($H7+IF($I7="",$H7*(1+$AD$2),$I7))/2/1000,"")) | K7: Nautakjöt 100% (rectangular cut, standard trim, cap on). | VANTAR – innihaldslýsing af umbúðum | Maukaðir tómatar 38%, kúrbítur 20%, eggaldin 20%, laukur 10%, rauð paprika 6%, græn paprika 6%. | Gulrætur (Dökkappelsínugular gulrætur 60%, gular gulrætur 40%.) | Laukur (90%), repjuolía (10%). | Tómatar | Grænmetiskraftur (vatn, laukur, gulrótþykkni, tómatur, **sellerí**rót, jurtaextrakt), bragðefni, glúkósasíróp, gerþykkni, salt, litarefni (karamellusykur), repjuolía, maltódextrín, sykur. | Vatn | Vatn, **sinnep**sfræ, edik, salt, rotvarnarefni (**súlfít**) | Maíssterkja. | Salt (salt, kekkjavarnarefni E535, lyftiefni E500). | Reykt paprika 100% (Capsicum annuum), reykþurrkuð. | Vatn, grænmeti (laukur, hvítlaukur, gulrætur, tómatar, kryddjurtir og krydd), bragðefni, gerþykkni, hoisin-sósa (sykur, rautt misó **soja**baunir, hrísgrjón, salt, vatn, ger, tamari-sojasósa vatn, **soja**baunir, salt, alkóhól, tómatpúrra, vatn, hrísgrjónaedik, stjörnuanís, lakkrís, hvítlauksmauk, chiliduft), salt, sykur, engifermauk, þurrkað glúkósasíróp, maltódextrín, möluð krydd (engifer, chili, kóríander, túrmerik, svartur pipar), repjuolía. | Svartur pipar 100% (Piper nigrum), hitaþurrkað. | Hvítlauksduft 100% | Þurrkað rósmarín (Rosmarinus officinalis) | L7: VANTAR – staðfesta ofnæmisvalda, Sellerí, Sinnep, súlfít, Soja | N7: 56.9 | O7: 2.3 | P7: 0.7 | Q7: 5.4 | R7: 3.3 | S7: 1.7 | T7: 1 | U7: Kælt | V7: Ofn | W7: 140 | X7: 50-60 | Y7: 80 | Z7: Hræra 1-2 sinnum | AC7: Hraunvallaskóli | AD7: Hámarkshlutfall matarkostnaðar | AE7: 0.3 | AF7: =IF($F7="","",IFERROR(IFERROR(INDEX(Réttabanki!$U:$U,MATCH($F7,Réttabanki!$A:$A,0)),INDEX(Vöruskrá!$R:$R,MATCH($F7,Vöruskrá!$B:$B,0)))*$H7/1000,"")) | AG7: =IF($F7="","",IFERROR(IFERROR(INDEX(Réttabanki!$U:$U,MATCH($F7,Réttabanki!$A:$A,0)),INDEX(Vöruskrá!$R:$R,MATCH($F7,Vöruskrá!$B:$B,0)))*IF($I7="",$H7*(1+$AD$2),$I7)/1000,"")) | AH7: =IF(N($AF7)+N($AG7)=0,"",MAX(N($AF7)/$AE$6,N($AG7)/$AE$5)) | AI7: =IF($AH7="","",IF($AH7>$AE$7,"⚠ Yfir "&TEXT($AE$7,"0%"),"OK")) | AJ7: =IF($A7<>"",$A7,AJ6) -> 46258
B8: Mánudagur | C8: 35 | D8: Leikskóli | E8: Aðalréttur | F8: Kartöflumús - Mydibel | G8: Kartöflumús | H8: 80 | J8: =IF($F8="","",IFERROR(IFERROR(INDEX(Réttabanki!$U:$U,MATCH($F8,Réttabanki!$A:$A,0)),INDEX(Vöruskrá!$R:$R,MATCH($F8,Vöruskrá!$B:$B,0)))*($H8+IF($I8="",$H8*(1+$AD$2),$I8))/2/1000,"")) -> 50 | K8: Kartöflur (80%), **nýmjólk**, **smjörfita**, salt, ýruefni (mónó- og díglýseríð fitusýra), krydd | L8: Mjólk | M8: Gæti innihaldið snefil af glúten og eggjum | N8: 103 | O8: 3 | P8: 2.1 | Q8: 16 | R8: 2.2 | S8: 0.7 | T8: 2 | U8: Kælt | V8: Ofn | W8: Steam - 98 | X8: 35-45 | Y8: 75 | Z8: Með loki | AC8: Hvaleyrarskóli | AD8: Hámark Grunnskóli (kr/dag) | AE8: =$AE$5*$AE$7 -> 345 | AF8: =IF($F8="","",IFERROR(IFERROR(INDEX(Réttabanki!$U:$U,MATCH($F8,Réttabanki!$A:$A,0)),INDEX(Vöruskrá!$R:$R,MATCH($F8,Vöruskrá!$B:$B,0)))*$H8/1000,"")) -> 40 | AG8: =IF($F8="","",IFERROR(IFERROR(INDEX(Réttabanki!$U:$U,MATCH($F8,Réttabanki!$A:$A,0)),INDEX(Vöruskrá!$R:$R,MATCH($F8,Vöruskrá!$B:$B,0)))*IF($I8="",$H8*(1+$AD$2),$I8)/1000,"")) -> 60 | AH8: =IF(N($AF8)+N($AG8)=0,"",MAX(N($AF8)/$AE$6,N($AG8)/$AE$5)) -> 0.052173913 | AI8: =IF($AH8="","",IF($AH8>$AE$7,"⚠ Yfir "&TEXT($AE$7,"0%"),"OK")) -> OK | AJ8: =IF($A8<>"",$A8,AJ7) -> 46258
B9: Mánudagur | C9: 35 | D9: Leikskóli | E9: Sérfæði | F9: Forsoðnar kartöflur | G9: Kartöflumús (Mjólkurlaus) | H9: 80 | J9: =IF($F9="","",IFERROR(IFERROR(INDEX(Réttabanki!$U:$U,MATCH($F9,Réttabanki!$A:$A,0)),INDEX(Vöruskrá!$R:$R,MATCH($F9,Vöruskrá!$B:$B,0)))*($H9+IF($I9="",$H9*(1+$AD$2),$I9))/2/1000,"")) -> 43 | K9: Kartöflur | L9: Engir skráðir | N9: 77 | O9: 0.1 | P9: 0 | Q9: 20 | R9: 1.7 | S9: 0 | AC9: Lækjarskóli | AD9: Hámark Leikskóli (kr/dag) | AE9: =$AE$6*$AE$7 -> 405 | AF9: =IF($F9="","",IFERROR(IFERROR(INDEX(Réttabanki!$U:$U,MATCH($F9,Réttabanki!$A:$A,0)),INDEX(Vöruskrá!$R:$R,MATCH($F9,Vöruskrá!$B:$B,0)))*$H9/1000,"")) -> 34.4 | AG9: =IF($F9="","",IFERROR(IFERROR(INDEX(Réttabanki!$U:$U,MATCH($F9,Réttabanki!$A:$A,0)),INDEX(Vöruskrá!$R:$R,MATCH($F9,Vöruskrá!$B:$B,0)))*IF($I9="",$H9*(1+$AD$2),$I9)/1000,"")) -> 51.6 | AH9: =IF(N($AF9)+N($AG9)=0,"",MAX(N($AF9)/$AE$6,N($AG9)/$AE$5)) -> 0.044869565 | AI9: =IF($AH9="","",IF($AH9>$AE$7,"⚠ Yfir "&TEXT($AE$7,"0%"),"OK")) -> OK | AJ9: =IF($A9<>"",$A9,AJ8) -> 46258
B10: Mánudagur | C10: 35 | D10: Leikskóli | E10: Hliðarréttur | G10: Marrakesh pottréttur, kartöflumús | J10: =IF($F10="","",IFERROR(IFERROR(INDEX(Réttabanki!$U:$U,MATCH($F10,Réttabanki!$A:$A,0)),INDEX(Vöruskrá!$R:$R,MATCH($F10,Vöruskrá!$B:$B,0)))*($H10+IF($I10="",$H10*(1+$AD$2),$I10))/2/1000,"")) | K10: Tómatar, kjúklingabaunir, laukur, gulrætur, sætar kartöflur, eplasafi (eplasafi, þráavarnarefni E330), blómkál, repjuolía, döðlur, limesafi (lime safi, þráavarnarefni E224, inniheldur **SÚLFÍÐ**), paprikumauk (rauð paprika, eggaldin, sólblómaolía, sykur, salt, sýrustillir E260, krydd, chili, náttúruleg bragðefni), hvítlaukur, salt, kóríander, chilimauk (rauður chili, salt, sykur, sýrustillir E260, E330, rotvarnarefni E211), grænmetiskraftur (salt, pálmaolía, maltodextrín, gulrætur, laukur, **sellerí**, blaðlaukur, graslaukur), sykur, krydd (túrmerik, hvítur pipar, kóríander, múskat, **sellerí**), rósmarínkraftur, kúmen, engifer, túrmerik, svartur pipar, kanill. | Kartöflur (80%), **nýmjólk**, **smjörfita**, salt, ýruefni (mónó- og díglýseríð fitusýra), krydd | L10: Súlfít, sellerí., Mjólk | AC10: Öldutúnsskóli | AF10: =IF($F10="","",IFERROR(IFERROR(INDEX(Réttabanki!$U:$U,MATCH($F10,Réttabanki!$A:$A,0)),INDEX(Vöruskrá!$R:$R,MATCH($F10,Vöruskrá!$B:$B,0)))*$H10/1000,"")) | AG10: =IF($F10="","",IFERROR(IFERROR(INDEX(Réttabanki!$U:$U,MATCH($F10,Réttabanki!$A:$A,0)),INDEX(Vöruskrá!$R:$R,MATCH($F10,Vöruskrá!$B:$B,0)))*IF($I10="",$H10*(1+$AD$2),$I10)/1000,"")) | AH10: =IF(N($AF10)+N($AG10)=0,"",MAX(N($AF10)/$AE$6,N($AG10)/$AE$5)) | AI10: =IF($AH10="","",IF($AH10>$AE$7,"⚠ Yfir "&TEXT($AE$7,"0%"),"OK")) | AJ10: =IF($A10<>"",$A10,AJ9) -> 46258
B11: Mánudagur | C11: 35 | D11: Leikskóli | E11: Hliðarréttur | F11: Marrakesh pottréttur | G11: Marrakesh pottréttur | H11: 180 | J11: =IF($F11="","",IFERROR(IFERROR(INDEX(Réttabanki!$U:$U,MATCH($F11,Réttabanki!$A:$A,0)),INDEX(Vöruskrá!$R:$R,MATCH($F11,Vöruskrá!$B:$B,0)))*($H11+IF($I11="",$H11*(1+$AD$2),$I11))/2/1000,"")) -> 405 | K11: Tómatar, kjúklingabaunir, laukur, gulrætur, sætar kartöflur, eplasafi (eplasafi, þráavarnarefni E330), blómkál, repjuolía, döðlur, limesafi (lime safi, þráavarnarefni E224, inniheldur **SÚLFÍÐ**), paprikumauk (rauð paprika, eggaldin, sólblómaolía, sykur, salt, sýrustillir E260, krydd, chili, náttúruleg bragðefni), hvítlaukur, salt, kóríander, chilimauk (rauður chili, salt, sykur, sýrustillir E260, E330, rotvarnarefni E211), grænmetiskraftur (salt, pálmaolía, maltodextrín, gulrætur, laukur, **sellerí**, blaðlaukur, graslaukur), sykur, krydd (túrmerik, hvítur pipar, kóríander, múskat, **sellerí**), rósmarínkraftur, kúmen, engifer, túrmerik, svartur pipar, kanill. | L11: Súlfít, sellerí. | M11: Framleitt á svæði þar sem unnið er með hnetur | N11: 118 | O11: 4.5 | P11: 0.4 | Q11: 13.5 | R11: 3.8 | S11: 0.9 | T11: 1 | U11: Kælt | V11: Ofn | W11: 140 | X11: 20-25 | Y11: 75 | Z11: Hræra 1-2 sinnum | AC11: Setbergsskóli | AF11: =IF($F11="","",IFERROR(IFERROR(INDEX(Réttabanki!$U:$U,MATCH($F11,Réttabanki!$A:$A,0)),INDEX(Vöruskrá!$R:$R,MATCH($F11,Vöruskrá!$B:$B,0)))*$H11/1000,"")) -> 324 | AG11: =IF($F11="","",IFERROR(IFERROR(INDEX(Réttabanki!$U:$U,MATCH($F11,Réttabanki!$A:$A,0)),INDEX(Vöruskrá!$R:$R,MATCH($F11,Vöruskrá!$B:$B,0)))*IF($I11="",$H11*(1+$AD$2),$I11)/1000,"")) -> 486 | AH11: =IF(N($AF11)+N($AG11)=0,"",MAX(N($AF11)/$AE$6,N($AG11)/$AE$5)) -> 0.4226087 | AI11: =IF($AH11="","",IF($AH11>$AE$7,"⚠ Yfir "&TEXT($AE$7,"0%"),"OK")) -> ⚠ Yfir 30% | AJ11: =IF($A11<>"",$A11,AJ10) -> 46258
B12: Mánudagur | C12: 35 | D12: Leikskóli | E12: Hliðarréttur | F12: Kartöflumús - Mydibel | G12: Kartöflumús | H12: 80 | J12: =IF($F12="","",IFERROR(IFERROR(INDEX(Réttabanki!$U:$U,MATCH($F12,Réttabanki!$A:$A,0)),INDEX(Vöruskrá!$R:$R,MATCH($F12,Vöruskrá!$B:$B,0)))*($H12+IF($I12="",$H12*(1+$AD$2),$I12))/2/1000,"")) -> 50 | K12: Kartöflur (80%), **nýmjólk**, **smjörfita**, salt, ýruefni (mónó- og díglýseríð fitusýra), krydd | L12: Mjólk | M12: Gæti innihaldið snefil af glúten og eggjum | N12: 103 | O12: 3 | P12: 2.1 | Q12: 16 | R12: 2.2 | S12: 0.7 | T12: 2 | U12: Kælt | V12: Ofn | W12: Steam - 98 | X12: 20-25 | Y12: 75 | Z12: Með loki | AC12: Skarðshlíðarskóli | AF12: =IF($F12="","",IFERROR(IFERROR(INDEX(Réttabanki!$U:$U,MATCH($F12,Réttabanki!$A:$A,0)),INDEX(Vöruskrá!$R:$R,MATCH($F12,Vöruskrá!$B:$B,0)))*$H12/1000,"")) -> 40 | AG12: =IF($F12="","",IFERROR(IFERROR(INDEX(Réttabanki!$U:$U,MATCH($F12,Réttabanki!$A:$A,0)),INDEX(Vöruskrá!$R:$R,MATCH($F12,Vöruskrá!$B:$B,0)))*IF($I12="",$H12*(1+$AD$2),$I12)/1000,"")) -> 60 | AH12: =IF(N($AF12)+N($AG12)=0,"",MAX(N($AF12)/$AE$6,N($AG12)/$AE$5)) -> 0.052173913 | AI12: =IF($AH12="","",IF($AH12>$AE$7,"⚠ Yfir "&TEXT($AE$7,"0%"),"OK")) -> OK | AJ12: =IF($A12<>"",$A12,AJ11) -> 46258
B13: Mánudagur | C13: 35 | D13: Grunnskólar starfsmenn | E13: Meðlætisbar | J13: =IF($F13="","",IFERROR(IFERROR(INDEX(Réttabanki!$U:$U,MATCH($F13,Réttabanki!$A:$A,0)),INDEX(Vöruskrá!$R:$R,MATCH($F13,Vöruskrá!$B:$B,0)))*($H13+IF($I13="",$H13*(1+$AD$2),$I13))/2/1000,"")) | L13: Engir skráðir | M13: =IF($F13="","",IFERROR(IFERROR(INDEX(Réttabanki!$F:$F,MATCH($F13,Réttabanki!$A:$A,0)),INDEX(Vöruskrá!$H:$H,MATCH($F13,Vöruskrá!$B:$B,0))),"")) | N13: =IF($F13="","",IFERROR(IFERROR(INDEX(Réttabanki!$G:$G,MATCH($F13,Réttabanki!$A:$A,0)),INDEX(Vöruskrá!$J:$J,MATCH($F13,Vöruskrá!$B:$B,0)))*($H13+IF($I13="",$H13*(1+$AD$2),$I13))/2/100,"")) | O13: =IF($F13="","",IFERROR(IFERROR(INDEX(Réttabanki!$H:$H,MATCH($F13,Réttabanki!$A:$A,0)),INDEX(Vöruskrá!$K:$K,MATCH($F13,Vöruskrá!$B:$B,0)))*($H13+IF($I13="",$H13*(1+$AD$2),$I13))/2/100,"")) | P13: =IF($F13="","",IFERROR(IFERROR(INDEX(Réttabanki!$I:$I,MATCH($F13,Réttabanki!$A:$A,0)),INDEX(Vöruskrá!$L:$L,MATCH($F13,Vöruskrá!$B:$B,0)))*($H13+IF($I13="",$H13*(1+$AD$2),$I13))/2/100,"")) | Q13: =IF($F13="","",IFERROR(IFERROR(INDEX(Réttabanki!$J:$J,MATCH($F13,Réttabanki!$A:$A,0)),INDEX(Vöruskrá!$M:$M,MATCH($F13,Vöruskrá!$B:$B,0)))*($H13+IF($I13="",$H13*(1+$AD$2),$I13))/2/100,"")) | R13: =IF($F13="","",IFERROR(IFERROR(INDEX(Réttabanki!$L:$L,MATCH($F13,Réttabanki!$A:$A,0)),INDEX(Vöruskrá!$O:$O,MATCH($F13,Vöruskrá!$B:$B,0)))*($H13+IF($I13="",$H13*(1+$AD$2),$I13))/2/100,"")) | S13: =IF($F13="","",IFERROR(IFERROR(INDEX(Réttabanki!$M:$M,MATCH($F13,Réttabanki!$A:$A,0)),INDEX(Vöruskrá!$P:$P,MATCH($F13,Vöruskrá!$B:$B,0)))*($H13+IF($I13="",$H13*(1+$AD$2),$I13))/2/100,"")) | T13: =IF(F13="","",IFERROR(INDEX(Réttabanki!Q:Q,MATCH(F13,Réttabanki!A:A,0)),IFERROR(INDEX(Réttabanki!Q:Q,MATCH(F13,Réttabanki!B:B,0)),""))) | AC13: Víðistaðaskóli | AF13: =IF($F13="","",IFERROR(IFERROR(INDEX(Réttabanki!$U:$U,MATCH($F13,Réttabanki!$A:$A,0)),INDEX(Vöruskrá!$R:$R,MATCH($F13,Vöruskrá!$B:$B,0)))*$H13/1000,"")) | AG13: =IF($F13="","",IFERROR(IFERROR(INDEX(Réttabanki!$U:$U,MATCH($F13,Réttabanki!$A:$A,0)),INDEX(Vöruskrá!$R:$R,MATCH($F13,Vöruskrá!$B:$B,0)))*IF($I13="",$H13*(1+$AD$2),$I13)/1000,"")) | AH13: =IF(N($AF13)+N($AG13)=0,"",MAX(N($AF13)/$AE$6,N($AG13)/$AE$5)) | AI13: =IF($AH13="","",IF($AH13>$AE$7,"⚠ Yfir "&TEXT($AE$7,"0%"),"OK")) | AJ13: =IF($A13<>"",$A13,AJ12) -> 46258
B14: Mánudagur | C14: 35 | D14: Leikskóli | E14: Meðlætisbar | G14: Gúrka, ávextir | J14: =IF($F14="","",IFERROR(IFERROR(INDEX(Réttabanki!$U:$U,MATCH($F14,Réttabanki!$A:$A,0)),INDEX(Vöruskrá!$R:$R,MATCH($F14,Vöruskrá!$B:$B,0)))*($H14+IF($I14="",$H14*(1+$AD$2),$I14))/2/1000,"")) | L14: Engir skráðir | M14: =IF($F14="","",IFERROR(IFERROR(INDEX(Réttabanki!$F:$F,MATCH($F14,Réttabanki!$A:$A,0)),INDEX(Vöruskrá!$H:$H,MATCH($F14,Vöruskrá!$B:$B,0))),"")) | N14: =IF($F14="","",IFERROR(IFERROR(INDEX(Réttabanki!$G:$G,MATCH($F14,Réttabanki!$A:$A,0)),INDEX(Vöruskrá!$J:$J,MATCH($F14,Vöruskrá!$B:$B,0)))*($H14+IF($I14="",$H14*(1+$AD$2),$I14))/2/100,"")) | O14: =IF($F14="","",IFERROR(IFERROR(INDEX(Réttabanki!$H:$H,MATCH($F14,Réttabanki!$A:$A,0)),INDEX(Vöruskrá!$K:$K,MATCH($F14,Vöruskrá!$B:$B,0)))*($H14+IF($I14="",$H14*(1+$AD$2),$I14))/2/100,"")) | P14: =IF($F14="","",IFERROR(IFERROR(INDEX(Réttabanki!$I:$I,MATCH($F14,Réttabanki!$A:$A,0)),INDEX(Vöruskrá!$L:$L,MATCH($F14,Vöruskrá!$B:$B,0)))*($H14+IF($I14="",$H14*(1+$AD$2),$I14))/2/100,"")) | Q14: =IF($F14="","",IFERROR(IFERROR(INDEX(Réttabanki!$J:$J,MATCH($F14,Réttabanki!$A:$A,0)),INDEX(Vöruskrá!$M:$M,MATCH($F14,Vöruskrá!$B:$B,0)))*($H14+IF($I14="",$H14*(1+$AD$2),$I14))/2/100,"")) | R14: =IF($F14="","",IFERROR(IFERROR(INDEX(Réttabanki!$L:$L,MATCH($F14,Réttabanki!$A:$A,0)),INDEX(Vöruskrá!$O:$O,MATCH($F14,Vöruskrá!$B:$B,0)))*($H14+IF($I14="",$H14*(1+$AD$2),$I14))/2/100,"")) | S14: =IF($F14="","",IFERROR(IFERROR(INDEX(Réttabanki!$M:$M,MATCH($F14,Réttabanki!$A:$A,0)),INDEX(Vöruskrá!$P:$P,MATCH($F14,Vöruskrá!$B:$B,0)))*($H14+IF($I14="",$H14*(1+$AD$2),$I14))/2/100,"")) | T14: =IF(F14="","",IFERROR(INDEX(Réttabanki!Q:Q,MATCH(F14,Réttabanki!A:A,0)),IFERROR(INDEX(Réttabanki!Q:Q,MATCH(F14,Réttabanki!B:B,0)),""))) | AC14: Álfaberg | AF14: =IF($F14="","",IFERROR(IFERROR(INDEX(Réttabanki!$U:$U,MATCH($F14,Réttabanki!$A:$A,0)),INDEX(Vöruskrá!$R:$R,MATCH($F14,Vöruskrá!$B:$B,0)))*$H14/1000,"")) | AG14: =IF($F14="","",IFERROR(IFERROR(INDEX(Réttabanki!$U:$U,MATCH($F14,Réttabanki!$A:$A,0)),INDEX(Vöruskrá!$R:$R,MATCH($F14,Vöruskrá!$B:$B,0)))*IF($I14="",$H14*(1+$AD$2),$I14)/1000,"")) | AH14: =IF(N($AF14)+N($AG14)=0,"",MAX(N($AF14)/$AE$6,N($AG14)/$AE$5)) | AI14: =IF($AH14="","",IF($AH14>$AE$7,"⚠ Yfir "&TEXT($AE$7,"0%"),"OK")) | AJ14: =IF($A14<>"",$A14,AJ13) -> 46258
B15: Mánudagur | C15: 35 | D15: Leikskóli | E15: Síðdegishressing | G15: Lífskornabrauð, ostur, tómatar, ávextir | J15: =IF($F15="","",IFERROR(IFERROR(INDEX(Réttabanki!$U:$U,MATCH($F15,Réttabanki!$A:$A,0)),INDEX(Vöruskrá!$R:$R,MATCH($F15,Vöruskrá!$B:$B,0)))*($H15+IF($I15="",$H15*(1+$AD$2),$I15))/2/1000,"")) | K15: Vatn, **tröllahafrar** 21%, heilkorna **heilhveiti** 16%, **hveiti**, **hveitiglúten**, **rúgmjöl**, þurrkað súrdeig (**rúgur**, súrdeigsgerlar), **hveitikurl**, ger, chia fræ 1% (Salvia hispanica), maltextrakt (**bygg**), repjuolía, joðbætt salt, þykkingarefni (E415), sýrustillir (E262), ýruefni (E471, E472e), mjölmeðhöndlunarefni (E300) | **Mjólk**, **undanrenna**, salt, ostahleypir. | L15: Glúten (hafrar, hveiti, rúgur, bygg), Mjólk | M15: =IF($F15="","",IFERROR(IFERROR(INDEX(Réttabanki!$F:$F,MATCH($F15,Réttabanki!$A:$A,0)),INDEX(Vöruskrá!$H:$H,MATCH($F15,Vöruskrá!$B:$B,0))),"")) | N15: =IF($F15="","",IFERROR(IFERROR(INDEX(Réttabanki!$G:$G,MATCH($F15,Réttabanki!$A:$A,0)),INDEX(Vöruskrá!$J:$J,MATCH($F15,Vöruskrá!$B:$B,0)))*($H15+IF($I15="",$H15*(1+$AD$2),$I15))/2/100,"")) | O15: =IF($F15="","",IFERROR(IFERROR(INDEX(Réttabanki!$H:$H,MATCH($F15,Réttabanki!$A:$A,0)),INDEX(Vöruskrá!$K:$K,MATCH($F15,Vöruskrá!$B:$B,0)))*($H15+IF($I15="",$H15*(1+$AD$2),$I15))/2/100,"")) | P15: =IF($F15="","",IFERROR(IFERROR(INDEX(Réttabanki!$I:$I,MATCH($F15,Réttabanki!$A:$A,0)),INDEX(Vöruskrá!$L:$L,MATCH($F15,Vöruskrá!$B:$B,0)))*($H15+IF($I15="",$H15*(1+$AD$2),$I15))/2/100,"")) | Q15: =IF($F15="","",IFERROR(IFERROR(INDEX(Réttabanki!$J:$J,MATCH($F15,Réttabanki!$A:$A,0)),INDEX(Vöruskrá!$M:$M,MATCH($F15,Vöruskrá!$B:$B,0)))*($H15+IF($I15="",$H15*(1+$AD$2),$I15))/2/100,"")) | R15: =IF($F15="","",IFERROR(IFERROR(INDEX(Réttabanki!$L:$L,MATCH($F15,Réttabanki!$A:$A,0)),INDEX(Vöruskrá!$O:$O,MATCH($F15,Vöruskrá!$B:$B,0)))*($H15+IF($I15="",$H15*(1+$AD$2),$I15))/2/100,"")) | S15: =IF($F15="","",IFERROR(IFERROR(INDEX(Réttabanki!$M:$M,MATCH($F15,Réttabanki!$A:$A,0)),INDEX(Vöruskrá!$P:$P,MATCH($F15,Vöruskrá!$B:$B,0)))*($H15+IF($I15="",$H15*(1+$AD$2),$I15))/2/100,"")) | T15: =IF(F15="","",IFERROR(INDEX(Réttabanki!Q:Q,MATCH(F15,Réttabanki!A:A,0)),IFERROR(INDEX(Réttabanki!Q:Q,MATCH(F15,Réttabanki!B:B,0)),""))) | AC15: Arnarberg | AF15: =IF($F15="","",IFERROR(IFERROR(INDEX(Réttabanki!$U:$U,MATCH($F15,Réttabanki!$A:$A,0)),INDEX(Vöruskrá!$R:$R,MATCH($F15,Vöruskrá!$B:$B,0)))*$H15/1000,"")) | AG15: =IF($F15="","",IFERROR(IFERROR(INDEX(Réttabanki!$U:$U,MATCH($F15,Réttabanki!$A:$A,0)),INDEX(Vöruskrá!$R:$R,MATCH($F15,Vöruskrá!$B:$B,0)))*IF($I15="",$H15*(1+$AD$2),$I15)/1000,"")) | AH15: =IF(N($AF15)+N($AG15)=0,"",MAX(N($AF15)/$AE$6,N($AG15)/$AE$5)) | AI15: =IF($AH15="","",IF($AH15>$AE$7,"⚠ Yfir "&TEXT($AE$7,"0%"),"OK")) | AJ15: =IF($A15<>"",$A15,AJ14) -> 46258
B16: Mánudagur | C16: 35 | D16: Leikskóli | E16: Síðdegishressing | F16: Lífskornabrauð m/ tröllahöfrum og chia | G16: Lífskornabrauð | H16: 40 | J16: =IF($F16="","",IFERROR(IFERROR(INDEX(Réttabanki!$U:$U,MATCH($F16,Réttabanki!$A:$A,0)),INDEX(Vöruskrá!$R:$R,MATCH($F16,Vöruskrá!$B:$B,0)))*($H16+IF($I16="",$H16*(1+$AD$2),$I16))/2/1000,"")) -> 30 | K16: Vatn, **tröllahafrar** 21%, heilkorna **heilhveiti** 16%, **hveiti**, **hveitiglúten**, **rúgmjöl**, þurrkað súrdeig (**rúgur**, súrdeigsgerlar), **hveitikurl**, ger, chia fræ 1% (Salvia hispanica), maltextrakt (**bygg**), repjuolía, joðbætt salt, þykkingarefni (E415), sýrustillir (E262), ýruefni (E471, E472e), mjölmeðhöndlunarefni (E300) | L16: Glúten (hafrar, hveiti, rúgur, bygg) | M16: Framleitt á svæði þar sem unnið er með sesamfræ, egg, mjólk og lúpínu | N16: 241 | O16: 4.3 | P16: 0.8 | Q16: 33 | R16: 14 | S16: 0.9 | T16: =IF(F16="","",IFERROR(INDEX(Réttabanki!Q:Q,MATCH(F16,Réttabanki!A:A,0)),IFERROR(INDEX(Réttabanki!Q:Q,MATCH(F16,Réttabanki!B:B,0)),""))) | AC16: Bjarkalundur | AF16: =IF($F16="","",IFERROR(IFERROR(INDEX(Réttabanki!$U:$U,MATCH($F16,Réttabanki!$A:$A,0)),INDEX(Vöruskrá!$R:$R,MATCH($F16,Vöruskrá!$B:$B,0)))*$H16/1000,"")) -> 24 | AG16: =IF($F16="","",IFERROR(IFERROR(INDEX(Réttabanki!$U:$U,MATCH($F16,Réttabanki!$A:$A,0)),INDEX(Vöruskrá!$R:$R,MATCH($F16,Vöruskrá!$B:$B,0)))*IF($I16="",$H16*(1+$AD$2),$I16)/1000,"")) -> 36 | AH16: =IF(N($AF16)+N($AG16)=0,"",MAX(N($AF16)/$AE$6,N($AG16)/$AE$5)) -> 0.031304348 | AI16: =IF($AH16="","",IF($AH16>$AE$7,"⚠ Yfir "&TEXT($AE$7,"0%"),"OK")) -> OK | AJ16: =IF($A16<>"",$A16,AJ15) -> 46258
B17: Mánudagur | C17: 35 | D17: Leikskóli | E17: Síðdegishressing | F17: Góðostur 26% sneiðar | G17: Ostur | H17: 20 | J17: =IF($F17="","",IFERROR(IFERROR(INDEX(Réttabanki!$U:$U,MATCH($F17,Réttabanki!$A:$A,0)),INDEX(Vöruskrá!$R:$R,MATCH($F17,Vöruskrá!$B:$B,0)))*($H17+IF($I17="",$H17*(1+$AD$2),$I17))/2/1000,"")) -> 70 | K17: **Mjólk**, **undanrenna**, salt, ostahleypir. | L17: Mjólk | N17: 330 | O17: 26 | P17: 14 | Q17: 0 | R17: 25 | S17: 1.5 | T17: =IF(F17="","",IFERROR(INDEX(Réttabanki!Q:Q,MATCH(F17,Réttabanki!A:A,0)),IFERROR(INDEX(Réttabanki!Q:Q,MATCH(F17,Réttabanki!B:B,0)),""))) | AC17: Hlíðarberg | AF17: =IF($F17="","",IFERROR(IFERROR(INDEX(Réttabanki!$U:$U,MATCH($F17,Réttabanki!$A:$A,0)),INDEX(Vöruskrá!$R:$R,MATCH($F17,Vöruskrá!$B:$B,0)))*$H17/1000,"")) -> 56 | AG17: =IF($F17="","",IFERROR(IFERROR(INDEX(Réttabanki!$U:$U,MATCH($F17,Réttabanki!$A:$A,0)),INDEX(Vöruskrá!$R:$R,MATCH($F17,Vöruskrá!$B:$B,0)))*IF($I17="",$H17*(1+$AD$2),$I17)/1000,"")) -> 84 | AH17: =IF(N($AF17)+N($AG17)=0,"",MAX(N($AF17)/$AE$6,N($AG17)/$AE$5)) -> 0.073043478 | AI17: =IF($AH17="","",IF($AH17>$AE$7,"⚠ Yfir "&TEXT($AE$7,"0%"),"OK")) -> OK | AJ17: =IF($A17<>"",$A17,AJ16) -> 46258
B18: Mánudagur | C18: 35 | D18: Leikskóli | E18: Sérfæði | G18: Lífskornabrauð, tómatar, ávextir | J18: =IF($F18="","",IFERROR(IFERROR(INDEX(Réttabanki!$U:$U,MATCH($F18,Réttabanki!$A:$A,0)),INDEX(Vöruskrá!$R:$R,MATCH($F18,Vöruskrá!$B:$B,0)))*($H18+IF($I18="",$H18*(1+$AD$2),$I18))/2/1000,"")) | K18: Vatn, **tröllahafrar** 21%, heilkorna **heilhveiti** 16%, **hveiti**, **hveitiglúten**, **rúgmjöl**, þurrkað súrdeig (**rúgur**, súrdeigsgerlar), **hveitikurl**, ger, chia fræ 1% (Salvia hispanica), maltextrakt (**bygg**), repjuolía, joðbætt salt, þykkingarefni (E415), sýrustillir (E262), ýruefni (E471, E472e), mjölmeðhöndlunarefni (E300) | L18: Glúten (hafrar, hveiti, rúgur, bygg) | M18: =IF($F18="","",IFERROR(IFERROR(INDEX(Réttabanki!$F:$F,MATCH($F18,Réttabanki!$A:$A,0)),INDEX(Vöruskrá!$H:$H,MATCH($F18,Vöruskrá!$B:$B,0))),"")) | N18: =IF($F18="","",IFERROR(IFERROR(INDEX(Réttabanki!$G:$G,MATCH($F18,Réttabanki!$A:$A,0)),INDEX(Vöruskrá!$J:$J,MATCH($F18,Vöruskrá!$B:$B,0)))*($H18+IF($I18="",$H18*(1+$AD$2),$I18))/2/100,"")) | O18: =IF($F18="","",IFERROR(IFERROR(INDEX(Réttabanki!$H:$H,MATCH($F18,Réttabanki!$A:$A,0)),INDEX(Vöruskrá!$K:$K,MATCH($F18,Vöruskrá!$B:$B,0)))*($H18+IF($I18="",$H18*(1+$AD$2),$I18))/2/100,"")) | P18: =IF($F18="","",IFERROR(IFERROR(INDEX(Réttabanki!$I:$I,MATCH($F18,Réttabanki!$A:$A,0)),INDEX(Vöruskrá!$L:$L,MATCH($F18,Vöruskrá!$B:$B,0)))*($H18+IF($I18="",$H18*(1+$AD$2),$I18))/2/100,"")) | Q18: =IF($F18="","",IFERROR(IFERROR(INDEX(Réttabanki!$J:$J,MATCH($F18,Réttabanki!$A:$A,0)),INDEX(Vöruskrá!$M:$M,MATCH($F18,Vöruskrá!$B:$B,0)))*($H18+IF($I18="",$H18*(1+$AD$2),$I18))/2/100,"")) | R18: =IF($F18="","",IFERROR(IFERROR(INDEX(Réttabanki!$L:$L,MATCH($F18,Réttabanki!$A:$A,0)),INDEX(Vöruskrá!$O:$O,MATCH($F18,Vöruskrá!$B:$B,0)))*($H18+IF($I18="",$H18*(1+$AD$2),$I18))/2/100,"")) | S18: =IF($F18="","",IFERROR(IFERROR(INDEX(Réttabanki!$M:$M,MATCH($F18,Réttabanki!$A:$A,0)),INDEX(Vöruskrá!$P:$P,MATCH($F18,Vöruskrá!$B:$B,0)))*($H18+IF($I18="",$H18*(1+$AD$2),$I18))/2/100,"")) | T18: =IF(F18="","",IFERROR(INDEX(Réttabanki!Q:Q,MATCH(F18,Réttabanki!A:A,0)),IFERROR(INDEX(Réttabanki!Q:Q,MATCH(F18,Réttabanki!B:B,0)),""))) | AC18: Hörðuvellir | AF18: =IF($F18="","",IFERROR(IFERROR(INDEX(Réttabanki!$U:$U,MATCH($F18,Réttabanki!$A:$A,0)),INDEX(Vöruskrá!$R:$R,MATCH($F18,Vöruskrá!$B:$B,0)))*$H18/1000,"")) | AG18: =IF($F18="","",IFERROR(IFERROR(INDEX(Réttabanki!$U:$U,MATCH($F18,Réttabanki!$A:$A,0)),INDEX(Vöruskrá!$R:$R,MATCH($F18,Vöruskrá!$B:$B,0)))*IF($I18="",$H18*(1+$AD$2),$I18)/1000,"")) | AH18: =IF(N($AF18)+N($AG18)=0,"",MAX(N($AF18)/$AE$6,N($AG18)/$AE$5)) | AI18: =IF($AH18="","",IF($AH18>$AE$7,"⚠ Yfir "&TEXT($AE$7,"0%"),"OK")) | AJ18: =IF($A18<>"",$A18,AJ17) -> 46258
B19: Mánudagur | C19: 35 | D19: Leikskóli | E19: Sérfæði | F19: Lífskornabrauð m/ tröllahöfrum og chia | G19: Lífskornabrauð | H19: 40 | J19: =IF($F19="","",IFERROR(IFERROR(INDEX(Réttabanki!$U:$U,MATCH($F19,Réttabanki!$A:$A,0)),INDEX(Vöruskrá!$R:$R,MATCH($F19,Vöruskrá!$B:$B,0)))*($H19+IF($I19="",$H19*(1+$AD$2),$I19))/2/1000,"")) -> 30 | K19: Vatn, **tröllahafrar** 21%, heilkorna **heilhveiti** 16%, **hveiti**, **hveitiglúten**, **rúgmjöl**, þurrkað súrdeig (**rúgur**, súrdeigsgerlar), **hveitikurl**, ger, chia fræ 1% (Salvia hispanica), maltextrakt (**bygg**), repjuolía, joðbætt salt, þykkingarefni (E415), sýrustillir (E262), ýruefni (E471, E472e), mjölmeðhöndlunarefni (E300) | L19: Glúten (hafrar, hveiti, rúgur, bygg) | M19: Framleitt á svæði þar sem unnið er með sesamfræ, egg, mjólk og lúpínu | N19: 241 | O19: 4.3 | P19: 0.8 | Q19: 33 | R19: 14 | S19: 0.9 | T19: =IF(F19="","",IFERROR(INDEX(Réttabanki!Q:Q,MATCH(F19,Réttabanki!A:A,0)),IFERROR(INDEX(Réttabanki!Q:Q,MATCH(F19,Réttabanki!B:B,0)),""))) | AC19: Hraunvallaleikskóli | AF19: =IF($F19="","",IFERROR(IFERROR(INDEX(Réttabanki!$U:$U,MATCH($F19,Réttabanki!$A:$A,0)),INDEX(Vöruskrá!$R:$R,MATCH($F19,Vöruskrá!$B:$B,0)))*$H19/1000,"")) -> 24 | AG19: =IF($F19="","",IFERROR(IFERROR(INDEX(Réttabanki!$U:$U,MATCH($F19,Réttabanki!$A:$A,0)),INDEX(Vöruskrá!$R:$R,MATCH($F19,Vöruskrá!$B:$B,0)))*IF($I19="",$H19*(1+$AD$2),$I19)/1000,"")) -> 36 | AH19: =IF(N($AF19)+N($AG19)=0,"",MAX(N($AF19)/$AE$6,N($AG19)/$AE$5)) -> 0.031304348 | AI19: =IF($AH19="","",IF($AH19>$AE$7,"⚠ Yfir "&TEXT($AE$7,"0%"),"OK")) -> OK | AJ19: =IF($A19<>"",$A19,AJ18) -> 46258
B20: Mánudagur | C20: 35 | D20: Leikskóli | E20: Sérfæði | G20: Glútenlaust samlokubrauð, ostur, tómatar, ávextir | J20: =IF($F20="","",IFERROR(IFERROR(INDEX(Réttabanki!$U:$U,MATCH($F20,Réttabanki!$A:$A,0)),INDEX(Vöruskrá!$R:$R,MATCH($F20,Vöruskrá!$B:$B,0)))*($H20+IF($I20="",$H20*(1+$AD$2),$I20))/2/1000,"")) | K20: Vatn, hrísgrjónamjöl, tapíókamjöl, þykkingarefni: sellulósi, hýdroxýprópýl metýl sellulósi, karboxýmetýl sellulósi, metýl sellulósi, xantangúmmí; kartöflusterkja, psyllium hýðisduft, rakaefni: glýserín; ger, heilkorna maísmjöl, repjuolía, hrísgrjónamjöl, gullinsíróp, maíssterkja, salt, edik, rotvarnarefni: natríumprópíónat, sorbínsýra, vínedik. | **Mjólk**, **undanrenna**, salt, ostahleypir. | L20: Mjólk | AC20: Skarðshlíðarleikskóli | AF20: =IF($F20="","",IFERROR(IFERROR(INDEX(Réttabanki!$U:$U,MATCH($F20,Réttabanki!$A:$A,0)),INDEX(Vöruskrá!$R:$R,MATCH($F20,Vöruskrá!$B:$B,0)))*$H20/1000,"")) | AG20: =IF($F20="","",IFERROR(IFERROR(INDEX(Réttabanki!$U:$U,MATCH($F20,Réttabanki!$A:$A,0)),INDEX(Vöruskrá!$R:$R,MATCH($F20,Vöruskrá!$B:$B,0)))*IF($I20="",$H20*(1+$AD$2),$I20)/1000,"")) | AH20: =IF(N($AF20)+N($AG20)=0,"",MAX(N($AF20)/$AE$6,N($AG20)/$AE$5)) | AI20: =IF($AH20="","",IF($AH20>$AE$7,"⚠ Yfir "&TEXT($AE$7,"0%"),"OK")) | AJ20: =IF($A20<>"",$A20,AJ19) -> 46258
B21: Mánudagur | C21: 35 | D21: Leikskóli | E21: Sérfæði | F21: Promise - Gluten frítt hvítt brauð | G21: Glútenlaust brauð | H21: 40 | J21: =IF($F21="","",IFERROR(IFERROR(INDEX(Réttabanki!$U:$U,MATCH($F21,Réttabanki!$A:$A,0)),INDEX(Vöruskrá!$R:$R,MATCH($F21,Vöruskrá!$B:$B,0)))*($H21+IF($I21="",$H21*(1+$AD$2),$I21))/2/1000,"")) -> 30 | K21: Vatn, hrísgrjónamjöl, tapíókamjöl, þykkingarefni: sellulósi, hýdroxýprópýl metýl sellulósi, karboxýmetýl sellulósi, metýl sellulósi, xantangúmmí; kartöflusterkja, psyllium hýðisduft, rakaefni: glýserín; ger, heilkorna maísmjöl, repjuolía, hrísgrjónamjöl, gullinsíróp, maíssterkja, salt, edik, rotvarnarefni: natríumprópíónat, sorbínsýra, vínedik. | N21: 225 | O21: 3 | P21: 0.3 | Q21: 41 | R21: 2.1 | S21: 1 | AC21: Smáralundur | AF21: =IF($F21="","",IFERROR(IFERROR(INDEX(Réttabanki!$U:$U,MATCH($F21,Réttabanki!$A:$A,0)),INDEX(Vöruskrá!$R:$R,MATCH($F21,Vöruskrá!$B:$B,0)))*$H21/1000,"")) -> 24 | AG21: =IF($F21="","",IFERROR(IFERROR(INDEX(Réttabanki!$U:$U,MATCH($F21,Réttabanki!$A:$A,0)),INDEX(Vöruskrá!$R:$R,MATCH($F21,Vöruskrá!$B:$B,0)))*IF($I21="",$H21*(1+$AD$2),$I21)/1000,"")) -> 36 | AH21: =IF(N($AF21)+N($AG21)=0,"",MAX(N($AF21)/$AE$6,N($AG21)/$AE$5)) -> 0.031304348 | AI21: =IF($AH21="","",IF($AH21>$AE$7,"⚠ Yfir "&TEXT($AE$7,"0%"),"OK")) -> OK | AJ21: =IF($A21<>"",$A21,AJ20) -> 46258
B22: Mánudagur | C22: 35 | D22: Leikskóli | E22: Sérfæði | F22: Góðostur 26% sneiðar | G22: Ostur | H22: 20 | J22: =IF($F22="","",IFERROR(IFERROR(INDEX(Réttabanki!$U:$U,MATCH($F22,Réttabanki!$A:$A,0)),INDEX(Vöruskrá!$R:$R,MATCH($F22,Vöruskrá!$B:$B,0)))*($H22+IF($I22="",$H22*(1+$AD$2),$I22))/2/1000,"")) -> 70 | K22: **Mjólk**, **undanrenna**, salt, ostahleypir. | L22: Mjólk | N22: 330 | O22: 26 | P22: 14 | Q22: 0 | R22: 25 | S22: 1.5 | AC22: Stekkjarás | AF22: =IF($F22="","",IFERROR(IFERROR(INDEX(Réttabanki!$U:$U,MATCH($F22,Réttabanki!$A:$A,0)),INDEX(Vöruskrá!$R:$R,MATCH($F22,Vöruskrá!$B:$B,0)))*$H22/1000,"")) -> 56 | AG22: =IF($F22="","",IFERROR(IFERROR(INDEX(Réttabanki!$U:$U,MATCH($F22,Réttabanki!$A:$A,0)),INDEX(Vöruskrá!$R:$R,MATCH($F22,Vöruskrá!$B:$B,0)))*IF($I22="",$H22*(1+$AD$2),$I22)/1000,"")) -> 84 | AH22: =IF(N($AF22)+N($AG22)=0,"",MAX(N($AF22)/$AE$6,N($AG22)/$AE$5)) -> 0.073043478 | AI22: =IF($AH22="","",IF($AH22>$AE$7,"⚠ Yfir "&TEXT($AE$7,"0%"),"OK")) -> OK | AJ22: =IF($A22<>"",$A22,AJ21) -> 46258
B23: Mánudagur | C23: 35 | F23: Leikskóli — dagskostnaður | J23: =SUMIFS($AF$3:$AF$796,$AJ$3:$AJ$796,$AJ23,$D$3:$D$796,"<>Grunnskólar starfsmenn",$E$3:$E$796,"Aðalréttur")+SUMIFS($AF$3:$AF$796,$AJ$3:$AJ$796,$AJ23,$D$3:$D$796,"<>Grunnskólar starfsmenn",$E$3:$E$796,"Meðlætisbar")+SUMIFS($AF$3:$AF$796,$AJ$3:$AJ$796,$AJ23,$D$3:$D$796,"<>Grunnskólar starfsmenn",$E$3:$E$796,"Síðdegishressing") -> 120 | K23: ⚠ Vara finnst ekki í Réttabanka/Vöruskrá — bætið henni við | AC23: Tjarnarás | AF23: =IF($F23="","",IFERROR(IFERROR(INDEX(Réttabanki!$U:$U,MATCH($F23,Réttabanki!$A:$A,0)),INDEX(Vöruskrá!$R:$R,MATCH($F23,Vöruskrá!$B:$B,0)))*$H23/1000,"")) | AG23: =IF($F23="","",IFERROR(IFERROR(INDEX(Réttabanki!$U:$U,MATCH($F23,Réttabanki!$A:$A,0)),INDEX(Vöruskrá!$R:$R,MATCH($F23,Vöruskrá!$B:$B,0)))*IF($I23="",$H23*(1+$AD$2),$I23)/1000,"")) | AH23: =IF($J23="","",$J23/$AE$6) -> 0.088888889 | AI23: =IF($AH23="","",IF($AH23>$AE$7,"⚠ Yfir "&TEXT($AE$7,"0%"),"OK")) -> OK | AJ23: =IF($A23<>"",$A23,AJ22) -> 46258
B24: Mánudagur | C24: 35 | F24: Grunnskóli — dagskostnaður | J24: =SUMIFS($AG$3:$AG$796,$AJ$3:$AJ$796,$AJ24,$D$3:$D$796,"<>Grunnskólar starfsmenn",$E$3:$E$796,"Aðalréttur")+SUMIFS($AG$3:$AG$796,$AJ$3:$AJ$796,$AJ24,$D$3:$D$796,"<>Grunnskólar starfsmenn",$E$3:$E$796,"Meðlætisbar") -> 60 | K24: ⚠ Vara finnst ekki í Réttabanka/Vöruskrá — bætið henni við | AC24: Vesturkot | AF24: =IF($F24="","",IFERROR(IFERROR(INDEX(Réttabanki!$U:$U,MATCH($F24,Réttabanki!$A:$A,0)),INDEX(Vöruskrá!$R:$R,MATCH($F24,Vöruskrá!$B:$B,0)))*$H24/1000,"")) | AG24: =IF($F24="","",IFERROR(IFERROR(INDEX(Réttabanki!$U:$U,MATCH($F24,Réttabanki!$A:$A,0)),INDEX(Vöruskrá!$R:$R,MATCH($F24,Vöruskrá!$B:$B,0)))*IF($I24="",$H24*(1+$AD$2),$I24)/1000,"")) | AH24: =IF($J24="","",$J24/$AE$5) -> 0.052173913 | AI24: =IF($AH24="","",IF($AH24>$AE$7,"⚠ Yfir "&TEXT($AE$7,"0%"),"OK")) -> OK | AJ24: =IF($A24<>"",$A24,AJ23) -> 46258
A25: 46259 | B25: Þriðjudagur | C25: 35 | D25: Grunnskóli | E25: Aðalréttur | G25: Plokkfiskur, rúgbrauð, smjör | J25: =IF($F25="","",IFERROR(IFERROR(INDEX(Réttabanki!$U:$U,MATCH($F25,Réttabanki!$A:$A,0)),INDEX(Vöruskrá!$R:$R,MATCH($F25,Vöruskrá!$B:$B,0)))*($H25+IF($I25="",$H25*(1+$AD$2),$I25))/2/1000,"")) | K25: Ýsa, salt. | Kartöflur | Laukur | **Mjólk**, laktasaensím, D-vítamín. Síuð, fitusprengd og gerilsneydd. | **Rjómi**, salt. | Maíssterkja. | Salt (salt, kekkjavarnarefni E535, lyftiefni E500). | Svartur pipar 100% (Piper nigrum), hitaþurrkað. | Vatn | **Rúg**mjöl, vatn, sykur, heil**hveiti**, maltað **bygg**, malt extrakt (úr **byggI**), súrdeigsduft úr hveiti (**hveiti**, mjólkursýrugerlar), salt, rotvarnarefni (E282), ger, mjölmeðhöndlunarefni (E300), kekkjarvarnarefni (E535), bindiefni (E491) | **Rjómi**, salt. | L25: Fiskur, Mjólk, Glúten (rúgur, hveiti, bygg) | M25: =IF($F25="","",IFERROR(IFERROR(INDEX(Réttabanki!$F:$F,MATCH($F25,Réttabanki!$A:$A,0)),INDEX(Vöruskrá!$H:$H,MATCH($F25,Vöruskrá!$B:$B,0))),"")) | N25: =IF($F25="","",IFERROR(IFERROR(INDEX(Réttabanki!$G:$G,MATCH($F25,Réttabanki!$A:$A,0)),INDEX(Vöruskrá!$J:$J,MATCH($F25,Vöruskrá!$B:$B,0)))*($H25+IF($I25="",$H25*(1+$AD$2),$I25))/2/100,"")) | O25: =IF($F25="","",IFERROR(IFERROR(INDEX(Réttabanki!$H:$H,MATCH($F25,Réttabanki!$A:$A,0)),INDEX(Vöruskrá!$K:$K,MATCH($F25,Vöruskrá!$B:$B,0)))*($H25+IF($I25="",$H25*(1+$AD$2),$I25))/2/100,"")) | P25: =IF($F25="","",IFERROR(IFERROR(INDEX(Réttabanki!$I:$I,MATCH($F25,Réttabanki!$A:$A,0)),INDEX(Vöruskrá!$L:$L,MATCH($F25,Vöruskrá!$B:$B,0)))*($H25+IF($I25="",$H25*(1+$AD$2),$I25))/2/100,"")) | Q25: =IF($F25="","",IFERROR(IFERROR(INDEX(Réttabanki!$J:$J,MATCH($F25,Réttabanki!$A:$A,0)),INDEX(Vöruskrá!$M:$M,MATCH($F25,Vöruskrá!$B:$B,0)))*($H25+IF($I25="",$H25*(1+$AD$2),$I25))/2/100,"")) | R25: =IF($F25="","",IFERROR(IFERROR(INDEX(Réttabanki!$L:$L,MATCH($F25,Réttabanki!$A:$A,0)),INDEX(Vöruskrá!$O:$O,MATCH($F25,Vöruskrá!$B:$B,0)))*($H25+IF($I25="",$H25*(1+$AD$2),$I25))/2/100,"")) | S25: =IF($F25="","",IFERROR(IFERROR(INDEX(Réttabanki!$M:$M,MATCH($F25,Réttabanki!$A:$A,0)),INDEX(Vöruskrá!$P:$P,MATCH($F25,Vöruskrá!$B:$B,0)))*($H25+IF($I25="",$H25*(1+$AD$2),$I25))/2/100,"")) | T25: =IF(F25="","",IFERROR(INDEX(Réttabanki!Q:Q,MATCH(F25,Réttabanki!A:A,0)),IFERROR(INDEX(Réttabanki!Q:Q,MATCH(F25,Réttabanki!B:B,0)),""))) | AC25: Víðivellir | AF25: =IF($F25="","",IFERROR(IFERROR(INDEX(Réttabanki!$U:$U,MATCH($F25,Réttabanki!$A:$A,0)),INDEX(Vöruskrá!$R:$R,MATCH($F25,Vöruskrá!$B:$B,0)))*$H25/1000,"")) | AG25: =IF($F25="","",IFERROR(IFERROR(INDEX(Réttabanki!$U:$U,MATCH($F25,Réttabanki!$A:$A,0)),INDEX(Vöruskrá!$R:$R,MATCH($F25,Vöruskrá!$B:$B,0)))*IF($I25="",$H25*(1+$AD$2),$I25)/1000,"")) | AH25: =IF(N($AF25)+N($AG25)=0,"",MAX(N($AF25)/$AE$6,N($AG25)/$AE$5)) | AI25: =IF($AH25="","",IF($AH25>$AE$7,"⚠ Yfir "&TEXT($AE$7,"0%"),"OK")) | AJ25: =IF($A25<>"",$A25,AJ24) -> 46259
B26: Þriðjudagur | C26: 35 | D26: Grunnskólar starfsmenn | E26: Aðalréttur | F26: Plokkfiskur „kennaraútgáfa“ | G26: Plokkfiskur | I26: 250 | J26: =IF($F26="","",IFERROR(IFERROR(INDEX(Réttabanki!$U:$U,MATCH($F26,Réttabanki!$A:$A,0)),INDEX(Vöruskrá!$R:$R,MATCH($F26,Vöruskrá!$B:$B,0)))*($H26+IF($I26="",$H26*(1+$AD$2),$I26))/2/1000,"")) | K26: Ýsa, salt. | Kartöflur | Laukur | **Mjólk**, laktasaensím, D-vítamín. Síuð, fitusprengd og gerilsneydd. | **Rjómi**, salt. | Maíssterkja. | Salt (salt, kekkjavarnarefni E535, lyftiefni E500). | Svartur pipar 100% (Piper nigrum), hitaþurrkað. | Vatn | L26: Fiskur, Mjólk | N26: 107.3 | O26: 3.7 | P26: 1.92 | Q26: 8.04 | R26: 7.26 | S26: 1.79 | T26: 1 | U26: Kælt | V26: Ofn | W26: 140 | X26: 35-40 | Y26: 75 | Z26: Hræra 1 sinni | AF26: =IF($F26="","",IFERROR(IFERROR(INDEX(Réttabanki!$U:$U,MATCH($F26,Réttabanki!$A:$A,0)),INDEX(Vöruskrá!$R:$R,MATCH($F26,Vöruskrá!$B:$B,0)))*$H26/1000,"")) | AG26: =IF($F26="","",IFERROR(IFERROR(INDEX(Réttabanki!$U:$U,MATCH($F26,Réttabanki!$A:$A,0)),INDEX(Vöruskrá!$R:$R,MATCH($F26,Vöruskrá!$B:$B,0)))*IF($I26="",$H26*(1+$AD$2),$I26)/1000,"")) | AH26: =IF(N($AF26)+N($AG26)=0,"",MAX(N($AF26)/$AE$6,N($AG26)/$AE$5)) | AI26: =IF($AH26="","",IF($AH26>$AE$7,"⚠ Yfir "&TEXT($AE$7,"0%"),"OK")) | AJ26: =IF($A26<>"",$A26,AJ25) -> 46259
B27: Þriðjudagur | C27: 35 | D27: Grunnskólar starfsmenn | E27: Aðalréttur | F27: Ömmu rúgbrauð (mjólkurlaust) | G27: Rúgbrauð | I27: 25 | J27: =IF($F27="","",IFERROR(IFERROR(INDEX(Réttabanki!$U:$U,MATCH($F27,Réttabanki!$A:$A,0)),INDEX(Vöruskrá!$R:$R,MATCH($F27,Vöruskrá!$B:$B,0)))*($H27+IF($I27="",$H27*(1+$AD$2),$I27))/2/1000,"")) -> 12.725 | K27: **Rúg**mjöl, vatn, sykur, heil**hveiti**, maltað **bygg**, malt extrakt (úr **byggI**), súrdeigsduft úr hveiti (**hveiti**, mjólkursýrugerlar), salt, rotvarnarefni (E282), ger, mjölmeðhöndlunarefni (E300), kekkjarvarnarefni (E535), bindiefni (E491) | L27: Glúten (rúgur, hveiti, bygg) | M27: Gæti innihaldið snefil af sesam | N27: 252 | O27: 1.1 | P27: 0.2 | Q27: 50 | R27: 4.8 | S27: 0.6 | T27: =IF(F27="","",IFERROR(INDEX(Réttabanki!Q:Q,MATCH(F27,Réttabanki!A:A,0)),IFERROR(INDEX(Réttabanki!Q:Q,MATCH(F27,Réttabanki!B:B,0)),""))) | U27: Kælt | V27: Engin (kalt) | AF27: =IF($F27="","",IFERROR(IFERROR(INDEX(Réttabanki!$U:$U,MATCH($F27,Réttabanki!$A:$A,0)),INDEX(Vöruskrá!$R:$R,MATCH($F27,Vöruskrá!$B:$B,0)))*$H27/1000,"")) -> 0 | AG27: =IF($F27="","",IFERROR(IFERROR(INDEX(Réttabanki!$U:$U,MATCH($F27,Réttabanki!$A:$A,0)),INDEX(Vöruskrá!$R:$R,MATCH($F27,Vöruskrá!$B:$B,0)))*IF($I27="",$H27*(1+$AD$2),$I27)/1000,"")) -> 25.45 | AH27: =IF(N($AF27)+N($AG27)=0,"",MAX(N($AF27)/$AE$6,N($AG27)/$AE$5)) -> 0.022130435 | AI27: =IF($AH27="","",IF($AH27>$AE$7,"⚠ Yfir "&TEXT($AE$7,"0%"),"OK")) -> OK | AJ27: =IF($A27<>"",$A27,AJ26) -> 46259
B28: Þriðjudagur | C28: 35 | D28: Grunnskólar starfsmenn | E28: Aðalréttur | F28: Smjör 500 g | G28: Smjör | I28: 10 | J28: =IF($F28="","",IFERROR(IFERROR(INDEX(Réttabanki!$U:$U,MATCH($F28,Réttabanki!$A:$A,0)),INDEX(Vöruskrá!$R:$R,MATCH($F28,Vöruskrá!$B:$B,0)))*($H28+IF($I28="",$H28*(1+$AD$2),$I28))/2/1000,"")) -> 11.5 | K28: **Rjómi**, salt. | L28: Mjólk | N28: 738 | O28: 82 | P28: 49 | Q28: 0.4 | R28: 0.6 | S28: 1.2 | T28: =IF(F28="","",IFERROR(INDEX(Réttabanki!Q:Q,MATCH(F28,Réttabanki!A:A,0)),IFERROR(INDEX(Réttabanki!Q:Q,MATCH(F28,Réttabanki!B:B,0)),""))) | U28: Kælt | V28: Engin (kalt) | AF28: =IF($F28="","",IFERROR(IFERROR(INDEX(Réttabanki!$U:$U,MATCH($F28,Réttabanki!$A:$A,0)),INDEX(Vöruskrá!$R:$R,MATCH($F28,Vöruskrá!$B:$B,0)))*$H28/1000,"")) -> 0 | AG28: =IF($F28="","",IFERROR(IFERROR(INDEX(Réttabanki!$U:$U,MATCH($F28,Réttabanki!$A:$A,0)),INDEX(Vöruskrá!$R:$R,MATCH($F28,Vöruskrá!$B:$B,0)))*IF($I28="",$H28*(1+$AD$2),$I28)/1000,"")) -> 23 | AH28: =IF(N($AF28)+N($AG28)=0,"",MAX(N($AF28)/$AE$6,N($AG28)/$AE$5)) -> 0.02 | AI28: =IF($AH28="","",IF($AH28>$AE$7,"⚠ Yfir "&TEXT($AE$7,"0%"),"OK")) -> OK | AJ28: =IF($A28<>"",$A28,AJ27) -> 46259
B29: Þriðjudagur | C29: 35 | D29: Bæði | E29: Hliðarréttur | G29: Grænmetiskarrí | J29: =IF($F29="","",IFERROR(IFERROR(INDEX(Réttabanki!$U:$U,MATCH($F29,Réttabanki!$A:$A,0)),INDEX(Vöruskrá!$R:$R,MATCH($F29,Vöruskrá!$B:$B,0)))*($H29+IF($I29="",$H29*(1+$AD$2),$I29))/2/1000,"")) | K29: Kókosmjólk (kókosmjólk, kókosvatn, vatn), smjörbaunir, laukur, kúrbítur, blómkál, gul paprika, sætar kartöflur, eplasafi (eplasafi, sýrustillir E330), repjuolía, sítrónusafi, hvítlaukur, maíssterkja, salt, kóríander, chilimauk (rauður chili, gulrætur, salt, paprika, sýrustillir E260, E330, bindiefni E412, E415, repjuolía, rotvarnarefni E202, E211, sítrónusafi, sýra E330, litarefni E160c), engifer, karrý 0,4%, túrmerik, limelauf, svartur pipar. | L29: Engir skráðir | AF29: =IF($F29="","",IFERROR(IFERROR(INDEX(Réttabanki!$U:$U,MATCH($F29,Réttabanki!$A:$A,0)),INDEX(Vöruskrá!$R:$R,MATCH($F29,Vöruskrá!$B:$B,0)))*$H29/1000,"")) | AG29: =IF($F29="","",IFERROR(IFERROR(INDEX(Réttabanki!$U:$U,MATCH($F29,Réttabanki!$A:$A,0)),INDEX(Vöruskrá!$R:$R,MATCH($F29,Vöruskrá!$B:$B,0)))*IF($I29="",$H29*(1+$AD$2),$I29)/1000,"")) | AH29: =IF(N($AF29)+N($AG29)=0,"",MAX(N($AF29)/$AE$6,N($AG29)/$AE$5)) | AI29: =IF($AH29="","",IF($AH29>$AE$7,"⚠ Yfir "&TEXT($AE$7,"0%"),"OK")) | AJ29: =IF($A29<>"",$A29,AJ28) -> 46259
B30: Þriðjudagur | C30: 35 | D30: Bæði | E30: Hliðarréttur | F30: Grænmetis karrí | G30: Grænmetiskarrí | H30: 220 | I30: 250 | J30: =IF($F30="","",IFERROR(IFERROR(INDEX(Réttabanki!$U:$U,MATCH($F30,Réttabanki!$A:$A,0)),INDEX(Vöruskrá!$R:$R,MATCH($F30,Vöruskrá!$B:$B,0)))*($H30+IF($I30="",$H30*(1+$AD$2),$I30))/2/1000,"")) -> 282 | K30: Kókosmjólk (kókosmjólk, kókosvatn, vatn), smjörbaunir, laukur, kúrbítur, blómkál, gul paprika, sætar kartöflur, eplasafi (eplasafi, sýrustillir E330), repjuolía, sítrónusafi, hvítlaukur, maíssterkja, salt, kóríander, chilimauk (rauður chili, gulrætur, salt, paprika, sýrustillir E260, E330, bindiefni E412, E415, repjuolía, rotvarnarefni E202, E211, sítrónusafi, sýra E330, litarefni E160c), engifer, karrý 0,4%, túrmerik, limelauf, svartur pipar. | M30: Gæti innihaldið snefil af hnetum og sesam. | N30: 151 | O30: 7 | P30: 3.3 | Q30: 15.2 | R30: 5.1 | S30: 0.9 | T30: 1 | U30: Kælt | V30: Ofn | W30: 140 | X30: 20-25 | Y30: 75 | Z30: Hræra 1 sinni | AF30: =IF($F30="","",IFERROR(IFERROR(INDEX(Réttabanki!$U:$U,MATCH($F30,Réttabanki!$A:$A,0)),INDEX(Vöruskrá!$R:$R,MATCH($F30,Vöruskrá!$B:$B,0)))*$H30/1000,"")) -> 264 | AG30: =IF($F30="","",IFERROR(IFERROR(INDEX(Réttabanki!$U:$U,MATCH($F30,Réttabanki!$A:$A,0)),INDEX(Vöruskrá!$R:$R,MATCH($F30,Vöruskrá!$B:$B,0)))*IF($I30="",$H30*(1+$AD$2),$I30)/1000,"")) -> 300 | AH30: =IF(N($AF30)+N($AG30)=0,"",MAX(N($AF30)/$AE$6,N($AG30)/$AE$5)) -> 0.26086957 | AI30: =IF($AH30="","",IF($AH30>$AE$7,"⚠ Yfir "&TEXT($AE$7,"0%"),"OK")) -> OK | AJ30: =IF($A30<>"",$A30,AJ29) -> 46259
B31: Þriðjudagur | C31: 35 | D31: Leikskóli | E31: Aðalréttur | G31: Plokkfiskur, rúgbrauð, smjör | J31: =IF($F31="","",IFERROR(IFERROR(INDEX(Réttabanki!$U:$U,MATCH($F31,Réttabanki!$A:$A,0)),INDEX(Vöruskrá!$R:$R,MATCH($F31,Vöruskrá!$B:$B,0)))*($H31+IF($I31="",$H31*(1+$AD$2),$I31))/2/1000,"")) | K31: **Ýsa/ þorskur**, kartöflur, laukur, **mjólk** ( mjólk, laktasaensím, D-vítamín), maissterkja, kryddblanda(vatn, rapsolía, salt, hvítlauksmauk, vínedik, sykur, þurrkaðar laukur, krydd, jurtir, þykkingarefni: xantangúmmí E 415, hvítlauksextract, rotvarnarefni: kalíumsorbat E 202, kryddextract), salt (salt, kekkjavarnarefni E535, lyftiefni E500), hvítur pipar | **Rúg**mjöl, vatn, sykur, heil**hveiti**, maltað **bygg**, malt extrakt (úr **byggI**), súrdeigsduft úr hveiti (**hveiti**, mjólkursýrugerlar), salt, rotvarnarefni (E282), ger, mjölmeðhöndlunarefni (E300), kekkjarvarnarefni (E535), bindiefni (E491) | **Rjómi**, salt. | L31: Fiskur, mjólk, Glúten (rúgur, hveiti, bygg), Mjólk | AF31: =IF($F31="","",IFERROR(IFERROR(INDEX(Réttabanki!$U:$U,MATCH($F31,Réttabanki!$A:$A,0)),INDEX(Vöruskrá!$R:$R,MATCH($F31,Vöruskrá!$B:$B,0)))*$H31/1000,"")) | AG31: =IF($F31="","",IFERROR(IFERROR(INDEX(Réttabanki!$U:$U,MATCH($F31,Réttabanki!$A:$A,0)),INDEX(Vöruskrá!$R:$R,MATCH($F31,Vöruskrá!$B:$B,0)))*IF($I31="",$H31*(1+$AD$2),$I31)/1000,"")) | AH31: =IF(N($AF31)+N($AG31)=0,"",MAX(N($AF31)/$AE$6,N($AG31)/$AE$5)) | AI31: =IF($AH31="","",IF($AH31>$AE$7,"⚠ Yfir "&TEXT($AE$7,"0%"),"OK")) | AJ31: =IF($A31<>"",$A31,AJ30) -> 46259
B32: Þriðjudagur | C32: 35 | D32: Leikskóli | E32: Aðalréttur | F32: Plokkfiskur - Matarstund | G32: Plokkfiskur | H32: 200 | J32: =IF($F32="","",IFERROR(IFERROR(INDEX(Réttabanki!$U:$U,MATCH($F32,Réttabanki!$A:$A,0)),INDEX(Vöruskrá!$R:$R,MATCH($F32,Vöruskrá!$B:$B,0)))*($H32+IF($I32="",$H32*(1+$AD$2),$I32))/2/1000,"")) -> 472.5 | K32: **Ýsa/ þorskur**, kartöflur, laukur, **mjólk** ( mjólk, laktasaensím, D-vítamín), maissterkja, kryddblanda(vatn, rapsolía, salt, hvítlauksmauk, vínedik, sykur, þurrkaðar laukur, krydd, jurtir, þykkingarefni: xantangúmmí E 415, hvítlauksextract, rotvarnarefni: kalíumsorbat E 202, kryddextract), salt (salt, kekkjavarnarefni E535, lyftiefni E500), hvítur pipar | L32: Fiskur, mjólk | N32: 108 | O32: 4.2 | P32: 2.6 | Q32: 9.4 | R32: 8.2 | S32: 0.5 | T32: 2 | U32: Kælt | V32: Ofn | W32: 140 | X32: 35-40 | Y32: 75 | Z32: Hræra 1 sinni | AF32: =IF($F32="","",IFERROR(IFERROR(INDEX(Réttabanki!$U:$U,MATCH($F32,Réttabanki!$A:$A,0)),INDEX(Vöruskrá!$R:$R,MATCH($F32,Vöruskrá!$B:$B,0)))*$H32/1000,"")) -> 378 | AG32: =IF($F32="","",IFERROR(IFERROR(INDEX(Réttabanki!$U:$U,MATCH($F32,Réttabanki!$A:$A,0)),INDEX(Vöruskrá!$R:$R,MATCH($F32,Vöruskrá!$B:$B,0)))*IF($I32="",$H32*(1+$AD$2),$I32)/1000,"")) -> 567 | AH32: =IF(N($AF32)+N($AG32)=0,"",MAX(N($AF32)/$AE$6,N($AG32)/$AE$5)) -> 0.49304348 | AI32: =IF($AH32="","",IF($AH32>$AE$7,"⚠ Yfir "&TEXT($AE$7,"0%"),"OK")) -> ⚠ Yfir 30% | AJ32: =IF($A32<>"",$A32,AJ31) -> 46259
B33: Þriðjudagur | C33: 35 | D33: Leikskóli | E33: Aðalréttur | F33: Ömmu rúgbrauð (mjólkurlaust) | G33: Rúgbrauð | H33: 25 | I33: 25 | J33: =IF($F33="","",IFERROR(IFERROR(INDEX(Réttabanki!$U:$U,MATCH($F33,Réttabanki!$A:$A,0)),INDEX(Vöruskrá!$R:$R,MATCH($F33,Vöruskrá!$B:$B,0)))*($H33+IF($I33="",$H33*(1+$AD$2),$I33))/2/1000,"")) -> 25.45 | K33: **Rúg**mjöl, vatn, sykur, heil**hveiti**, maltað **bygg**, malt extrakt (úr **byggI**), súrdeigsduft úr hveiti (**hveiti**, mjólkursýrugerlar), salt, rotvarnarefni (E282), ger, mjölmeðhöndlunarefni (E300), kekkjarvarnarefni (E535), bindiefni (E491) | L33: Glúten (rúgur, hveiti, bygg) | M33: Gæti innihaldið snefil af sesam | N33: 252 | O33: 1.1 | P33: 0.2 | Q33: 50 | R33: 4.8 | S33: 0.6 | T33: =IF(F33="","",IFERROR(INDEX(Réttabanki!Q:Q,MATCH(F33,Réttabanki!A:A,0)),IFERROR(INDEX(Réttabanki!Q:Q,MATCH(F33,Réttabanki!B:B,0)),""))) | U33: Kælt | V33: Engin (kalt) | AF33: =IF($F33="","",IFERROR(IFERROR(INDEX(Réttabanki!$U:$U,MATCH($F33,Réttabanki!$A:$A,0)),INDEX(Vöruskrá!$R:$R,MATCH($F33,Vöruskrá!$B:$B,0)))*$H33/1000,"")) -> 25.45 | AG33: =IF($F33="","",IFERROR(IFERROR(INDEX(Réttabanki!$U:$U,MATCH($F33,Réttabanki!$A:$A,0)),INDEX(Vöruskrá!$R:$R,MATCH($F33,Vöruskrá!$B:$B,0)))*IF($I33="",$H33*(1+$AD$2),$I33)/1000,"")) -> 25.45 | AH33: =IF(N($AF33)+N($AG33)=0,"",MAX(N($AF33)/$AE$6,N($AG33)/$AE$5)) -> 0.022130435 | AI33: =IF($AH33="","",IF($AH33>$AE$7,"⚠ Yfir "&TEXT($AE$7,"0%"),"OK")) -> OK | AJ33: =IF($A33<>"",$A33,AJ32) -> 46259
B34: Þriðjudagur | C34: 35 | D34: Leikskóli | E34: Aðalréttur | F34: Smjör 500 g | G34: Smjör | H34: 10 | I34: 10 | J34: =IF($F34="","",IFERROR(IFERROR(INDEX(Réttabanki!$U:$U,MATCH($F34,Réttabanki!$A:$A,0)),INDEX(Vöruskrá!$R:$R,MATCH($F34,Vöruskrá!$B:$B,0)))*($H34+IF($I34="",$H34*(1+$AD$2),$I34))/2/1000,"")) -> 23 | K34: **Rjómi**, salt. | L34: Mjólk | N34: 738 | O34: 82 | P34: 49 | Q34: 0.4 | R34: 0.6 | S34: 1.2 | T34: =IF(F34="","",IFERROR(INDEX(Réttabanki!Q:Q,MATCH(F34,Réttabanki!A:A,0)),IFERROR(INDEX(Réttabanki!Q:Q,MATCH(F34,Réttabanki!B:B,0)),""))) | U34: Kælt | V34: Engin (kalt) | AF34: =IF($F34="","",IFERROR(IFERROR(INDEX(Réttabanki!$U:$U,MATCH($F34,Réttabanki!$A:$A,0)),INDEX(Vöruskrá!$R:$R,MATCH($F34,Vöruskrá!$B:$B,0)))*$H34/1000,"")) -> 23 | AG34: =IF($F34="","",IFERROR(IFERROR(INDEX(Réttabanki!$U:$U,MATCH($F34,Réttabanki!$A:$A,0)),INDEX(Vöruskrá!$R:$R,MATCH($F34,Vöruskrá!$B:$B,0)))*IF($I34="",$H34*(1+$AD$2),$I34)/1000,"")) -> 23 | AH34: =IF(N($AF34)+N($AG34)=0,"",MAX(N($AF34)/$AE$6,N($AG34)/$AE$5)) -> 0.02 | AI34: =IF($AH34="","",IF($AH34>$AE$7,"⚠ Yfir "&TEXT($AE$7,"0%"),"OK")) -> OK | AJ34: =IF($A34<>"",$A34,AJ33) -> 46259
B35: Þriðjudagur | C35: 35 | D35: Leikskóli | E35: Sérfæði | G35: Plokkfiskur, hrísgrjónabrauð | J35: =IF($F35="","",IFERROR(IFERROR(INDEX(Réttabanki!$U:$U,MATCH($F35,Réttabanki!$A:$A,0)),INDEX(Vöruskrá!$R:$R,MATCH($F35,Vöruskrá!$B:$B,0)))*($H35+IF($I35="",$H35*(1+$AD$2),$I35))/2/1000,"")) | K35: **Ýsa/ þorskur**, kartöflur, laukur, **mjólk** ( mjólk, laktasaensím, D-vítamín), maissterkja, kryddblanda(vatn, rapsolía, salt, hvítlauksmauk, vínedik, sykur, þurrkaðar laukur, krydd, jurtir, þykkingarefni: xantangúmmí E 415, hvítlauksextract, rotvarnarefni: kalíumsorbat E 202, kryddextract), salt (salt, kekkjavarnarefni E535, lyftiefni E500), hvítur pipar | Hrísmjöl, vatn, hirsi, krydd, súrdeig, salt | L35: Fiskur, mjólk | AF35: =IF($F35="","",IFERROR(IFERROR(INDEX(Réttabanki!$U:$U,MATCH($F35,Réttabanki!$A:$A,0)),INDEX(Vöruskrá!$R:$R,MATCH($F35,Vöruskrá!$B:$B,0)))*$H35/1000,"")) | AG35: =IF($F35="","",IFERROR(IFERROR(INDEX(Réttabanki!$U:$U,MATCH($F35,Réttabanki!$A:$A,0)),INDEX(Vöruskrá!$R:$R,MATCH($F35,Vöruskrá!$B:$B,0)))*IF($I35="",$H35*(1+$AD$2),$I35)/1000,"")) | AH35: =IF(N($AF35)+N($AG35)=0,"",MAX(N($AF35)/$AE$6,N($AG35)/$AE$5)) | AI35: =IF($AH35="","",IF($AH35>$AE$7,"⚠ Yfir "&TEXT($AE$7,"0%"),"OK")) | AJ35: =IF($A35<>"",$A35,AJ34) -> 46259
B36: Þriðjudagur | C36: 35 | D36: Leikskóli | E36: Sérfæði | F36: Plokkfiskur - Matarstund | G36: Plokkfiskur | H36: 200 | J36: =IF($F36="","",IFERROR(IFERROR(INDEX(Réttabanki!$U:$U,MATCH($F36,Réttabanki!$A:$A,0)),INDEX(Vöruskrá!$R:$R,MATCH($F36,Vöruskrá!$B:$B,0)))*($H36+IF($I36="",$H36*(1+$AD$2),$I36))/2/1000,"")) -> 472.5 | K36: **Ýsa/ þorskur**, kartöflur, laukur, **mjólk** ( mjólk, laktasaensím, D-vítamín), maissterkja, kryddblanda(vatn, rapsolía, salt, hvítlauksmauk, vínedik, sykur, þurrkaðar laukur, krydd, jurtir, þykkingarefni: xantangúmmí E 415, hvítlauksextract, rotvarnarefni: kalíumsorbat E 202, kryddextract), salt (salt, kekkjavarnarefni E535, lyftiefni E500), hvítur pipar | L36: Fiskur, mjólk | N36: 108 | O36: 4.2 | P36: 2.6 | Q36: 9.4 | R36: 8.2 | S36: 0.5 | AF36: =IF($F36="","",IFERROR(IFERROR(INDEX(Réttabanki!$U:$U,MATCH($F36,Réttabanki!$A:$A,0)),INDEX(Vöruskrá!$R:$R,MATCH($F36,Vöruskrá!$B:$B,0)))*$H36/1000,"")) -> 378 | AG36: =IF($F36="","",IFERROR(IFERROR(INDEX(Réttabanki!$U:$U,MATCH($F36,Réttabanki!$A:$A,0)),INDEX(Vöruskrá!$R:$R,MATCH($F36,Vöruskrá!$B:$B,0)))*IF($I36="",$H36*(1+$AD$2),$I36)/1000,"")) -> 567 | AH36: =IF(N($AF36)+N($AG36)=0,"",MAX(N($AF36)/$AE$6,N($AG36)/$AE$5)) -> 0.49304348 | AI36: =IF($AH36="","",IF($AH36>$AE$7,"⚠ Yfir "&TEXT($AE$7,"0%"),"OK")) -> ⚠ Yfir 30% | AJ36: =IF($A36<>"",$A36,AJ35) -> 46259
B37: Þriðjudagur | C37: 35 | D37: Leikskóli | E37: Sérfæði | F37: Hrísgrjónabrauð - Glútenlaust | G37: Hrísgrjónabrauð | H37: 25 | J37: =IF($F37="","",IFERROR(IFERROR(INDEX(Réttabanki!$U:$U,MATCH($F37,Réttabanki!$A:$A,0)),INDEX(Vöruskrá!$R:$R,MATCH($F37,Vöruskrá!$B:$B,0)))*($H37+IF($I37="",$H37*(1+$AD$2),$I37))/2/1000,"")) -> 18.75 | K37: Hrísmjöl, vatn, hirsi, krydd, súrdeig, salt | N37: 218 | O37: 1.2 | P37: 0.2 | Q37: 45.9 | R37: 5.6 | S37: 1 | AF37: =IF($F37="","",IFERROR(IFERROR(INDEX(Réttabanki!$U:$U,MATCH($F37,Réttabanki!$A:$A,0)),INDEX(Vöruskrá!$R:$R,MATCH($F37,Vöruskrá!$B:$B,0)))*$H37/1000,"")) -> 15 | AG37: =IF($F37="","",IFERROR(IFERROR(INDEX(Réttabanki!$U:$U,MATCH($F37,Réttabanki!$A:$A,0)),INDEX(Vöruskrá!$R:$R,MATCH($F37,Vöruskrá!$B:$B,0)))*IF($I37="",$H37*(1+$AD$2),$I37)/1000,"")) -> 22.5 | AH37: =IF(N($AF37)+N($AG37)=0,"",MAX(N($AF37)/$AE$6,N($AG37)/$AE$5)) -> 0.019565217 | AI37: =IF($AH37="","",IF($AH37>$AE$7,"⚠ Yfir "&TEXT($AE$7,"0%"),"OK")) -> OK | AJ37: =IF($A37<>"",$A37,AJ36) -> 46259
B38: Þriðjudagur | C38: 35 | D38: Leikskóli | E38: Sérfæði | G38: Plokkfiskur (Mjólkurlaust), rúgbrauð | J38: =IF($F38="","",IFERROR(IFERROR(INDEX(Réttabanki!$U:$U,MATCH($F38,Réttabanki!$A:$A,0)),INDEX(Vöruskrá!$R:$R,MATCH($F38,Vöruskrá!$B:$B,0)))*($H38+IF($I38="",$H38*(1+$AD$2),$I38))/2/1000,"")) | K38: Ýsa | Kartöflur | Laukur | Repjuolía | Vatn (64%), jurtaolía (29%) (pálmakjarni, pálmi), þurrkað glúkósasíróp (5%), umbreytt sterkja, salt, bindiefni (E339, gellangúmmí), ýruefni (lesitín, E435, E472b), litarefni (karótín), náttúruleg bragðefni. | Vatn | Maíssterkja. | Salt (salt, kekkjavarnarefni E535, lyftiefni E500). | Þurrkað vín, edik | Sykur, sykurreyrssíróp. | Múskat 100% (Myristica fragrans), hitaþurrkað. | Túrmerik, dillfræ, fenugreek (grikkjasmári), kóríander, cayennepipar, svartur pipar, negull. | Svartur pipar 100% (Piper nigrum), hitaþurrkað. | L38: Fiskur, Súlfít, Engir | T38: 2 | U38: Kælt | V38: Ofn | W38: 140 | X38: 20-25 | Y38: 75 | Z38: Hræra 1 sinni | AF38: =IF($F38="","",IFERROR(IFERROR(INDEX(Réttabanki!$U:$U,MATCH($F38,Réttabanki!$A:$A,0)),INDEX(Vöruskrá!$R:$R,MATCH($F38,Vöruskrá!$B:$B,0)))*$H38/1000,"")) | AG38: =IF($F38="","",IFERROR(IFERROR(INDEX(Réttabanki!$U:$U,MATCH($F38,Réttabanki!$A:$A,0)),INDEX(Vöruskrá!$R:$R,MATCH($F38,Vöruskrá!$B:$B,0)))*IF($I38="",$H38*(1+$AD$2),$I38)/1000,"")) | AH38: =IF(N($AF38)+N($AG38)=0,"",MAX(N($AF38)/$AE$6,N($AG38)/$AE$5)) | AI38: =IF($AH38="","",IF($AH38>$AE$7,"⚠ Yfir "&TEXT($AE$7,"0%"),"OK")) | AJ38: =IF($A38<>"",$A38,AJ37) -> 46259
B39: Þriðjudagur | C39: 35 | D39: Leikskóli | E39: Sérfæði | F39: Plokkfiskur - Mjólkurlaus | G39: Plokkfiskur (Mjólkurlaust) | H39: 200 | J39: =IF($F39="","",IFERROR(IFERROR(INDEX(Réttabanki!$U:$U,MATCH($F39,Réttabanki!$A:$A,0)),INDEX(Vöruskrá!$R:$R,MATCH($F39,Vöruskrá!$B:$B,0)))*($H39+IF($I39="",$H39*(1+$AD$2),$I39))/2/1000,"")) | K39: Ýsa | Kartöflur | Laukur | Repjuolía | Vatn (64%), jurtaolía (29%) (pálmakjarni, pálmi), þurrkað glúkósasíróp (5%), umbreytt sterkja, salt, bindiefni (E339, gellangúmmí), ýruefni (lesitín, E435, E472b), litarefni (karótín), náttúruleg bragðefni. | Vatn | Maíssterkja. | Salt (salt, kekkjavarnarefni E535, lyftiefni E500). | Þurrkað vín, edik | Sykur, sykurreyrssíróp. | Múskat 100% (Myristica fragrans), hitaþurrkað. | Túrmerik, dillfræ, fenugreek (grikkjasmári), kóríander, cayennepipar, svartur pipar, negull. | Svartur pipar 100% (Piper nigrum), hitaþurrkað. | L39: Fiskur, Súlfít, Engir | N39: 115.06 | O39: 4.18 | P39: 2.62 | Q39: 9.64 | R39: 10.05 | S39: 0.68 | AF39: =IF($F39="","",IFERROR(IFERROR(INDEX(Réttabanki!$U:$U,MATCH($F39,Réttabanki!$A:$A,0)),INDEX(Vöruskrá!$R:$R,MATCH($F39,Vöruskrá!$B:$B,0)))*$H39/1000,"")) | AG39: =IF($F39="","",IFERROR(IFERROR(INDEX(Réttabanki!$U:$U,MATCH($F39,Réttabanki!$A:$A,0)),INDEX(Vöruskrá!$R:$R,MATCH($F39,Vöruskrá!$B:$B,0)))*IF($I39="",$H39*(1+$AD$2),$I39)/1000,"")) | AH39: =IF(N($AF39)+N($AG39)=0,"",MAX(N($AF39)/$AE$6,N($AG39)/$AE$5)) | AI39: =IF($AH39="","",IF($AH39>$AE$7,"⚠ Yfir "&TEXT($AE$7,"0%"),"OK")) | AJ39: =IF($A39<>"",$A39,AJ38) -> 46259
B40: Þriðjudagur | C40: 35 | D40: Leikskóli | E40: Sérfæði | G40: Kjúklingaplokkari (Fisklaust) | J40: =IF($F40="","",IFERROR(IFERROR(INDEX(Réttabanki!$U:$U,MATCH($F40,Réttabanki!$A:$A,0)),INDEX(Vöruskrá!$R:$R,MATCH($F40,Vöruskrá!$B:$B,0)))*($H40+IF($I40="",$H40*(1+$AD$2),$I40))/2/1000,"")) | K40: Kjúklingur (kjúklingainnifilé, vatn, salt, bindiefni E407, maltódextrín, dextrósi), kartöflur, vegan rjómi (vatn, pálmakjarnaolía, pálmaolía, þurrkað glúkósasíróp, umbreytt sterkja, salt, þykkingarefni E339, gellangúmmí, ýruefni lesitín, E435, E472b, litarefni karótín, náttúrulegt bragðefni), vatn, laukur, repjuolía, maíssterkja, hvítvínsedik, púðursykur, borðsalt, karrýduft, múskat, piparblanda, svartur pipar | L40: Engir skráðir | AF40: =IF($F40="","",IFERROR(IFERROR(INDEX(Réttabanki!$U:$U,MATCH($F40,Réttabanki!$A:$A,0)),INDEX(Vöruskrá!$R:$R,MATCH($F40,Vöruskrá!$B:$B,0)))*$H40/1000,"")) | AG40: =IF($F40="","",IFERROR(IFERROR(INDEX(Réttabanki!$U:$U,MATCH($F40,Réttabanki!$A:$A,0)),INDEX(Vöruskrá!$R:$R,MATCH($F40,Vöruskrá!$B:$B,0)))*IF($I40="",$H40*(1+$AD$2),$I40)/1000,"")) | AH40: =IF(N($AF40)+N($AG40)=0,"",MAX(N($AF40)/$AE$6,N($AG40)/$AE$5)) | AI40: =IF($AH40="","",IF($AH40>$AE$7,"⚠ Yfir "&TEXT($AE$7,"0%"),"OK")) | AJ40: =IF($A40<>"",$A40,AJ39) -> 46259
B41: Þriðjudagur | C41: 35 | D41: Leikskóli | E41: Sérfæði | F41: Kjúklingaplokkari | G41: Kjúklingaplokkari (Fisklaust) | H41: 200 | J41: =IF($F41="","",IFERROR(IFERROR(INDEX(Réttabanki!$U:$U,MATCH($F41,Réttabanki!$A:$A,0)),INDEX(Vöruskrá!$R:$R,MATCH($F41,Vöruskrá!$B:$B,0)))*($H41+IF($I41="",$H41*(1+$AD$2),$I41))/2/1000,"")) -> 300 | K41: Kjúklingur (kjúklingainnifilé, vatn, salt, bindiefni E407, maltódextrín, dextrósi), kartöflur, vegan rjómi (vatn, pálmakjarnaolía, pálmaolía, þurrkað glúkósasíróp, umbreytt sterkja, salt, þykkingarefni E339, gellangúmmí, ýruefni lesitín, E435, E472b, litarefni karótín, náttúrulegt bragðefni), vatn, laukur, repjuolía, maíssterkja, hvítvínsedik, púðursykur, borðsalt, karrýduft, múskat, piparblanda, svartur pipar | N41: 105 | O41: 5.1 | P41: 3.3 | Q41: 7.8 | R41: 6.9 | S41: 0.6 | T41: 1 | U41: Kælt | V41: Ofn | W41: 160 | X41: 20-25 | Y41: 75 | Z41: Hræra 1 sinni | AF41: =IF($F41="","",IFERROR(IFERROR(INDEX(Réttabanki!$U:$U,MATCH($F41,Réttabanki!$A:$A,0)),INDEX(Vöruskrá!$R:$R,MATCH($F41,Vöruskrá!$B:$B,0)))*$H41/1000,"")) -> 240 | AG41: =IF($F41="","",IFERROR(IFERROR(INDEX(Réttabanki!$U:$U,MATCH($F41,Réttabanki!$A:$A,0)),INDEX(Vöruskrá!$R:$R,MATCH($F41,Vöruskrá!$B:$B,0)))*IF($I41="",$H41*(1+$AD$2),$I41)/1000,"")) -> 360 | AH41: =IF(N($AF41)+N($AG41)=0,"",MAX(N($AF41)/$AE$6,N($AG41)/$AE$5)) -> 0.31304348 | AI41: =IF($AH41="","",IF($AH41>$AE$7,"⚠ Yfir "&TEXT($AE$7,"0%"),"OK")) -> ⚠ Yfir 30% | AJ41: =IF($A41<>"",$A41,AJ40) -> 46259
B42: Þriðjudagur | C42: 35 | D42: Grunnskólar starfsmenn | E42: Meðlætisbar | J42: =IF($F42="","",IFERROR(IFERROR(INDEX(Réttabanki!$U:$U,MATCH($F42,Réttabanki!$A:$A,0)),INDEX(Vöruskrá!$R:$R,MATCH($F42,Vöruskrá!$B:$B,0)))*($H42+IF($I42="",$H42*(1+$AD$2),$I42))/2/1000,"")) | L42: Engir skráðir | M42: =IF($F42="","",IFERROR(IFERROR(INDEX(Réttabanki!$F:$F,MATCH($F42,Réttabanki!$A:$A,0)),INDEX(Vöruskrá!$H:$H,MATCH($F42,Vöruskrá!$B:$B,0))),"")) | N42: =IF($F42="","",IFERROR(IFERROR(INDEX(Réttabanki!$G:$G,MATCH($F42,Réttabanki!$A:$A,0)),INDEX(Vöruskrá!$J:$J,MATCH($F42,Vöruskrá!$B:$B,0)))*($H42+IF($I42="",$H42*(1+$AD$2),$I42))/2/100,"")) | O42: =IF($F42="","",IFERROR(IFERROR(INDEX(Réttabanki!$H:$H,MATCH($F42,Réttabanki!$A:$A,0)),INDEX(Vöruskrá!$K:$K,MATCH($F42,Vöruskrá!$B:$B,0)))*($H42+IF($I42="",$H42*(1+$AD$2),$I42))/2/100,"")) | P42: =IF($F42="","",IFERROR(IFERROR(INDEX(Réttabanki!$I:$I,MATCH($F42,Réttabanki!$A:$A,0)),INDEX(Vöruskrá!$L:$L,MATCH($F42,Vöruskrá!$B:$B,0)))*($H42+IF($I42="",$H42*(1+$AD$2),$I42))/2/100,"")) | Q42: =IF($F42="","",IFERROR(IFERROR(INDEX(Réttabanki!$J:$J,MATCH($F42,Réttabanki!$A:$A,0)),INDEX(Vöruskrá!$M:$M,MATCH($F42,Vöruskrá!$B:$B,0)))*($H42+IF($I42="",$H42*(1+$AD$2),$I42))/2/100,"")) | R42: =IF($F42="","",IFERROR(IFERROR(INDEX(Réttabanki!$L:$L,MATCH($F42,Réttabanki!$A:$A,0)),INDEX(Vöruskrá!$O:$O,MATCH($F42,Vöruskrá!$B:$B,0)))*($H42+IF($I42="",$H42*(1+$AD$2),$I42))/2/100,"")) | S42: =IF($F42="","",IFERROR(IFERROR(INDEX(Réttabanki!$M:$M,MATCH($F42,Réttabanki!$A:$A,0)),INDEX(Vöruskrá!$P:$P,MATCH($F42,Vöruskrá!$B:$B,0)))*($H42+IF($I42="",$H42*(1+$AD$2),$I42))/2/100,"")) | T42: =IF(F42="","",IFERROR(INDEX(Réttabanki!Q:Q,MATCH(F42,Réttabanki!A:A,0)),IFERROR(INDEX(Réttabanki!Q:Q,MATCH(F42,Réttabanki!B:B,0)),""))) | AF42: =IF($F42="","",IFERROR(IFERROR(INDEX(Réttabanki!$U:$U,MATCH($F42,Réttabanki!$A:$A,0)),INDEX(Vöruskrá!$R:$R,MATCH($F42,Vöruskrá!$B:$B,0)))*$H42/1000,"")) | AG42: =IF($F42="","",IFERROR(IFERROR(INDEX(Réttabanki!$U:$U,MATCH($F42,Réttabanki!$A:$A,0)),INDEX(Vöruskrá!$R:$R,MATCH($F42,Vöruskrá!$B:$B,0)))*IF($I42="",$H42*(1+$AD$2),$I42)/1000,"")) | AH42: =IF(N($AF42)+N($AG42)=0,"",MAX(N($AF42)/$AE$6,N($AG42)/$AE$5)) | AI42: =IF($AH42="","",IF($AH42>$AE$7,"⚠ Yfir "&TEXT($AE$7,"0%"),"OK")) | AJ42: =IF($A42<>"",$A42,AJ41) -> 46259
B43: Þriðjudagur | C43: 35 | D43: Leikskóli | E43: Meðlætisbar | G43: Paprika, ávextir | J43: =IF($F43="","",IFERROR(IFERROR(INDEX(Réttabanki!$U:$U,MATCH($F43,Réttabanki!$A:$A,0)),INDEX(Vöruskrá!$R:$R,MATCH($F43,Vöruskrá!$B:$B,0)))*($H43+IF($I43="",$H43*(1+$AD$2),$I43))/2/1000,"")) | L43: Engir skráðir | M43: =IF($F43="","",IFERROR(IFERROR(INDEX(Réttabanki!$F:$F,MATCH($F43,Réttabanki!$A:$A,0)),INDEX(Vöruskrá!$H:$H,MATCH($F43,Vöruskrá!$B:$B,0))),"")) | N43: =IF($F43="","",IFERROR(IFERROR(INDEX(Réttabanki!$G:$G,MATCH($F43,Réttabanki!$A:$A,0)),INDEX(Vöruskrá!$J:$J,MATCH($F43,Vöruskrá!$B:$B,0)))*($H43+IF($I43="",$H43*(1+$AD$2),$I43))/2/100,"")) | O43: =IF($F43="","",IFERROR(IFERROR(INDEX(Réttabanki!$H:$H,MATCH($F43,Réttabanki!$A:$A,0)),INDEX(Vöruskrá!$K:$K,MATCH($F43,Vöruskrá!$B:$B,0)))*($H43+IF($I43="",$H43*(1+$AD$2),$I43))/2/100,"")) | P43: =IF($F43="","",IFERROR(IFERROR(INDEX(Réttabanki!$I:$I,MATCH($F43,Réttabanki!$A:$A,0)),INDEX(Vöruskrá!$L:$L,MATCH($F43,Vöruskrá!$B:$B,0)))*($H43+IF($I43="",$H43*(1+$AD$2),$I43))/2/100,"")) | Q43: =IF($F43="","",IFERROR(IFERROR(INDEX(Réttabanki!$J:$J,MATCH($F43,Réttabanki!$A:$A,0)),INDEX(Vöruskrá!$M:$M,MATCH($F43,Vöruskrá!$B:$B,0)))*($H43+IF($I43="",$H43*(1+$AD$2),$I43))/2/100,"")) | R43: =IF($F43="","",IFERROR(IFERROR(INDEX(Réttabanki!$L:$L,MATCH($F43,Réttabanki!$A:$A,0)),INDEX(Vöruskrá!$O:$O,MATCH($F43,Vöruskrá!$B:$B,0)))*($H43+IF($I43="",$H43*(1+$AD$2),$I43))/2/100,"")) | S43: =IF($F43="","",IFERROR(IFERROR(INDEX(Réttabanki!$M:$M,MATCH($F43,Réttabanki!$A:$A,0)),INDEX(Vöruskrá!$P:$P,MATCH($F43,Vöruskrá!$B:$B,0)))*($H43+IF($I43="",$H43*(1+$AD$2),$I43))/2/100,"")) | T43: =IF(F43="","",IFERROR(INDEX(Réttabanki!Q:Q,MATCH(F43,Réttabanki!A:A,0)),IFERROR(INDEX(Réttabanki!Q:Q,MATCH(F43,Réttabanki!B:B,0)),""))) | AF43: =IF($F43="","",IFERROR(IFERROR(INDEX(Réttabanki!$U:$U,MATCH($F43,Réttabanki!$A:$A,0)),INDEX(Vöruskrá!$R:$R,MATCH($F43,Vöruskrá!$B:$B,0)))*$H43/1000,"")) | AG43: =IF($F43="","",IFERROR(IFERROR(INDEX(Réttabanki!$U:$U,MATCH($F43,Réttabanki!$A:$A,0)),INDEX(Vöruskrá!$R:$R,MATCH($F43,Vöruskrá!$B:$B,0)))*IF($I43="",$H43*(1+$AD$2),$I43)/1000,"")) | AH43: =IF(N($AF43)+N($AG43)=0,"",MAX(N($AF43)/$AE$6,N($AG43)/$AE$5)) | AI43: =IF($AH43="","",IF($AH43>$AE$7,"⚠ Yfir "&TEXT($AE$7,"0%"),"OK")) | AJ43: =IF($A43<>"",$A43,AJ42) -> 46259
B44: Þriðjudagur | C44: 35 | D44: Leikskóli | E44: Síðdegishressing | G44: Dökkt súrdeigsbrauð, lifrarkæfa, paprika, ávextir | J44: =IF($F44="","",IFERROR(IFERROR(INDEX(Réttabanki!$U:$U,MATCH($F44,Réttabanki!$A:$A,0)),INDEX(Vöruskrá!$R:$R,MATCH($F44,Vöruskrá!$B:$B,0)))*($H44+IF($I44="",$H44*(1+$AD$2),$I44))/2/1000,"")) | K44: Vatn, **hveitimjöl**, **hafraflögur**, súrdeig úr **hveiti**, síróp,**hveitiglúten**, **heilkornahveitimjöl**, **heilkornsrúgmjöl**, sólblómafræ (2%), skáldað **heilkornshaframjöl**, **hveitiklíð**, repjuolía, malt úr **rúgi** og **byggi**, ger, salt, mjölmeðhöndlunarefni (askorbínsýra). | Grísalifur og kjöt 80%, vatn, laukur, salt, kartöflumjöl, **soja**prótein, krydd, vatnsrofið jurtaprótein, repjuolía, maísprótein, jurtafita (pálma), þrúgusykur, rotvarnarefni (E250), þráavarnarefni (E315, E316, E330), bindiefni (E450, E451) | L44: Glúten (hveiti, hafrar, rúgur, bygg), Soja | M44: =IF($F44="","",IFERROR(IFERROR(INDEX(Réttabanki!$F:$F,MATCH($F44,Réttabanki!$A:$A,0)),INDEX(Vöruskrá!$H:$H,MATCH($F44,Vöruskrá!$B:$B,0))),"")) | N44: =IF($F44="","",IFERROR(IFERROR(INDEX(Réttabanki!$G:$G,MATCH($F44,Réttabanki!$A:$A,0)),INDEX(Vöruskrá!$J:$J,MATCH($F44,Vöruskrá!$B:$B,0)))*($H44+IF($I44="",$H44*(1+$AD$2),$I44))/2/100,"")) | O44: =IF($F44="","",IFERROR(IFERROR(INDEX(Réttabanki!$H:$H,MATCH($F44,Réttabanki!$A:$A,0)),INDEX(Vöruskrá!$K:$K,MATCH($F44,Vöruskrá!$B:$B,0)))*($H44+IF($I44="",$H44*(1+$AD$2),$I44))/2/100,"")) | P44: =IF($F44="","",IFERROR(IFERROR(INDEX(Réttabanki!$I:$I,MATCH($F44,Réttabanki!$A:$A,0)),INDEX(Vöruskrá!$L:$L,MATCH($F44,Vöruskrá!$B:$B,0)))*($H44+IF($I44="",$H44*(1+$AD$2),$I44))/2/100,"")) | Q44: =IF($F44="","",IFERROR(IFERROR(INDEX(Réttabanki!$J:$J,MATCH($F44,Réttabanki!$A:$A,0)),INDEX(Vöruskrá!$M:$M,MATCH($F44,Vöruskrá!$B:$B,0)))*($H44+IF($I44="",$H44*(1+$AD$2),$I44))/2/100,"")) | R44: =IF($F44="","",IFERROR(IFERROR(INDEX(Réttabanki!$L:$L,MATCH($F44,Réttabanki!$A:$A,0)),INDEX(Vöruskrá!$O:$O,MATCH($F44,Vöruskrá!$B:$B,0)))*($H44+IF($I44="",$H44*(1+$AD$2),$I44))/2/100,"")) | S44: =IF($F44="","",IFERROR(IFERROR(INDEX(Réttabanki!$M:$M,MATCH($F44,Réttabanki!$A:$A,0)),INDEX(Vöruskrá!$P:$P,MATCH($F44,Vöruskrá!$B:$B,0)))*($H44+IF($I44="",$H44*(1+$AD$2),$I44))/2/100,"")) | T44: =IF(F44="","",IFERROR(INDEX(Réttabanki!Q:Q,MATCH(F44,Réttabanki!A:A,0)),IFERROR(INDEX(Réttabanki!Q:Q,MATCH(F44,Réttabanki!B:B,0)),""))) | AF44: =IF($F44="","",IFERROR(IFERROR(INDEX(Réttabanki!$U:$U,MATCH($F44,Réttabanki!$A:$A,0)),INDEX(Vöruskrá!$R:$R,MATCH($F44,Vöruskrá!$B:$B,0)))*$H44/1000,"")) | AG44: =IF($F44="","",IFERROR(IFERROR(INDEX(Réttabanki!$U:$U,MATCH($F44,Réttabanki!$A:$A,0)),INDEX(Vöruskrá!$R:$R,MATCH($F44,Vöruskrá!$B:$B,0)))*IF($I44="",$H44*(1+$AD$2),$I44)/1000,"")) | AH44: =IF(N($AF44)+N($AG44)=0,"",MAX(N($AF44)/$AE$6,N($AG44)/$AE$5)) | AI44: =IF($AH44="","",IF($AH44>$AE$7,"⚠ Yfir "&TEXT($AE$7,"0%"),"OK")) | AJ44: =IF($A44<>"",$A44,AJ43) -> 46259
B45: Þriðjudagur | C45: 35 | D45: Leikskóli | E45: Síðdegishressing | F45: Pågen grautabrauð dökkt | G45: Dökkt súrdeigsbrauð | H45: 40 | J45: =IF($F45="","",IFERROR(IFERROR(INDEX(Réttabanki!$U:$U,MATCH($F45,Réttabanki!$A:$A,0)),INDEX(Vöruskrá!$R:$R,MATCH($F45,Vöruskrá!$B:$B,0)))*($H45+IF($I45="",$H45*(1+$AD$2),$I45))/2/1000,"")) -> 35 | K45: Vatn, **hveitimjöl**, **hafraflögur**, súrdeig úr **hveiti**, síróp,**hveitiglúten**, **heilkornahveitimjöl**, **heilkornsrúgmjöl**, sólblómafræ (2%), skáldað **heilkornshaframjöl**, **hveitiklíð**, repjuolía, malt úr **rúgi** og **byggi**, ger, salt, mjölmeðhöndlunarefni (askorbínsýra). | L45: Glúten (hveiti, hafrar, rúgur, bygg) | N45: 266 | O45: 4.7 | P45: 0.6 | Q45: 42 | R45: 11 | S45: 1 | T45: =IF(F45="","",IFERROR(INDEX(Réttabanki!Q:Q,MATCH(F45,Réttabanki!A:A,0)),IFERROR(INDEX(Réttabanki!Q:Q,MATCH(F45,Réttabanki!B:B,0)),""))) | AF45: =IF($F45="","",IFERROR(IFERROR(INDEX(Réttabanki!$U:$U,MATCH($F45,Réttabanki!$A:$A,0)),INDEX(Vöruskrá!$R:$R,MATCH($F45,Vöruskrá!$B:$B,0)))*$H45/1000,"")) -> 28 | AG45: =IF($F45="","",IFERROR(IFERROR(INDEX(Réttabanki!$U:$U,MATCH($F45,Réttabanki!$A:$A,0)),INDEX(Vöruskrá!$R:$R,MATCH($F45,Vöruskrá!$B:$B,0)))*IF($I45="",$H45*(1+$AD$2),$I45)/1000,"")) -> 42 | AH45: =IF(N($AF45)+N($AG45)=0,"",MAX(N($AF45)/$AE$6,N($AG45)/$AE$5)) -> 0.036521739 | AI45: =IF($AH45="","",IF($AH45>$AE$7,"⚠ Yfir "&TEXT($AE$7,"0%"),"OK")) -> OK | AJ45: =IF($A45<>"",$A45,AJ44) -> 46259
B46: Þriðjudagur | C46: 35 | D46: Leikskóli | E46: Síðdegishressing | F46: Dönsk lifrarkæfa | G46: Lifrarkæfa | H46: 20 | J46: =IF($F46="","",IFERROR(IFERROR(INDEX(Réttabanki!$U:$U,MATCH($F46,Réttabanki!$A:$A,0)),INDEX(Vöruskrá!$R:$R,MATCH($F46,Vöruskrá!$B:$B,0)))*($H46+IF($I46="",$H46*(1+$AD$2),$I46))/2/1000,"")) -> 45 | K46: Grísalifur og kjöt 80%, vatn, laukur, salt, kartöflumjöl, **soja**prótein, krydd, vatnsrofið jurtaprótein, repjuolía, maísprótein, jurtafita (pálma), þrúgusykur, rotvarnarefni (E250), þráavarnarefni (E315, E316, E330), bindiefni (E450, E451) | L46: Soja | N46: 384 | O46: 29.3 | P46: 14.7 | Q46: 2.4 | R46: 12.8 | S46: 1.7 | T46: =IF(F46="","",IFERROR(INDEX(Réttabanki!Q:Q,MATCH(F46,Réttabanki!A:A,0)),IFERROR(INDEX(Réttabanki!Q:Q,MATCH(F46,Réttabanki!B:B,0)),""))) | AF46: =IF($F46="","",IFERROR(IFERROR(INDEX(Réttabanki!$U:$U,MATCH($F46,Réttabanki!$A:$A,0)),INDEX(Vöruskrá!$R:$R,MATCH($F46,Vöruskrá!$B:$B,0)))*$H46/1000,"")) -> 36 | AG46: =IF($F46="","",IFERROR(IFERROR(INDEX(Réttabanki!$U:$U,MATCH($F46,Réttabanki!$A:$A,0)),INDEX(Vöruskrá!$R:$R,MATCH($F46,Vöruskrá!$B:$B,0)))*IF($I46="",$H46*(1+$AD$2),$I46)/1000,"")) -> 54 | AH46: =IF(N($AF46)+N($AG46)=0,"",MAX(N($AF46)/$AE$6,N($AG46)/$AE$5)) -> 0.046956522 | AI46: =IF($AH46="","",IF($AH46>$AE$7,"⚠ Yfir "&TEXT($AE$7,"0%"),"OK")) -> OK | AJ46: =IF($A46<>"",$A46,AJ45) -> 46259
B47: Þriðjudagur | C47: 35 | D47: Leikskóli | E47: Sérfæði | G47: Dökkt súrdeigsbrauð, paprika, ávextir | J47: =IF($F47="","",IFERROR(IFERROR(INDEX(Réttabanki!$U:$U,MATCH($F47,Réttabanki!$A:$A,0)),INDEX(Vöruskrá!$R:$R,MATCH($F47,Vöruskrá!$B:$B,0)))*($H47+IF($I47="",$H47*(1+$AD$2),$I47))/2/1000,"")) | K47: Vatn, **hveiti**mjöl, súrdeig úr **hveiti**korni (13%), heilkorna**hveiti**mjöl, dinkel**hveiti**mjöl, muldir heilkornakjarnar úr dinkel**hveiti**, **hafra**grjón, skolað heilkorna**hafra**mjöl, **hveiti**glúten, heilkorna**rúg**mjöl, heilkorna durum**hveiti**mjöl, **hafra**trefjar, kaldpressuð repjuolía (1%), **hveiti**kímar, gul hörfræ, sykur (eingöngu sem næring fyrir ger), ger, malt úr **byggi** og **hveiti**, salt. | L47: Glúten (hveiti, rúgur, hafrar, bygg) | M47: =IF($F47="","",IFERROR(IFERROR(INDEX(Réttabanki!$F:$F,MATCH($F47,Réttabanki!$A:$A,0)),INDEX(Vöruskrá!$H:$H,MATCH($F47,Vöruskrá!$B:$B,0))),"")) | N47: =IF($F47="","",IFERROR(IFERROR(INDEX(Réttabanki!$G:$G,MATCH($F47,Réttabanki!$A:$A,0)),INDEX(Vöruskrá!$J:$J,MATCH($F47,Vöruskrá!$B:$B,0)))*($H47+IF($I47="",$H47*(1+$AD$2),$I47))/2/100,"")) | O47: =IF($F47="","",IFERROR(IFERROR(INDEX(Réttabanki!$H:$H,MATCH($F47,Réttabanki!$A:$A,0)),INDEX(Vöruskrá!$K:$K,MATCH($F47,Vöruskrá!$B:$B,0)))*($H47+IF($I47="",$H47*(1+$AD$2),$I47))/2/100,"")) | P47: =IF($F47="","",IFERROR(IFERROR(INDEX(Réttabanki!$I:$I,MATCH($F47,Réttabanki!$A:$A,0)),INDEX(Vöruskrá!$L:$L,MATCH($F47,Vöruskrá!$B:$B,0)))*($H47+IF($I47="",$H47*(1+$AD$2),$I47))/2/100,"")) | Q47: =IF($F47="","",IFERROR(IFERROR(INDEX(Réttabanki!$J:$J,MATCH($F47,Réttabanki!$A:$A,0)),INDEX(Vöruskrá!$M:$M,MATCH($F47,Vöruskrá!$B:$B,0)))*($H47+IF($I47="",$H47*(1+$AD$2),$I47))/2/100,"")) | R47: =IF($F47="","",IFERROR(IFERROR(INDEX(Réttabanki!$L:$L,MATCH($F47,Réttabanki!$A:$A,0)),INDEX(Vöruskrá!$O:$O,MATCH($F47,Vöruskrá!$B:$B,0)))*($H47+IF($I47="",$H47*(1+$AD$2),$I47))/2/100,"")) | S47: =IF($F47="","",IFERROR(IFERROR(INDEX(Réttabanki!$M:$M,MATCH($F47,Réttabanki!$A:$A,0)),INDEX(Vöruskrá!$P:$P,MATCH($F47,Vöruskrá!$B:$B,0)))*($H47+IF($I47="",$H47*(1+$AD$2),$I47))/2/100,"")) | T47: =IF(F47="","",IFERROR(INDEX(Réttabanki!Q:Q,MATCH(F47,Réttabanki!A:A,0)),IFERROR(INDEX(Réttabanki!Q:Q,MATCH(F47,Réttabanki!B:B,0)),""))) | AF47: =IF($F47="","",IFERROR(IFERROR(INDEX(Réttabanki!$U:$U,MATCH($F47,Réttabanki!$A:$A,0)),INDEX(Vöruskrá!$R:$R,MATCH($F47,Vöruskrá!$B:$B,0)))*$H47/1000,"")) | AG47: =IF($F47="","",IFERROR(IFERROR(INDEX(Réttabanki!$U:$U,MATCH($F47,Réttabanki!$A:$A,0)),INDEX(Vöruskrá!$R:$R,MATCH($F47,Vöruskrá!$B:$B,0)))*IF($I47="",$H47*(1+$AD$2),$I47)/1000,"")) | AH47: =IF(N($AF47)+N($AG47)=0,"",MAX(N($AF47)/$AE$6,N($AG47)/$AE$5)) | AI47: =IF($AH47="","",IF($AH47>$AE$7,"⚠ Yfir "&TEXT($AE$7,"0%"),"OK")) | AJ47: =IF($A47<>"",$A47,AJ46) -> 46259
B48: Þriðjudagur | C48: 35 | D48: Leikskóli | E48: Sérfæði | F48: Dökkt súrdeigsbrauð (Skanörgrova) | G48: Dökkt súrdeigsbrauð | H48: 40 | J48: =IF($F48="","",IFERROR(IFERROR(INDEX(Réttabanki!$U:$U,MATCH($F48,Réttabanki!$A:$A,0)),INDEX(Vöruskrá!$R:$R,MATCH($F48,Vöruskrá!$B:$B,0)))*($H48+IF($I48="",$H48*(1+$AD$2),$I48))/2/1000,"")) -> 30 | K48: Vatn, **hveiti**mjöl, súrdeig úr **hveiti**korni (13%), heilkorna**hveiti**mjöl, dinkel**hveiti**mjöl, muldir heilkornakjarnar úr dinkel**hveiti**, **hafra**grjón, skolað heilkorna**hafra**mjöl, **hveiti**glúten, heilkorna**rúg**mjöl, heilkorna durum**hveiti**mjöl, **hafra**trefjar, kaldpressuð repjuolía (1%), **hveiti**kímar, gul hörfræ, sykur (eingöngu sem næring fyrir ger), ger, malt úr **byggi** og **hveiti**, salt. | L48: Glúten (hveiti, rúgur, hafrar, bygg) | N48: 308 | O48: 7.8 | P48: 0.8 | Q48: 48 | R48: 10 | S48: 1.4 | T48: =IF(F48="","",IFERROR(INDEX(Réttabanki!Q:Q,MATCH(F48,Réttabanki!A:A,0)),IFERROR(INDEX(Réttabanki!Q:Q,MATCH(F48,Réttabanki!B:B,0)),""))) | AF48: =IF($F48="","",IFERROR(IFERROR(INDEX(Réttabanki!$U:$U,MATCH($F48,Réttabanki!$A:$A,0)),INDEX(Vöruskrá!$R:$R,MATCH($F48,Vöruskrá!$B:$B,0)))*$H48/1000,"")) -> 24 | AG48: =IF($F48="","",IFERROR(IFERROR(INDEX(Réttabanki!$U:$U,MATCH($F48,Réttabanki!$A:$A,0)),INDEX(Vöruskrá!$R:$R,MATCH($F48,Vöruskrá!$B:$B,0)))*IF($I48="",$H48*(1+$AD$2),$I48)/1000,"")) -> 36 | AH48: =IF(N($AF48)+N($AG48)=0,"",MAX(N($AF48)/$AE$6,N($AG48)/$AE$5)) -> 0.031304348 | AI48: =IF($AH48="","",IF($AH48>$AE$7,"⚠ Yfir "&TEXT($AE$7,"0%"),"OK")) -> OK | AJ48: =IF($A48<>"",$A48,AJ47) -> 46259
B49: Þriðjudagur | C49: 35 | D49: Leikskóli | E49: Sérfæði | G49: Glútenlaust dökkt brauð, lifrarkæfa, paprika, ávextir | J49: =IF($F49="","",IFERROR(IFERROR(INDEX(Réttabanki!$U:$U,MATCH($F49,Réttabanki!$A:$A,0)),INDEX(Vöruskrá!$R:$R,MATCH($F49,Vöruskrá!$B:$B,0)))*($H49+IF($I49="",$H49*(1+$AD$2),$I49))/2/1000,"")) | K49: Vatn, tapíókamjöl, hrísgrjónamjöl, þykkingarefni: sellulósi, hýdroxýprópýl metýl sellulósi, karboxýmetýl sellulósi, metýl sellulósi, xantangúmmí; heilkorna maís, kartöflusterkja, ger, psyllium hýðisduft, rakaefni; glýseról; repjuolía, hrísgrjónasterkja, síróp, maíssterkja, salt, rotvarnarefni: natríumprópíónat, sorbínsýra, brenndur sykur, vínedik. | Grísalifur og kjöt 80%, vatn, laukur, salt, kartöflumjöl, **soja**prótein, krydd, vatnsrofið jurtaprótein, repjuolía, maísprótein, jurtafita (pálma), þrúgusykur, rotvarnarefni (E250), þráavarnarefni (E315, E316, E330), bindiefni (E450, E451) | L49: Soja | AF49: =IF($F49="","",IFERROR(IFERROR(INDEX(Réttabanki!$U:$U,MATCH($F49,Réttabanki!$A:$A,0)),INDEX(Vöruskrá!$R:$R,MATCH($F49,Vöruskrá!$B:$B,0)))*$H49/1000,"")) | AG49: =IF($F49="","",IFERROR(IFERROR(INDEX(Réttabanki!$U:$U,MATCH($F49,Réttabanki!$A:$A,0)),INDEX(Vöruskrá!$R:$R,MATCH($F49,Vöruskrá!$B:$B,0)))*IF($I49="",$H49*(1+$AD$2),$I49)/1000,"")) | AH49: =IF(N($AF49)+N($AG49)=0,"",MAX(N($AF49)/$AE$6,N($AG49)/$AE$5)) | AI49: =IF($AH49="","",IF($AH49>$AE$7,"⚠ Yfir "&TEXT($AE$7,"0%"),"OK")) | AJ49: =IF($A49<>"",$A49,AJ48) -> 46259
B50: Þriðjudagur | C50: 35 | D50: Leikskóli | E50: Sérfæði | F50: Promise - Gluten frítt dökkt brauð | G50: Glútenlaust brauð | H50: 40 | J50: =IF($F50="","",IFERROR(IFERROR(INDEX(Réttabanki!$U:$U,MATCH($F50,Réttabanki!$A:$A,0)),INDEX(Vöruskrá!$R:$R,MATCH($F50,Vöruskrá!$B:$B,0)))*($H50+IF($I50="",$H50*(1+$AD$2),$I50))/2/1000,"")) -> 30 | K50: Vatn, tapíókamjöl, hrísgrjónamjöl, þykkingarefni: sellulósi, hýdroxýprópýl metýl sellulósi, karboxýmetýl sellulósi, metýl sellulósi, xantangúmmí; heilkorna maís, kartöflusterkja, ger, psyllium hýðisduft, rakaefni; glýseról; repjuolía, hrísgrjónasterkja, síróp, maíssterkja, salt, rotvarnarefni: natríumprópíónat, sorbínsýra, brenndur sykur, vínedik. | N50: 227 | O50: 4.2 | P50: 0.4 | Q50: 39.8 | R50: 2.1 | S50: 0.9 | AF50: =IF($F50="","",IFERROR(IFERROR(INDEX(Réttabanki!$U:$U,MATCH($F50,Réttabanki!$A:$A,0)),INDEX(Vöruskrá!$R:$R,MATCH($F50,Vöruskrá!$B:$B,0)))*$H50/1000,"")) -> 24 | AG50: =IF($F50="","",IFERROR(IFERROR(INDEX(Réttabanki!$U:$U,MATCH($F50,Réttabanki!$A:$A,0)),INDEX(Vöruskrá!$R:$R,MATCH($F50,Vöruskrá!$B:$B,0)))*IF($I50="",$H50*(1+$AD$2),$I50)/1000,"")) -> 36 | AH50: =IF(N($AF50)+N($AG50)=0,"",MAX(N($AF50)/$AE$6,N($AG50)/$AE$5)) -> 0.031304348 | AI50: =IF($AH50="","",IF($AH50>$AE$7,"⚠ Yfir "&TEXT($AE$7,"0%"),"OK")) -> OK | AJ50: =IF($A50<>"",$A50,AJ49) -> 46259
B51: Þriðjudagur | C51: 35 | D51: Leikskóli | E51: Sérfæði | F51: Dönsk lifrarkæfa | G51: Lifrarkæfa | H51: 20 | J51: =IF($F51="","",IFERROR(IFERROR(INDEX(Réttabanki!$U:$U,MATCH($F51,Réttabanki!$A:$A,0)),INDEX(Vöruskrá!$R:$R,MATCH($F51,Vöruskrá!$B:$B,0)))*($H51+IF($I51="",$H51*(1+$AD$2),$I51))/2/1000,"")) -> 45 | K51: Grísalifur og kjöt 80%, vatn, laukur, salt, kartöflumjöl, **soja**prótein, krydd, vatnsrofið jurtaprótein, repjuolía, maísprótein, jurtafita (pálma), þrúgusykur, rotvarnarefni (E250), þráavarnarefni (E315, E316, E330), bindiefni (E450, E451) | L51: Soja | N51: 384 | O51: 29.3 | P51: 14.7 | Q51: 2.4 | R51: 12.8 | S51: 1.7 | AF51: =IF($F51="","",IFERROR(IFERROR(INDEX(Réttabanki!$U:$U,MATCH($F51,Réttabanki!$A:$A,0)),INDEX(Vöruskrá!$R:$R,MATCH($F51,Vöruskrá!$B:$B,0)))*$H51/1000,"")) -> 36 | AG51: =IF($F51="","",IFERROR(IFERROR(INDEX(Réttabanki!$U:$U,MATCH($F51,Réttabanki!$A:$A,0)),INDEX(Vöruskrá!$R:$R,MATCH($F51,Vöruskrá!$B:$B,0)))*IF($I51="",$H51*(1+$AD$2),$I51)/1000,"")) -> 54 | AH51: =IF(N($AF51)+N($AG51)=0,"",MAX(N($AF51)/$AE$6,N($AG51)/$AE$5)) -> 0.046956522 | AI51: =IF($AH51="","",IF($AH51>$AE$7,"⚠ Yfir "&TEXT($AE$7,"0%"),"OK")) -> OK | AJ51: =IF($A51<>"",$A51,AJ50) -> 46259
B52: Þriðjudagur | C52: 35 | F52: Leikskóli — dagskostnaður | J52: =SUMIFS($AF$3:$AF$796,$AJ$3:$AJ$796,$AJ52,$D$3:$D$796,"<>Grunnskólar starfsmenn",$E$3:$E$796,"Aðalréttur")+SUMIFS($AF$3:$AF$796,$AJ$3:$AJ$796,$AJ52,$D$3:$D$796,"<>Grunnskólar starfsmenn",$E$3:$E$796,"Meðlætisbar")+SUMIFS($AF$3:$AF$796,$AJ$3:$AJ$796,$AJ52,$D$3:$D$796,"<>Grunnskólar starfsmenn",$E$3:$E$796,"Síðdegishressing") -> 490.45 | K52: ⚠ Vara finnst ekki í Réttabanka/Vöruskrá — bætið henni við | AF52: =IF($F52="","",IFERROR(IFERROR(INDEX(Réttabanki!$U:$U,MATCH($F52,Réttabanki!$A:$A,0)),INDEX(Vöruskrá!$R:$R,MATCH($F52,Vöruskrá!$B:$B,0)))*$H52/1000,"")) | AG52: =IF($F52="","",IFERROR(IFERROR(INDEX(Réttabanki!$U:$U,MATCH($F52,Réttabanki!$A:$A,0)),INDEX(Vöruskrá!$R:$R,MATCH($F52,Vöruskrá!$B:$B,0)))*IF($I52="",$H52*(1+$AD$2),$I52)/1000,"")) | AH52: =IF($J52="","",$J52/$AE$6) -> 0.3632963 | AI52: =IF($AH52="","",IF($AH52>$AE$7,"⚠ Yfir "&TEXT($AE$7,"0%"),"OK")) -> ⚠ Yfir 30% | AJ52: =IF($A52<>"",$A52,AJ51) -> 46259
B53: Þriðjudagur | C53: 35 | F53: Grunnskóli — dagskostnaður | J53: =SUMIFS($AG$3:$AG$796,$AJ$3:$AJ$796,$AJ53,$D$3:$D$796,"<>Grunnskólar starfsmenn",$E$3:$E$796,"Aðalréttur")+SUMIFS($AG$3:$AG$796,$AJ$3:$AJ$796,$AJ53,$D$3:$D$796,"<>Grunnskólar starfsmenn",$E$3:$E$796,"Meðlætisbar") -> 615.45 | K53: ⚠ Vara finnst ekki í Réttabanka/Vöruskrá — bætið henni við | AF53: =IF($F53="","",IFERROR(IFERROR(INDEX(Réttabanki!$U:$U,MATCH($F53,Réttabanki!$A:$A,0)),INDEX(Vöruskrá!$R:$R,MATCH($F53,Vöruskrá!$B:$B,0)))*$H53/1000,"")) | AG53: =IF($F53="","",IFERROR(IFERROR(INDEX(Réttabanki!$U:$U,MATCH($F53,Réttabanki!$A:$A,0)),INDEX(Vöruskrá!$R:$R,MATCH($F53,Vöruskrá!$B:$B,0)))*IF($I53="",$H53*(1+$AD$2),$I53)/1000,"")) | AH53: =IF($J53="","",$J53/$AE$5) -> 0.53517391 | AI53: =IF($AH53="","",IF($AH53>$AE$7,"⚠ Yfir "&TEXT($AE$7,"0%"),"OK")) -> ⚠ Yfir 30% | AJ53: =IF($A53<>"",$A53,AJ52) -> 46259
A54: 46260 | B54: Miðvikudagur | C54: 35 | D54: Bæði | E54: Aðalréttur | G54: Grjónagrautur, lifrarpylsa, kanill | J54: =IF($F54="","",IFERROR(IFERROR(INDEX(Réttabanki!$U:$U,MATCH($F54,Réttabanki!$A:$A,0)),INDEX(Vöruskrá!$R:$R,MATCH($F54,Vöruskrá!$B:$B,0)))*($H54+IF($I54="",$H54*(1+$AD$2),$I54))/2/1000,"")) | K54: Nýmjólk (gerilsneydd **mjólk**, D-vítamín), vatn, hrísgrjón 12%, sykur, salt. | Lambalifur 32%, lambamör, **rúgmjöl**, **haframjöl**, vatn, salt. | Kanill 100% (Cinnamomum burmanni). | Lifur (26%); lamba-og nautalifur (upprunaland Ísland), mör, vatn, **RÚGMJÖL**, **HVEITI**, maltódextrín, **SOJAPRÓTEIN**, kartöflumjöl, **HAFRAMJÖL**, salt | L54: Mjólk, Glúten (rúgur, hafrar), Glúten (hveiti, rúgur, soja | M54: =IF(F54="","",IFERROR(IFERROR(INDEX(Réttabanki!F:F,MATCH(F54,Réttabanki!A:A,0)),""),IFERROR(IFERROR(INDEX(Vöruskrá!H:H,MATCH(F54,Vöruskrá!B:B,0)),""),""))) | N54: =IF(OR(F54="",H54=""),"",IFERROR(IFERROR(INDEX(Réttabanki!G:G,MATCH(F54,Réttabanki!A:A,0)),"")*H54/100,IFERROR(IFERROR(INDEX(Vöruskrá!J:J,MATCH(F54,Vöruskrá!B:B,0)),"")*H54/100,""))) | O54: =IF(OR(F54="",H54=""),"",IFERROR(IFERROR(INDEX(Réttabanki!H:H,MATCH(F54,Réttabanki!A:A,0)),"")*H54/100,IFERROR(IFERROR(INDEX(Vöruskrá!K:K,MATCH(F54,Vöruskrá!B:B,0)),"")*H54/100,""))) | P54: =IF(OR(F54="",H54=""),"",IFERROR(IFERROR(INDEX(Réttabanki!I:I,MATCH(F54,Réttabanki!A:A,0)),"")*H54/100,IFERROR(IFERROR(INDEX(Vöruskrá!L:L,MATCH(F54,Vöruskrá!B:B,0)),"")*H54/100,""))) | Q54: =IF(OR(F54="",H54=""),"",IFERROR(IFERROR(INDEX(Réttabanki!J:J,MATCH(F54,Réttabanki!A:A,0)),"")*H54/100,IFERROR(IFERROR(INDEX(Vöruskrá!M:M,MATCH(F54,Vöruskrá!B:B,0)),"")*H54/100,""))) | R54: =IF(OR(F54="",H54=""),"",IFERROR(IFERROR(INDEX(Réttabanki!K:K,MATCH(F54,Réttabanki!A:A,0)),"")*H54/100,IFERROR(IFERROR(INDEX(Vöruskrá!O:O,MATCH(F54,Vöruskrá!B:B,0)),"")*H54/100,""))) | S54: =IF(OR(F54="",H54=""),"",IFERROR(IFERROR(INDEX(Réttabanki!L:L,MATCH(F54,Réttabanki!A:A,0)),"")*H54/100,IFERROR(IFERROR(INDEX(Vöruskrá!P:P,MATCH(F54,Vöruskrá!B:B,0)),"")*H54/100,""))) | T54: =IF(F54="","",IFERROR(INDEX(Réttabanki!Q:Q,MATCH(F54,Réttabanki!A:A,0)),IFERROR(INDEX(Réttabanki!Q:Q,MATCH(F54,Réttabanki!B:B,0)),""))) | AF54: =IF($F54="","",IFERROR(IFERROR(INDEX(Réttabanki!$U:$U,MATCH($F54,Réttabanki!$A:$A,0)),INDEX(Vöruskrá!$R:$R,MATCH($F54,Vöruskrá!$B:$B,0)))*$H54/1000,"")) | AG54: =IF($F54="","",IFERROR(IFERROR(INDEX(Réttabanki!$U:$U,MATCH($F54,Réttabanki!$A:$A,0)),INDEX(Vöruskrá!$R:$R,MATCH($F54,Vöruskrá!$B:$B,0)))*IF($I54="",$H54*(1+$AD$2),$I54)/1000,"")) | AH54: =IF(N($AF54)+N($AG54)=0,"",MAX(N($AF54)/$AE$6,N($AG54)/$AE$5)) | AI54: =IF($AH54="","",IF($AH54>$AE$7,"⚠ Yfir "&TEXT($AE$7,"0%"),"OK")) | AJ54: =IF($A54<>"",$A54,AJ53) -> 46260
B55: Miðvikudagur | C55: 35 | D55: Bæði | E55: Aðalréttur | F55: Grjónagrautur (venjulegur) | G55: Grjónagrautur | H55: 250 | I55: 250 | J55: =IF($F55="","",IFERROR(IFERROR(INDEX(Réttabanki!$U:$U,MATCH($F55,Réttabanki!$A:$A,0)),INDEX(Vöruskrá!$R:$R,MATCH($F55,Vöruskrá!$B:$B,0)))*($H55+IF($I55="",$H55*(1+$AD$2),$I55))/2/1000,"")) -> 152.5 | K55: Nýmjólk (gerilsneydd **mjólk**, D-vítamín), vatn, hrísgrjón 12%, sykur, salt. | L55: Mjólk | N55: 48 | O55: 2 | P55: 1.1 | Q55: 5.7 | R55: 1.9 | S55: 0.1 | T55: 1 | U55: Kælt | V55: Ofn | W55: Steam 98 | X55: 50-60 | Y55: 75 | Z55: Hræra eftir helming tímans og bæta við mjólk ef grauturinn er of þykkur | AF55: =IF($F55="","",IFERROR(IFERROR(INDEX(Réttabanki!$U:$U,MATCH($F55,Réttabanki!$A:$A,0)),INDEX(Vöruskrá!$R:$R,MATCH($F55,Vöruskrá!$B:$B,0)))*$H55/1000,"")) -> 152.5 | AG55: =IF($F55="","",IFERROR(IFERROR(INDEX(Réttabanki!$U:$U,MATCH($F55,Réttabanki!$A:$A,0)),INDEX(Vöruskrá!$R:$R,MATCH($F55,Vöruskrá!$B:$B,0)))*IF($I55="",$H55*(1+$AD$2),$I55)/1000,"")) -> 152.5 | AH55: =IF(N($AF55)+N($AG55)=0,"",MAX(N($AF55)/$AE$6,N($AG55)/$AE$5)) -> 0.1326087 | AI55: =IF($AH55="","",IF($AH55>$AE$7,"⚠ Yfir "&TEXT($AE$7,"0%"),"OK")) -> OK | AJ55: =IF($A55<>"",$A55,AJ54) -> 46260
B56: Miðvikudagur | C56: 35 | D56: Bæði | E56: Aðalréttur | F56: Lifrarpylsa án mjólkur, soðin | G56: Lifrarpylsa | H56: 25 | I56: 25 | J56: =IF($F56="","",IFERROR(IFERROR(INDEX(Réttabanki!$U:$U,MATCH($F56,Réttabanki!$A:$A,0)),INDEX(Vöruskrá!$R:$R,MATCH($F56,Vöruskrá!$B:$B,0)))*($H56+IF($I56="",$H56*(1+$AD$2),$I56))/2/1000,"")) -> 45 | K56: Lambalifur 32%, lambamör, **rúgmjöl**, **haframjöl**, vatn, salt. | L56: Glúten (rúgur, hafrar) | N56: 401 | O56: 32.7 | P56: 16.6 | Q56: 15.7 | R56: 10.3 | S56: 1 | T56: =IF(F56="","",IFERROR(INDEX(Réttabanki!Q:Q,MATCH(F56,Réttabanki!A:A,0)),IFERROR(INDEX(Réttabanki!Q:Q,MATCH(F56,Réttabanki!B:B,0)),""))) | U56: Kælt | V56: Engin (kalt) | AF56: =IF($F56="","",IFERROR(IFERROR(INDEX(Réttabanki!$U:$U,MATCH($F56,Réttabanki!$A:$A,0)),INDEX(Vöruskrá!$R:$R,MATCH($F56,Vöruskrá!$B:$B,0)))*$H56/1000,"")) -> 45 | AG56: =IF($F56="","",IFERROR(IFERROR(INDEX(Réttabanki!$U:$U,MATCH($F56,Réttabanki!$A:$A,0)),INDEX(Vöruskrá!$R:$R,MATCH($F56,Vöruskrá!$B:$B,0)))*IF($I56="",$H56*(1+$AD$2),$I56)/1000,"")) -> 45 | AH56: =IF(N($AF56)+N($AG56)=0,"",MAX(N($AF56)/$AE$6,N($AG56)/$AE$5)) -> 0.039130435 | AI56: =IF($AH56="","",IF($AH56>$AE$7,"⚠ Yfir "&TEXT($AE$7,"0%"),"OK")) -> OK | AJ56: =IF($A56<>"",$A56,AJ55) -> 46260
B57: Miðvikudagur | C57: 35 | D57: Bæði | E57: Aðalréttur | F57: Kanill, malaður | G57: Kanill | H57: 5 | I57: 5 | J57: =IF($F57="","",IFERROR(IFERROR(INDEX(Réttabanki!$U:$U,MATCH($F57,Réttabanki!$A:$A,0)),INDEX(Vöruskrá!$R:$R,MATCH($F57,Vöruskrá!$B:$B,0)))*($H57+IF($I57="",$H57*(1+$AD$2),$I57))/2/1000,"")) -> 27.495 | K57: Kanill 100% (Cinnamomum burmanni). | M57: Framleitt á svæði þar sem unnið er með glúten, fisk, krabbadýr, lindýr, mjólk, soja, sellerí, sinnep og sesam. | N57: 243 | O57: 1.2 | P57: 0.4 | Q57: 81 | R57: 4 | S57: 0 | T57: =IF(F57="","",IFERROR(INDEX(Réttabanki!Q:Q,MATCH(F57,Réttabanki!A:A,0)),IFERROR(INDEX(Réttabanki!Q:Q,MATCH(F57,Réttabanki!B:B,0)),""))) | AF57: =IF($F57="","",IFERROR(IFERROR(INDEX(Réttabanki!$U:$U,MATCH($F57,Réttabanki!$A:$A,0)),INDEX(Vöruskrá!$R:$R,MATCH($F57,Vöruskrá!$B:$B,0)))*$H57/1000,"")) -> 27.495 | AG57: =IF($F57="","",IFERROR(IFERROR(INDEX(Réttabanki!$U:$U,MATCH($F57,Réttabanki!$A:$A,0)),INDEX(Vöruskrá!$R:$R,MATCH($F57,Vöruskrá!$B:$B,0)))*IF($I57="",$H57*(1+$AD$2),$I57)/1000,"")) -> 27.495 | AH57: =IF(N($AF57)+N($AG57)=0,"",MAX(N($AF57)/$AE$6,N($AG57)/$AE$5)) -> 0.023908696 | AI57: =IF($AH57="","",IF($AH57>$AE$7,"⚠ Yfir "&TEXT($AE$7,"0%"),"OK")) -> OK | AJ57: =IF($A57<>"",$A57,AJ56) -> 46260
B58: Miðvikudagur | C58: 35 | D58: Grunnskóli | E58: Aðalréttur | F58: Lifrarpylsa - SS | G58: Lifrarpylsa - SOJA | I58: 25 | J58: =IF($F58="","",IFERROR(IFERROR(INDEX(Réttabanki!$U:$U,MATCH($F58,Réttabanki!$A:$A,0)),INDEX(Vöruskrá!$R:$R,MATCH($F58,Vöruskrá!$B:$B,0)))*($H58+IF($I58="",$H58*(1+$AD$2),$I58))/2/1000,"")) -> 15 | K58: Lifur (26%); lamba-og nautalifur (upprunaland Ísland), mör, vatn, **RÚGMJÖL**, **HVEITI**, maltódextrín, **SOJAPRÓTEIN**, kartöflumjöl, **HAFRAMJÖL**, salt | L58: Glúten (hveiti, rúgur, hafrar), soja | N58: 307 | O58: 24 | P58: 12 | Q58: 15 | R58: 8.1 | S58: 1.1 | AF58: =IF($F58="","",IFERROR(IFERROR(INDEX(Réttabanki!$U:$U,MATCH($F58,Réttabanki!$A:$A,0)),INDEX(Vöruskrá!$R:$R,MATCH($F58,Vöruskrá!$B:$B,0)))*$H58/1000,"")) -> 0 | AG58: =IF($F58="","",IFERROR(IFERROR(INDEX(Réttabanki!$U:$U,MATCH($F58,Réttabanki!$A:$A,0)),INDEX(Vöruskrá!$R:$R,MATCH($F58,Vöruskrá!$B:$B,0)))*IF($I58="",$H58*(1+$AD$2),$I58)/1000,"")) -> 30 | AH58: =IF(N($AF58)+N($AG58)=0,"",MAX(N($AF58)/$AE$6,N($AG58)/$AE$5)) -> 0.026086957 | AI58: =IF($AH58="","",IF($AH58>$AE$7,"⚠ Yfir "&TEXT($AE$7,"0%"),"OK")) -> OK | AJ58: =IF($A58<>"",$A58,AJ57) -> 46260
B59: Miðvikudagur | C59: 35 | D59: Bæði | E59: Sérfæði | G59: Grjónagrautur, glútenlaust brauð, kanill | J59: =IF($F59="","",IFERROR(IFERROR(INDEX(Réttabanki!$U:$U,MATCH($F59,Réttabanki!$A:$A,0)),INDEX(Vöruskrá!$R:$R,MATCH($F59,Vöruskrá!$B:$B,0)))*($H59+IF($I59="",$H59*(1+$AD$2),$I59))/2/1000,"")) | K59: Nýmjólk (gerilsneydd **mjólk**, D-vítamín), vatn, hrísgrjón 12%, sykur, salt. | Vatn, hrísgrjónamjöl, tapíókamjöl, þykkingarefni: sellulósi, hýdroxýprópýl metýl sellulósi, karboxýmetýl sellulósi, metýl sellulósi, xantangúmmí; kartöflusterkja, psyllium hýðisduft, rakaefni: glýserín; ger, heilkorna maísmjöl, repjuolía, hrísgrjónamjöl, gullinsíróp, maíssterkja, salt, edik, rotvarnarefni: natríumprópíónat, sorbínsýra, vínedik. | Kanill 100% (Cinnamomum burmanni). | L59: Mjólk | AF59: =IF($F59="","",IFERROR(IFERROR(INDEX(Réttabanki!$U:$U,MATCH($F59,Réttabanki!$A:$A,0)),INDEX(Vöruskrá!$R:$R,MATCH($F59,Vöruskrá!$B:$B,0)))*$H59/1000,"")) | AG59: =IF($F59="","",IFERROR(IFERROR(INDEX(Réttabanki!$U:$U,MATCH($F59,Réttabanki!$A:$A,0)),INDEX(Vöruskrá!$R:$R,MATCH($F59,Vöruskrá!$B:$B,0)))*IF($I59="",$H59*(1+$AD$2),$I59)/1000,"")) | AH59: =IF(N($AF59)+N($AG59)=0,"",MAX(N($AF59)/$AE$6,N($AG59)/$AE$5)) | AI59: =IF($AH59="","",IF($AH59>$AE$7,"⚠ Yfir "&TEXT($AE$7,"0%"),"OK")) | AJ59: =IF($A59<>"",$A59,AJ58) -> 46260
B60: Miðvikudagur | C60: 35 | D60: Bæði | E60: Sérfæði | F60: Grjónagrautur (venjulegur) | G60: Grjónagrautur | H60: 250 | I60: 250 | J60: =IF($F60="","",IFERROR(IFERROR(INDEX(Réttabanki!$U:$U,MATCH($F60,Réttabanki!$A:$A,0)),INDEX(Vöruskrá!$R:$R,MATCH($F60,Vöruskrá!$B:$B,0)))*($H60+IF($I60="",$H60*(1+$AD$2),$I60))/2/1000,"")) -> 152.5 | K60: Nýmjólk (gerilsneydd **mjólk**, D-vítamín), vatn, hrísgrjón 12%, sykur, salt. | L60: Mjólk | N60: 48 | O60: 2 | P60: 1.1 | Q60: 5.7 | R60: 1.9 | S60: 0.1 | AF60: =IF($F60="","",IFERROR(IFERROR(INDEX(Réttabanki!$U:$U,MATCH($F60,Réttabanki!$A:$A,0)),INDEX(Vöruskrá!$R:$R,MATCH($F60,Vöruskrá!$B:$B,0)))*$H60/1000,"")) -> 152.5 | AG60: =IF($F60="","",IFERROR(IFERROR(INDEX(Réttabanki!$U:$U,MATCH($F60,Réttabanki!$A:$A,0)),INDEX(Vöruskrá!$R:$R,MATCH($F60,Vöruskrá!$B:$B,0)))*IF($I60="",$H60*(1+$AD$2),$I60)/1000,"")) -> 152.5 | AH60: =IF(N($AF60)+N($AG60)=0,"",MAX(N($AF60)/$AE$6,N($AG60)/$AE$5)) -> 0.1326087 | AI60: =IF($AH60="","",IF($AH60>$AE$7,"⚠ Yfir "&TEXT($AE$7,"0%"),"OK")) -> OK | AJ60: =IF($A60<>"",$A60,AJ59) -> 46260
